gdti9/wuerfel_dekoder.vhdl
library ieee;
use ieee.std_logic_1164.all;

entity wuerfel_dekoder is
  port (
    inputs : in std_logic_vector (2 downto 0);
    outputs : out std_logic_vector (6 downto 0)
  );
end wuerfel_dekoder;

architecture behav of wuerfel_dekoder is
begin
  process (inputs) begin
    case inputs is
      when "001" => outputs<="0000001";
      when "010" => outputs<="0000110";
      when "011" => outputs<="0000111";
      when "100" => outputs<="0011110";
      when "101" => outputs<="0011111";
      when "110" => outputs<="1111110";
      when others => outputs<="1111111";
    end case;
  end process;
end architecture;

gdti9/ctr_1_to_6.vhdl
library ieee;
use ieee.std_logic_1164.all;
use ieee.numeric_std.all;

entity ctr_1_to_6 is
  port (
    clk : in std_logic;
    clk_enable : in std_logic;
    ctr_value : out std_logic_vector(2 downto 0)
  );
end ctr_1_to_6;

architecture behav of ctr_1_to_6 is 
begin
    process (clk) 
        variable v_Counter : integer := 1;
    begin
        if falling_edge(clk) and clk_enable='1' then
            v_Counter := v_Counter + 1;

            if v_Counter = 7 then 
                v_Counter := 1; 
            end if;

            ctr_value <= std_logic_vector(to_unsigned(v_Counter, ctr_value'length));

        end if;
    end process;
end architecture;

gdti9/wuerfel.vhdl
library ieee;
use ieee.std_logic_1164.all;
use ieee.numeric_std.all;

entity wuerfel is
  port (
    clk : in std_logic;
    clk_enable : in std_logic;
    outputs : out std_logic_vector (6 downto 0)
  );
end wuerfel;

architecture behav of wuerfel is 
component ctr_1_to_6 is
    port (clk : in std_logic; clk_enable : in std_logic; ctr_value : out std_logic_vector(2 downto 0));
end component;
component wuerfel_dekoder is
    port (inputs : in std_logic_vector (2 downto 0); outputs : out std_logic_vector (6 downto 0));
end component;
signal s_CountValue : std_logic_vector (2 downto 0) := "001";
begin
    l_counter: ctr_1_to_6 port map(clk, clk_enable, s_CountValue);
    l_Wuerfel: wuerfel_dekoder port map(s_CountValue, outputs);
end architecture;

gdti9/wuerfel_tb.vhdl
library ieee;
use ieee.std_logic_1164.all;

entity wuerfel_tb is end wuerfel_tb;

architecture behav of wuerfel_tb is
  component wuerfel port (
    clk : in std_logic;
    clk_enable : in std_logic;
    outputs : out std_logic_vector (6 downto 0)
  ); end component;
  signal clk : std_logic;
  signal clk_enable : std_logic;
  signal outputs : std_logic_vector (6 downto 0);
begin
  wuerfel_0: wuerfel port map (clk, clk_enable, outputs);

  process
  variable st, st_expect : integer;
  begin
    clk_enable <= '1';
    clk <= '0'; wait for 1 fs;
    clk <= '1'; wait for 1 fs;
    clk <= '0'; wait for 1 fs;
    if outputs="0000001" then
      st := 1;
    elsif outputs="0000110" or outputs="0011000" then
      st := 2;
    elsif outputs="0000111" or outputs="0011001" then
      st := 3;
    elsif outputs="0011110" then
      st := 4;
    elsif outputs="0011111" then
      st := 5;
    elsif outputs="1111110" then
      st := 6;
    else
      report "Bad state after initial clk pulse" severity error;
    end if;
    --report integer'image(st);

    for n in 1 to 20 loop
      clk <= '1'; wait for 1 fs;
      clk <= '0'; wait for 1 fs;
      st_expect := st+1;  if st_expect=7 then st_expect:=1; end if;
      if outputs="0000001" then
	st := 1;
      else if outputs="0000110" or outputs="0011000" then
	st := 2;
      else if outputs="0000111" or outputs="0011001" then
	st := 3;
      else if outputs="0011110" then
	st := 4;
      else if outputs="0011111" then
	st := 5;
      else if outputs="1111110" then
	st := 6;
      else
	report "Bad state after some clk pulse" severity error;
      end if; end if; end if; end if; end if; end if;
      if st /= st_expect then
        report "did not expect that state" severity error;
      end if;
    end loop;

    clk_enable <= '0';
    for n in 1 to 20 loop
      clk <= '1'; wait for 1 fs;
      clk <= '0'; wait for 1 fs;
      if outputs="0000001" then
	st := 1;
      else if outputs="0000110" or outputs="0011000" then
	st := 2;
      else if outputs="0000111" or outputs="0011001" then
	st := 3;
      else if outputs="0011110" then
	st := 4;
      else if outputs="0011111" then
	st := 5;
      else if outputs="1111110" then
	st := 6;
      else
	report "Bad state after some clk pulse" severity error;
      end if; end if; end if; end if; end if; end if;
      if st /= st_expect then
        report "did not expect that state (clk_enable is LOW!)" severity error;
      end if;
    end loop;

    assert false report "end of test" severity note;
    wait; --  Wait forever; this will finish the simulation.
  end process;
end behav;

gdti9/out_wuerfel.vcd
$date
  Tue Jan 24 14:30:04 2023
$end
$version
  GHDL v0
$end
$timescale
  1 fs
$end
$scope module standard $end
$upscope $end
$scope module std_logic_1164 $end
$upscope $end
$scope module numeric_std $end
$upscope $end
$scope module wuerfel_tb $end
$var reg 1 ! clk $end
$var reg 1 " clk_enable $end
$var reg 7 # outputs[6:0] $end
$scope module wuerfel_0 $end
$var reg 1 $ clk $end
$var reg 1 % clk_enable $end
$var reg 7 & outputs[6:0] $end
$var reg 3 ' s_countvalue[2:0] $end
$scope module l_counter $end
$var reg 1 ( clk $end
$var reg 1 ) clk_enable $end
$var reg 3 * ctr_value[2:0] $end
$upscope $end
$scope module l_wuerfel $end
$var reg 3 + inputs[2:0] $end
$var reg 7 , outputs[6:0] $end
$upscope $end
$upscope $end
$upscope $end
$enddefinitions $end
#0
0!
1"
b1111111 #
0$
1%
b1111111 &
bUUU '
0(
1)
bUUU *
bUUU +
b1111111 ,
#1
1!
1$
1(
#2
0!
b0000110 #
0$
b0000110 &
b010 '
0(
b010 *
b010 +
b0000110 ,
#3
1!
1$
1(
#4
0!
b0000111 #
0$
b0000111 &
b011 '
0(
b011 *
b011 +
b0000111 ,
#5
1!
1$
1(
#6
0!
b0011110 #
0$
b0011110 &
b100 '
0(
b100 *
b100 +
b0011110 ,
#7
1!
1$
1(
#8
0!
b0011111 #
0$
b0011111 &
b101 '
0(
b101 *
b101 +
b0011111 ,
#9
1!
1$
1(
#10
0!
b1111110 #
0$
b1111110 &
b110 '
0(
b110 *
b110 +
b1111110 ,
#11
1!
1$
1(
#12
0!
b0000001 #
0$
b0000001 &
b001 '
0(
b001 *
b001 +
b0000001 ,
#13
1!
1$
1(
#14
0!
b0000110 #
0$
b0000110 &
b010 '
0(
b010 *
b010 +
b0000110 ,
#15
1!
1$
1(
#16
0!
b0000111 #
0$
b0000111 &
b011 '
0(
b011 *
b011 +
b0000111 ,
#17
1!
1$
1(
#18
0!
b0011110 #
0$
b0011110 &
b100 '
0(
b100 *
b100 +
b0011110 ,
#19
1!
1$
1(
#20
0!
b0011111 #
0$
b0011111 &
b101 '
0(
b101 *
b101 +
b0011111 ,
#21
1!
1$
1(
#22
0!
b1111110 #
0$
b1111110 &
b110 '
0(
b110 *
b110 +
b1111110 ,
#23
1!
1$
1(
#24
0!
b0000001 #
0$
b0000001 &
b001 '
0(
b001 *
b001 +
b0000001 ,
#25
1!
1$
1(
#26
0!
b0000110 #
0$
b0000110 &
b010 '
0(
b010 *
b010 +
b0000110 ,
#27
1!
1$
1(
#28
0!
b0000111 #
0$
b0000111 &
b011 '
0(
b011 *
b011 +
b0000111 ,
#29
1!
1$
1(
#30
0!
b0011110 #
0$
b0011110 &
b100 '
0(
b100 *
b100 +
b0011110 ,
#31
1!
1$
1(
#32
0!
b0011111 #
0$
b0011111 &
b101 '
0(
b101 *
b101 +
b0011111 ,
#33
1!
1$
1(
#34
0!
b1111110 #
0$
b1111110 &
b110 '
0(
b110 *
b110 +
b1111110 ,
#35
1!
1$
1(
#36
0!
b0000001 #
0$
b0000001 &
b001 '
0(
b001 *
b001 +
b0000001 ,
#37
1!
1$
1(
#38
0!
b0000110 #
0$
b0000110 &
b010 '
0(
b010 *
b010 +
b0000110 ,
#39
1!
1$
1(
#40
0!
b0000111 #
0$
b0000111 &
b011 '
0(
b011 *
b011 +
b0000111 ,
#41
1!
1$
1(
#42
0!
b0011110 #
0$
b0011110 &
b100 '
0(
b100 *
b100 +
b0011110 ,
