gdti9/ctr_1_to_6.vhdl
library ieee;
use ieee.std_logic_1164.all;
use ieee.numeric_std.all;

entity ctr_1_to_6 is
  port (
    clk : in std_logic;
    clk_enable : in std_logic;
    ctr_value : out std_logic_vector(2 downto 0)
  );
end ctr_1_to_6;

architecture behav of ctr_1_to_6 is 
begin
    process (clk) 
        variable v_Counter : integer := 1;
    begin
        if falling_edge(clk) and clk_enable='1' then
            v_Counter := v_Counter + 1;

            if v_Counter = 7 then 
                v_Counter := 1; 
            end if;

            ctr_value <= std_logic_vector(to_unsigned(v_Counter, ctr_value'length));

        end if;
    end process;
end architecture;

gdti9/ctr_1_to_6_tb.vhdl
library ieee;
use ieee.std_logic_1164.all;
use ieee.numeric_std.all;

entity ctr_1_to_6_tb is end ctr_1_to_6_tb;

architecture behav of ctr_1_to_6_tb is
  component ctr_1_to_6 is
    port (
      clk : in std_logic;
      clk_enable : in std_logic;
      ctr_value : out std_logic_vector(2 downto 0)
    );
  end component;
  signal clk : std_logic;
  signal clk_enable : std_logic;
  signal ctr_value : std_logic_vector(2 downto 0);
begin
  the_instance: ctr_1_to_6 port map (clk, clk_enable, ctr_value);

  process
  variable expect : integer;
  begin
    -- initialise ctr
    clk_enable <= '1';
    clk <= '0'; wait for 1 fs;
    clk <= '1'; wait for 1 fs;
    clk <= '0'; wait for 1 fs;
    expect := to_integer(unsigned(ctr_value));
    if (expect < 1) or (6 < expect) then
      report "ctr not in range 1..6 after first clk" severity error;
    end if;
    -- now do 20 clk ticks and look for proper counting
    for n in 1 to 20 loop
      clk <= '1'; wait for 1 fs;
      if expect < 6 then
        expect := expect + 1;
      else
        expect := 1;
      end if;
      clk <= '0'; wait for 1 fs;
      -- report integer'image(n) & " " & integer'image(expect);
      if expect /= to_integer(unsigned(ctr_value)) then
        report "ctr not doing cycle 1..6" severity error;
      end if;
    end loop;
    -- now do 20 clk ticks and look for no counting
    clk_enable <= '0';
    for n in 1 to 20 loop
      clk <= '1'; wait for 1 fs;
      clk <= '0'; wait for 1 fs;
      -- report integer'image(n) & " " & integer'image(expect);
      if expect /= to_integer(unsigned(ctr_value)) then
        report "ctr not stable while clk_enable is 0" severity error;
      end if;
    end loop;
    report "end of test." severity note;
    wait; --  Wait forever; this will finish the simulation.
  end process;
end behav;

gdti9/out_ctr_1_to_6.vcd
$date
  Tue Jan 24 14:29:42 2023
$end
$version
  GHDL v0
$end
$timescale
  1 fs
$end
$scope module standard $end
$upscope $end
$scope module std_logic_1164 $end
$upscope $end
$scope module numeric_std $end
$upscope $end
$scope module ctr_1_to_6_tb $end
$var reg 1 ! clk $end
$var reg 1 " clk_enable $end
$var reg 3 # ctr_value[2:0] $end
$scope module the_instance $end
$var reg 1 $ clk $end
$var reg 1 % clk_enable $end
$var reg 3 & ctr_value[2:0] $end
$upscope $end
$upscope $end
$enddefinitions $end
#0
0!
1"
bUUU #
0$
1%
bUUU &
#1
1!
1$
#2
0!
b010 #
0$
b010 &
#3
1!
1$
#4
0!
b011 #
0$
b011 &
#5
1!
1$
#6
0!
b100 #
0$
b100 &
#7
1!
1$
#8
0!
b101 #
0$
b101 &
#9
1!
1$
#10
0!
b110 #
0$
b110 &
#11
1!
1$
#12
0!
b001 #
0$
b001 &
#13
1!
1$
#14
0!
b010 #
0$
b010 &
#15
1!
1$
#16
0!
b011 #
0$
b011 &
#17
1!
1$
#18
0!
b100 #
0$
b100 &
#19
1!
1$
#20
0!
b101 #
0$
b101 &
#21
1!
1$
#22
0!
b110 #
0$
b110 &
#23
1!
1$
#24
0!
b001 #
0$
b001 &
#25
1!
1$
#26
0!
b010 #
0$
b010 &
#27
1!
1$
#28
0!
b011 #
0$
b011 &
#29
1!
1$
#30
0!
b100 #
0$
b100 &
#31
1!
1$
#32
0!
b101 #
0$
b101 &
#33
1!
1$
#34
0!
b110 #
0$
b110 &
#35
1!
1$
#36
0!
b001 #
0$
b001 &
#37
1!
1$
#38
0!
b010 #
0$
b010 &
#39
1!
1$
#40
0!
b011 #
0$
b011 &
#41
1!
1$
#42
0!
b100 #
0$
b100 &
