gdti10/key.vhdl
library ieee;
use ieee.std_logic_1164.all;

entity key is
  port (
    clk : in std_logic;
    echte_taste : in std_logic;
    taste_wurde_gedrueckt : out std_logic
  );
end key;

architecture behav of key is
  signal last_key : std_logic := '0';
begin
  process (clk) begin
    if rising_edge(clk) then
      
      taste_wurde_gedrueckt <= (not last_key) and echte_taste;
      last_key <= echte_taste;

    end if;
  end process;
end architecture;

gdti10/schloss.vhdl
library ieee;
use ieee.std_logic_1164.all;
use ieee.numeric_std.all;

entity schloss is
  port (
    clk : in std_logic;
    echte_tasten : in std_logic_vector(1 to 3);
    echte_taste_reset : in std_logic;
    offen : out std_logic
  );
end schloss;

architecture behav of schloss is
  component key is port (
    clk : in std_logic;
    echte_taste : in std_logic;
    taste_wurde_gedrueckt : out std_logic
  ); end component;

  signal s_key_pressed : std_logic_vector(1 to 3) := "000";
  signal s_reset_pressed : std_logic := '0';
  begin
    l_key_1: key port map(clk, echte_tasten(1), s_key_pressed(1));
    l_key_2: key port map(clk, echte_tasten(2), s_key_pressed(2));
    l_key_3: key port map(clk, echte_tasten(3), s_key_pressed(3));
    l_key_reset: key port map(clk, echte_taste_reset, s_reset_pressed);
    
    process (clk) 
      variable v_state : integer := 1;
    begin
    if rising_edge(clk) then

        case v_state is
          when 1 => 
          if s_key_pressed(1) = '1' then v_state := 2; end if;
          if s_key_pressed(2) = '1' then v_state := 4; end if;
          if s_key_pressed(3) = '1' then v_state := 4; end if;
          when 2 => 
          if s_key_pressed(2) = '1' then v_state := 3; end if;
          if s_key_pressed(1) = '1' then v_state := 4; end if;
          if s_key_pressed(3) = '1' then v_state := 4; end if;
          when 3 => 
          if s_key_pressed(3) = '1' then v_state := 5; end if;
          if s_key_pressed(1) = '1' then v_state := 4; end if;
          if s_key_pressed(2) = '1' then v_state := 4; end if;
          when 4 =>
            if s_reset_pressed = '1' then
              offen <= '0';
              v_state := 1;
            end if;
          when 5 =>
            offen <= '1';
          if s_reset_pressed = '1' then
            offen <= '0';
            v_state := 1;
          end if;
          when others =>
        end case;

    end if;
  end process;
end architecture;

gdti10/schloss_tb.vhdl
library ieee;
use ieee.std_logic_1164.all;

entity schloss_tb is end schloss_tb;

architecture behav of schloss_tb is
  component schloss is port (
    clk : in std_logic;
    echte_tasten : in std_logic_vector(1 to 3);
    echte_taste_reset : in std_logic;
    offen : out std_logic
  ); end component;
  signal clk : std_logic;
  signal echte_tasten : std_logic_vector(1 to 3);
  signal echte_taste_reset : std_logic;
  signal offen : std_logic;
begin
  schloss_instance: schloss port map(clk, echte_tasten, echte_taste_reset, offen);

  process
    variable i : integer := 0;
    variable t1,t2,t3,t4 : integer;
    variable ok : integer := -1;
  begin
    echte_tasten <= "000";  echte_taste_reset <= '0';
    clk<='0'; wait for 1 fs;

    while i < 3*3*3*3 loop
      t4 := 1 + (i mod 3);
      t3 := 1 + ((i / 3) mod 3);
      t2 := 1 + ((i / 9) mod 3);
      t1 := 1 + ((i / 27));
      i := i + 1;
      --report integer'image(t1) & "-" & integer'image(t2) & "-" & integer'image(t3) & "-" & integer'image(t4);
      echte_tasten <= "000";
      echte_taste_reset <= '0';
                     wait for 1 fs;
                     clk<='1'; wait for 2 fs; clk<='0'; wait for 2 fs;
                     clk<='1'; wait for 2 fs; clk<='0'; wait for 2 fs;
                     clk<='1'; wait for 2 fs; clk<='0'; wait for 1 fs; 
      -- ein mal reset druecken
      report "Drücke Taste 'reset'";
      echte_taste_reset <= '1';
                     wait for 1 fs;
                     clk<='1'; wait for 2 fs; clk<='0'; wait for 2 fs;
                     clk<='1'; wait for 2 fs; clk<='0'; wait for 2 fs;
                     clk<='1'; wait for 2 fs; clk<='0'; wait for 1 fs; 
      echte_taste_reset <= '0';
                     wait for 1 fs;
                     clk<='1'; wait for 2 fs; clk<='0'; wait for 2 fs;
                     clk<='1'; wait for 2 fs; clk<='0'; wait for 2 fs;
                     clk<='1'; wait for 2 fs; clk<='0'; wait for 1 fs; 
      if offen='1' then report "Schloss offen nach (nur!) 'reset'" severity failure; end if;
      -- erste taste druecken
      report "Drücke Taste '"&integer'image(t1)&"'";
      echte_tasten(t1)<='1';
                     wait for 1 fs;
                     clk<='1'; wait for 2 fs; clk<='0'; wait for 2 fs;
                     clk<='1'; wait for 2 fs; clk<='0'; wait for 2 fs;
                     clk<='1'; wait for 2 fs; clk<='0'; wait for 1 fs; 
      echte_tasten(t1)<='0';
                     wait for 1 fs;
                     clk<='1'; wait for 2 fs; clk<='0'; wait for 2 fs;
                     clk<='1'; wait for 2 fs; clk<='0'; wait for 2 fs;
                     clk<='1'; wait for 2 fs; clk<='0'; wait for 1 fs; 
      if offen='1' then report "Schloss offen nach 'reset' und nur einer weiteren Taste?!?" severity failure; end if;
      -- zweite taste druecken
      report "Drücke Taste '"&integer'image(t2)&"'";
      echte_tasten(t2)<='1';
                     wait for 1 fs;
                     clk<='1'; wait for 2 fs; clk<='0'; wait for 2 fs;
                     clk<='1'; wait for 2 fs; clk<='0'; wait for 2 fs;
                     clk<='1'; wait for 2 fs; clk<='0'; wait for 1 fs; 
      echte_tasten(t2)<='0';
                     wait for 1 fs;
                     clk<='1'; wait for 2 fs; clk<='0'; wait for 2 fs;
                     clk<='1'; wait for 2 fs; clk<='0'; wait for 2 fs;
                     clk<='1'; wait for 2 fs; clk<='0'; wait for 1 fs; 
      if offen='1' then report "Schloss offen nach 'reset' und nur zwei weiteren Tasten?!?" severity failure; end if;
      -- dritte taste druecken
      report "Drücke Taste '"&integer'image(t3)&"'";
      echte_tasten(t3)<='1';
                     wait for 1 fs;
                     clk<='1'; wait for 2 fs; clk<='0'; wait for 2 fs;
                     clk<='1'; wait for 2 fs; clk<='0'; wait for 2 fs;
                     clk<='1'; wait for 2 fs; clk<='0'; wait for 1 fs; 
      echte_tasten(t3)<='0';
                     wait for 1 fs;
                     clk<='1'; wait for 2 fs; clk<='0'; wait for 2 fs;
                     clk<='1'; wait for 2 fs; clk<='0'; wait for 2 fs;
                     clk<='1'; wait for 2 fs; clk<='0'; wait for 1 fs; 
      if offen='1' then
        if ok=-1 then
          report "Schloss offen nach 'reset' und " & integer'image(t1) & "-" & integer'image(t2) & "-" & integer'image(t3);
          ok := i;
          i := i + 2; -- skip pressing fourth key at all
        else
	  t3 := 1 + ((ok / 3) mod 3);
	  t2 := 1 + ((ok / 9) mod 3);
	  t1 := 1 + ((ok / 27));
          report "Aber es war doch mit dem code 'reset' und " & integer'image(t1) & "-" & integer'image(t2) & "-" & integer'image(t3) & " auch schon offen ?!?" severity failure;
        end if;
      else
	-- vierte taste druecken
	report "Drücke Taste '"&integer'image(t4)&"'";
	echte_tasten(t4)<='1';
		       wait for 1 fs;
		       clk<='1'; wait for 2 fs; clk<='0'; wait for 2 fs;
		       clk<='1'; wait for 2 fs; clk<='0'; wait for 2 fs;
		       clk<='1'; wait for 2 fs; clk<='0'; wait for 1 fs; 
	echte_tasten(t4)<='0';
		       wait for 1 fs;
		       clk<='1'; wait for 2 fs; clk<='0'; wait for 2 fs;
		       clk<='1'; wait for 2 fs; clk<='0'; wait for 2 fs;
		       clk<='1'; wait for 2 fs; clk<='0'; wait for 1 fs; 
	if offen='1' then report "Schloss offen nach 'reset' und vier weiteren Tasten?!?" severity failure; end if;
      end if;

    end loop;
    t3 := 1 + ((ok / 3) mod 3);
    t2 := 1 + ((ok / 9) mod 3);
    t1 := 1 + ((ok / 27));
    report "=====> Einziger gefundener gueltiger code ist 'reset-"
         & integer'image(t1) & "-" & integer'image(t2) & "-" & integer'image(t3) & "'";
    report "=====> Test bestanden";
    report "end of test";
    wait;

  end process;
end architecture;

gdti10/out_schloss.vcd
$date
  Tue Jan 31 14:49:03 2023
$end
$version
  GHDL v0
$end
$timescale
  1 fs
$end
$scope module standard $end
$upscope $end
$scope module std_logic_1164 $end
$upscope $end
$scope module numeric_std $end
$upscope $end
$scope module schloss_tb $end
$var reg 1 ! clk $end
$var reg 3 " echte_tasten[1:3] $end
$var reg 1 # echte_taste_reset $end
$var reg 1 $ offen $end
$scope module schloss_instance $end
$var reg 1 % clk $end
$var reg 3 & echte_tasten[1:3] $end
$var reg 1 ' echte_taste_reset $end
$var reg 1 ( offen $end
$var reg 3 ) s_key_pressed[1:3] $end
$var reg 1 * s_reset_pressed $end
$scope module l_key_1 $end
$var reg 1 + clk $end
$var reg 1 , echte_taste $end
$var reg 1 - taste_wurde_gedrueckt $end
$var reg 1 . last_key $end
$upscope $end
$scope module l_key_2 $end
$var reg 1 / clk $end
$var reg 1 0 echte_taste $end
$var reg 1 1 taste_wurde_gedrueckt $end
$var reg 1 2 last_key $end
$upscope $end
$scope module l_key_3 $end
$var reg 1 3 clk $end
$var reg 1 4 echte_taste $end
$var reg 1 5 taste_wurde_gedrueckt $end
$var reg 1 6 last_key $end
$upscope $end
$scope module l_key_reset $end
$var reg 1 7 clk $end
$var reg 1 8 echte_taste $end
$var reg 1 9 taste_wurde_gedrueckt $end
$var reg 1 : last_key $end
$upscope $end
$upscope $end
$upscope $end
$enddefinitions $end
#0
0!
b000 "
0#
U$
0%
b000 &
0'
U(
bUUU )
U*
0+
0,
U-
0.
0/
00
U1
02
03
04
U5
06
07
08
U9
0:
#1
#2
1!
1%
b000 )
0*
1+
0-
1/
01
13
05
17
09
#4
0!
0%
0+
0/
03
07
#6
1!
1%
1+
1/
13
17
#8
0!
0%
0+
0/
03
07
#10
1!
1%
1+
1/
13
17
#12
0!
0%
0+
0/
03
07
#13
1#
1'
18
#14
1!
1%
1*
1+
1/
13
17
19
1:
#16
0!
0%
0+
0/
03
07
#18
1!
1%
0*
1+
1/
13
17
09
#20
0!
0%
0+
0/
03
07
#22
1!
1%
1+
1/
13
17
#24
0!
0%
0+
0/
03
07
#25
0#
0'
08
#26
1!
1%
1+
1/
13
17
0:
#28
0!
0%
0+
0/
03
07
#30
1!
1%
1+
1/
13
17
#32
0!
0%
0+
0/
03
07
#34
1!
1%
1+
1/
13
17
#36
0!
0%
0+
0/
03
07
#37
b100 "
b100 &
1,
#38
1!
1%
b100 )
1+
1-
1.
1/
13
17
#40
0!
0%
0+
0/
03
07
#42
1!
1%
b000 )
1+
0-
1/
13
17
#44
0!
0%
0+
0/
03
07
#46
1!
1%
1+
1/
13
17
#48
0!
0%
0+
0/
03
07
#49
b000 "
b000 &
0,
#50
1!
1%
1+
0.
1/
13
17
#52
0!
0%
0+
0/
03
07
#54
1!
1%
1+
1/
13
17
#56
0!
0%
0+
0/
03
07
#58
1!
1%
1+
1/
13
17
#60
0!
0%
0+
0/
03
07
#61
b100 "
b100 &
1,
#62
1!
1%
b100 )
1+
1-
1.
1/
13
17
#64
0!
0%
0+
0/
03
07
#66
1!
1%
b000 )
1+
0-
1/
13
17
#68
0!
0%
0+
0/
03
07
#70
1!
1%
1+
1/
13
17
#72
0!
0%
0+
0/
03
07
#73
b000 "
b000 &
0,
#74
1!
1%
1+
0.
1/
13
17
#76
0!
0%
0+
0/
03
07
#78
1!
1%
1+
1/
13
17
#80
0!
0%
0+
0/
03
07
#82
1!
1%
1+
1/
13
17
#84
0!
0%
0+
0/
03
07
#85
b100 "
b100 &
1,
#86
1!
1%
b100 )
1+
1-
1.
1/
13
17
#88
0!
0%
0+
0/
03
07
#90
1!
1%
b000 )
1+
0-
1/
13
17
#92
0!
0%
0+
0/
03
07
#94
1!
1%
1+
1/
13
17
#96
0!
0%
0+
0/
03
07
#97
b000 "
b000 &
0,
#98
1!
1%
1+
0.
1/
13
17
#100
0!
0%
0+
0/
03
07
#102
1!
1%
1+
1/
13
17
#104
0!
0%
0+
0/
03
07
#106
1!
1%
1+
1/
13
17
#108
0!
0%
0+
0/
03
07
#109
b100 "
b100 &
1,
#110
1!
1%
b100 )
1+
1-
1.
1/
13
17
#112
0!
0%
0+
0/
03
07
#114
1!
1%
b000 )
1+
0-
1/
13
17
#116
0!
0%
0+
0/
03
07
#118
1!
1%
1+
1/
13
17
#120
0!
0%
0+
0/
03
07
#121
b000 "
b000 &
0,
#122
1!
1%
1+
0.
1/
13
17
#124
0!
0%
0+
0/
03
07
#126
1!
1%
1+
1/
13
17
#128
0!
0%
0+
0/
03
07
#130
1!
1%
1+
1/
13
17
#132
0!
0%
0+
0/
03
07
#133
#134
1!
1%
1+
1/
13
17
#136
0!
0%
0+
0/
03
07
#138
1!
1%
1+
1/
13
17
#140
0!
0%
0+
0/
03
07
#142
1!
1%
1+
1/
13
17
#144
0!
0%
0+
0/
03
07
#145
1#
1'
18
#146
1!
1%
1*
1+
1/
13
17
19
1:
#148
0!
0%
0+
0/
03
07
#150
1!
0$
1%
0(
0*
1+
1/
13
17
09
#152
0!
0%
0+
0/
03
07
#154
1!
1%
1+
1/
13
17
#156
0!
0%
0+
0/
03
07
#157
0#
0'
08
#158
1!
1%
1+
1/
13
17
0:
#160
0!
0%
0+
0/
03
07
#162
1!
1%
1+
1/
13
17
#164
0!
0%
0+
0/
03
07
#166
1!
1%
1+
1/
13
17
#168
0!
0%
0+
0/
03
07
#169
b100 "
b100 &
1,
#170
1!
1%
b100 )
1+
1-
1.
1/
13
17
#172
0!
0%
0+
0/
03
07
#174
1!
1%
b000 )
1+
0-
1/
13
17
#176
0!
0%
0+
0/
03
07
#178
1!
1%
1+
1/
13
17
#180
0!
0%
0+
0/
03
07
#181
b000 "
b000 &
0,
#182
1!
1%
1+
0.
1/
13
17
#184
0!
0%
0+
0/
03
07
#186
1!
1%
1+
1/
13
17
#188
0!
0%
0+
0/
03
07
#190
1!
1%
1+
1/
13
17
#192
0!
0%
0+
0/
03
07
#193
b100 "
b100 &
1,
#194
1!
1%
b100 )
1+
1-
1.
1/
13
17
#196
0!
0%
0+
0/
03
07
#198
1!
1%
b000 )
1+
0-
1/
13
17
#200
0!
0%
0+
0/
03
07
#202
1!
1%
1+
1/
13
17
#204
0!
0%
0+
0/
03
07
#205
b000 "
b000 &
0,
#206
1!
1%
1+
0.
1/
13
17
#208
0!
0%
0+
0/
03
07
#210
1!
1%
1+
1/
13
17
#212
0!
0%
0+
0/
03
07
#214
1!
1%
1+
1/
13
17
#216
0!
0%
0+
0/
03
07
#217
b100 "
b100 &
1,
#218
1!
1%
b100 )
1+
1-
1.
1/
13
17
#220
0!
0%
0+
0/
03
07
#222
1!
1%
b000 )
1+
0-
1/
13
17
#224
0!
0%
0+
0/
03
07
#226
1!
1%
1+
1/
13
17
#228
0!
0%
0+
0/
03
07
#229
b000 "
b000 &
0,
#230
1!
1%
1+
0.
1/
13
17
#232
0!
0%
0+
0/
03
07
#234
1!
1%
1+
1/
13
17
#236
0!
0%
0+
0/
03
07
#238
1!
1%
1+
1/
13
17
#240
0!
0%
0+
0/
03
07
#241
b010 "
b010 &
10
#242
1!
1%
b010 )
1+
1/
11
12
13
17
#244
0!
0%
0+
0/
03
07
#246
1!
1%
b000 )
1+
1/
01
13
17
#248
0!
0%
0+
0/
03
07
#250
1!
1%
1+
1/
13
17
#252
0!
0%
0+
0/
03
07
#253
b000 "
b000 &
00
#254
1!
1%
1+
1/
02
13
17
#256
0!
0%
0+
0/
03
07
#258
1!
1%
1+
1/
13
17
#260
0!
0%
0+
0/
03
07
#262
1!
1%
1+
1/
13
17
#264
0!
0%
0+
0/
03
07
#265
#266
1!
1%
1+
1/
13
17
#268
0!
0%
0+
0/
03
07
#270
1!
1%
1+
1/
13
17
#272
0!
0%
0+
0/
03
07
#274
1!
1%
1+
1/
13
17
#276
0!
0%
0+
0/
03
07
#277
1#
1'
18
#278
1!
1%
1*
1+
1/
13
17
19
1:
#280
0!
0%
0+
0/
03
07
#282
1!
1%
0*
1+
1/
13
17
09
#284
0!
0%
0+
0/
03
07
#286
1!
1%
1+
1/
13
17
#288
0!
0%
0+
0/
03
07
#289
0#
0'
08
#290
1!
1%
1+
1/
13
17
0:
#292
0!
0%
0+
0/
03
07
#294
1!
1%
1+
1/
13
17
#296
0!
0%
0+
0/
03
07
#298
1!
1%
1+
1/
13
17
#300
0!
0%
0+
0/
03
07
#301
b100 "
b100 &
1,
#302
1!
1%
b100 )
1+
1-
1.
1/
13
17
#304
0!
0%
0+
0/
03
07
#306
1!
1%
b000 )
1+
0-
1/
13
17
#308
0!
0%
0+
0/
03
07
#310
1!
1%
1+
1/
13
17
#312
0!
0%
0+
0/
03
07
#313
b000 "
b000 &
0,
#314
1!
1%
1+
0.
1/
13
17
#316
0!
0%
0+
0/
03
07
#318
1!
1%
1+
1/
13
17
#320
0!
0%
0+
0/
03
07
#322
1!
1%
1+
1/
13
17
#324
0!
0%
0+
0/
03
07
#325
b100 "
b100 &
1,
#326
1!
1%
b100 )
1+
1-
1.
1/
13
17
#328
0!
0%
0+
0/
03
07
#330
1!
1%
b000 )
1+
0-
1/
13
17
#332
0!
0%
0+
0/
03
07
#334
1!
1%
1+
1/
13
17
#336
0!
0%
0+
0/
03
07
#337
b000 "
b000 &
0,
#338
1!
1%
1+
0.
1/
13
17
#340
0!
0%
0+
0/
03
07
#342
1!
1%
1+
1/
13
17
#344
0!
0%
0+
0/
03
07
#346
1!
1%
1+
1/
13
17
#348
0!
0%
0+
0/
03
07
#349
b100 "
b100 &
1,
#350
1!
1%
b100 )
1+
1-
1.
1/
13
17
#352
0!
0%
0+
0/
03
07
#354
1!
1%
b000 )
1+
0-
1/
13
17
#356
0!
0%
0+
0/
03
07
#358
1!
1%
1+
1/
13
17
#360
0!
0%
0+
0/
03
07
#361
b000 "
b000 &
0,
#362
1!
1%
1+
0.
1/
13
17
#364
0!
0%
0+
0/
03
07
#366
1!
1%
1+
1/
13
17
#368
0!
0%
0+
0/
03
07
#370
1!
1%
1+
1/
13
17
#372
0!
0%
0+
0/
03
07
#373
b001 "
b001 &
14
#374
1!
1%
b001 )
1+
1/
13
15
16
17
#376
0!
0%
0+
0/
03
07
#378
1!
1%
b000 )
1+
1/
13
05
17
#380
0!
0%
0+
0/
03
07
#382
1!
1%
1+
1/
13
17
#384
0!
0%
0+
0/
03
07
#385
b000 "
b000 &
04
#386
1!
1%
1+
1/
13
06
17
#388
0!
0%
0+
0/
03
07
#390
1!
1%
1+
1/
13
17
#392
0!
0%
0+
0/
03
07
#394
1!
1%
1+
1/
13
17
#396
0!
0%
0+
0/
03
07
#397
#398
1!
1%
1+
1/
13
17
#400
0!
0%
0+
0/
03
07
#402
1!
1%
1+
1/
13
17
#404
0!
0%
0+
0/
03
07
#406
1!
1%
1+
1/
13
17
#408
0!
0%
0+
0/
03
07
#409
1#
1'
18
#410
1!
1%
1*
1+
1/
13
17
19
1:
#412
0!
0%
0+
0/
03
07
#414
1!
1%
0*
1+
1/
13
17
09
#416
0!
0%
0+
0/
03
07
#418
1!
1%
1+
1/
13
17
#420
0!
0%
0+
0/
03
07
#421
0#
0'
08
#422
1!
1%
1+
1/
13
17
0:
#424
0!
0%
0+
0/
03
07
#426
1!
1%
1+
1/
13
17
#428
0!
0%
0+
0/
03
07
#430
1!
1%
1+
1/
13
17
#432
0!
0%
0+
0/
03
07
#433
b100 "
b100 &
1,
#434
1!
1%
b100 )
1+
1-
1.
1/
13
17
#436
0!
0%
0+
0/
03
07
#438
1!
1%
b000 )
1+
0-
1/
13
17
#440
0!
0%
0+
0/
03
07
#442
1!
1%
1+
1/
13
17
#444
0!
0%
0+
0/
03
07
#445
b000 "
b000 &
0,
#446
1!
1%
1+
0.
1/
13
17
#448
0!
0%
0+
0/
03
07
#450
1!
1%
1+
1/
13
17
#452
0!
0%
0+
0/
03
07
#454
1!
1%
1+
1/
13
17
#456
0!
0%
0+
0/
03
07
#457
b100 "
b100 &
1,
#458
1!
1%
b100 )
1+
1-
1.
1/
13
17
#460
0!
0%
0+
0/
03
07
#462
1!
1%
b000 )
1+
0-
1/
13
17
#464
0!
0%
0+
0/
03
07
#466
1!
1%
1+
1/
13
17
#468
0!
0%
0+
0/
03
07
#469
b000 "
b000 &
0,
#470
1!
1%
1+
0.
1/
13
17
#472
0!
0%
0+
0/
03
07
#474
1!
1%
1+
1/
13
17
#476
0!
0%
0+
0/
03
07
#478
1!
1%
1+
1/
13
17
#480
0!
0%
0+
0/
03
07
#481
b010 "
b010 &
10
#482
1!
1%
b010 )
1+
1/
11
12
13
17
#484
0!
0%
0+
0/
03
07
#486
1!
1%
b000 )
1+
1/
01
13
17
#488
0!
0%
0+
0/
03
07
#490
1!
1%
1+
1/
13
17
#492
0!
0%
0+
0/
03
07
#493
b000 "
b000 &
00
#494
1!
1%
1+
1/
02
13
17
#496
0!
0%
0+
0/
03
07
#498
1!
1%
1+
1/
13
17
#500
0!
0%
0+
0/
03
07
#502
1!
1%
1+
1/
13
17
#504
0!
0%
0+
0/
03
07
#505
b100 "
b100 &
1,
#506
1!
1%
b100 )
1+
1-
1.
1/
13
17
#508
0!
0%
0+
0/
03
07
#510
1!
1%
b000 )
1+
0-
1/
13
17
#512
0!
0%
0+
0/
03
07
#514
1!
1%
1+
1/
13
17
#516
0!
0%
0+
0/
03
07
#517
b000 "
b000 &
0,
#518
1!
1%
1+
0.
1/
13
17
#520
0!
0%
0+
0/
03
07
#522
1!
1%
1+
1/
13
17
#524
0!
0%
0+
0/
03
07
#526
1!
1%
1+
1/
13
17
#528
0!
0%
0+
0/
03
07
#529
#530
1!
1%
1+
1/
13
17
#532
0!
0%
0+
0/
03
07
#534
1!
1%
1+
1/
13
17
#536
0!
0%
0+
0/
03
07
#538
1!
1%
1+
1/
13
17
#540
0!
0%
0+
0/
03
07
#541
1#
1'
18
#542
1!
1%
1*
1+
1/
13
17
19
1:
#544
0!
0%
0+
0/
03
07
#546
1!
1%
0*
1+
1/
13
17
09
#548
0!
0%
0+
0/
03
07
#550
1!
1%
1+
1/
13
17
#552
0!
0%
0+
0/
03
07
#553
0#
0'
08
#554
1!
1%
1+
1/
13
17
0:
#556
0!
0%
0+
0/
03
07
#558
1!
1%
1+
1/
13
17
#560
0!
0%
0+
0/
03
07
#562
1!
1%
1+
1/
13
17
#564
0!
0%
0+
0/
03
07
#565
b100 "
b100 &
1,
#566
1!
1%
b100 )
1+
1-
1.
1/
13
17
#568
0!
0%
0+
0/
03
07
#570
1!
1%
b000 )
1+
0-
1/
13
17
#572
0!
0%
0+
0/
03
07
#574
1!
1%
1+
1/
13
17
#576
0!
0%
0+
0/
03
07
#577
b000 "
b000 &
0,
#578
1!
1%
1+
0.
1/
13
17
#580
0!
0%
0+
0/
03
07
#582
1!
1%
1+
1/
13
17
#584
0!
0%
0+
0/
03
07
#586
1!
1%
1+
1/
13
17
#588
0!
0%
0+
0/
03
07
#589
b100 "
b100 &
1,
#590
1!
1%
b100 )
1+
1-
1.
1/
13
17
#592
0!
0%
0+
0/
03
07
#594
1!
1%
b000 )
1+
0-
1/
13
17
#596
0!
0%
0+
0/
03
07
#598
1!
1%
1+
1/
13
17
#600
0!
0%
0+
0/
03
07
#601
b000 "
b000 &
0,
#602
1!
1%
1+
0.
1/
13
17
#604
0!
0%
0+
0/
03
07
#606
1!
1%
1+
1/
13
17
#608
0!
0%
0+
0/
03
07
#610
1!
1%
1+
1/
13
17
#612
0!
0%
0+
0/
03
07
#613
b010 "
b010 &
10
#614
1!
1%
b010 )
1+
1/
11
12
13
17
#616
0!
0%
0+
0/
03
07
#618
1!
1%
b000 )
1+
1/
01
13
17
#620
0!
0%
0+
0/
03
07
#622
1!
1%
1+
1/
13
17
#624
0!
0%
0+
0/
03
07
#625
b000 "
b000 &
00
#626
1!
1%
1+
1/
02
13
17
#628
0!
0%
0+
0/
03
07
#630
1!
1%
1+
1/
13
17
#632
0!
0%
0+
0/
03
07
#634
1!
1%
1+
1/
13
17
#636
0!
0%
0+
0/
03
07
#637
b010 "
b010 &
10
#638
1!
1%
b010 )
1+
1/
11
12
13
17
#640
0!
0%
0+
0/
03
07
#642
1!
1%
b000 )
1+
1/
01
13
17
#644
0!
0%
0+
0/
03
07
#646
1!
1%
1+
1/
13
17
#648
0!
0%
0+
0/
03
07
#649
b000 "
b000 &
00
#650
1!
1%
1+
1/
02
13
17
#652
0!
0%
0+
0/
03
07
#654
1!
1%
1+
1/
13
17
#656
0!
0%
0+
0/
03
07
#658
1!
1%
1+
1/
13
17
#660
0!
0%
0+
0/
03
07
#661
#662
1!
1%
1+
1/
13
17
#664
0!
0%
0+
0/
03
07
#666
1!
1%
1+
1/
13
17
#668
0!
0%
0+
0/
03
07
#670
1!
1%
1+
1/
13
17
#672
0!
0%
0+
0/
03
07
#673
1#
1'
18
#674
1!
1%
1*
1+
1/
13
17
19
1:
#676
0!
0%
0+
0/
03
07
#678
1!
1%
0*
1+
1/
13
17
09
#680
0!
0%
0+
0/
03
07
#682
1!
1%
1+
1/
13
17
#684
0!
0%
0+
0/
03
07
#685
0#
0'
08
#686
1!
1%
1+
1/
13
17
0:
#688
0!
0%
0+
0/
03
07
#690
1!
1%
1+
1/
13
17
#692
0!
0%
0+
0/
03
07
#694
1!
1%
1+
1/
13
17
#696
0!
0%
0+
0/
03
07
#697
b100 "
b100 &
1,
#698
1!
1%
b100 )
1+
1-
1.
1/
13
17
#700
0!
0%
0+
0/
03
07
#702
1!
1%
b000 )
1+
0-
1/
13
17
#704
0!
0%
0+
0/
03
07
#706
1!
1%
1+
1/
13
17
#708
0!
0%
0+
0/
03
07
#709
b000 "
b000 &
0,
#710
1!
1%
1+
0.
1/
13
17
#712
0!
0%
0+
0/
03
07
#714
1!
1%
1+
1/
13
17
#716
0!
0%
0+
0/
03
07
#718
1!
1%
1+
1/
13
17
#720
0!
0%
0+
0/
03
07
#721
b100 "
b100 &
1,
#722
1!
1%
b100 )
1+
1-
1.
1/
13
17
#724
0!
0%
0+
0/
03
07
#726
1!
1%
b000 )
1+
0-
1/
13
17
#728
0!
0%
0+
0/
03
07
#730
1!
1%
1+
1/
13
17
#732
0!
0%
0+
0/
03
07
#733
b000 "
b000 &
0,
#734
1!
1%
1+
0.
1/
13
17
#736
0!
0%
0+
0/
03
07
#738
1!
1%
1+
1/
13
17
#740
0!
0%
0+
0/
03
07
#742
1!
1%
1+
1/
13
17
#744
0!
0%
0+
0/
03
07
#745
b010 "
b010 &
10
#746
1!
1%
b010 )
1+
1/
11
12
13
17
#748
0!
0%
0+
0/
03
07
#750
1!
1%
b000 )
1+
1/
01
13
17
#752
0!
0%
0+
0/
03
07
#754
1!
1%
1+
1/
13
17
#756
0!
0%
0+
0/
03
07
#757
b000 "
b000 &
00
#758
1!
1%
1+
1/
02
13
17
#760
0!
0%
0+
0/
03
07
#762
1!
1%
1+
1/
13
17
#764
0!
0%
0+
0/
03
07
#766
1!
1%
1+
1/
13
17
#768
0!
0%
0+
0/
03
07
#769
b001 "
b001 &
14
#770
1!
1%
b001 )
1+
1/
13
15
16
17
#772
0!
0%
0+
0/
03
07
#774
1!
1%
b000 )
1+
1/
13
05
17
#776
0!
0%
0+
0/
03
07
#778
1!
1%
1+
1/
13
17
#780
0!
0%
0+
0/
03
07
#781
b000 "
b000 &
04
#782
1!
1%
1+
1/
13
06
17
#784
0!
0%
0+
0/
03
07
#786
1!
1%
1+
1/
13
17
#788
0!
0%
0+
0/
03
07
#790
1!
1%
1+
1/
13
17
#792
0!
0%
0+
0/
03
07
#793
#794
1!
1%
1+
1/
13
17
#796
0!
0%
0+
0/
03
07
#798
1!
1%
1+
1/
13
17
#800
0!
0%
0+
0/
03
07
#802
1!
1%
1+
1/
13
17
#804
0!
0%
0+
0/
03
07
#805
1#
1'
18
#806
1!
1%
1*
1+
1/
13
17
19
1:
#808
0!
0%
0+
0/
03
07
#810
1!
1%
0*
1+
1/
13
17
09
#812
0!
0%
0+
0/
03
07
#814
1!
1%
1+
1/
13
17
#816
0!
0%
0+
0/
03
07
#817
0#
0'
08
#818
1!
1%
1+
1/
13
17
0:
#820
0!
0%
0+
0/
03
07
#822
1!
1%
1+
1/
13
17
#824
0!
0%
0+
0/
03
07
#826
1!
1%
1+
1/
13
17
#828
0!
0%
0+
0/
03
07
#829
b100 "
b100 &
1,
#830
1!
1%
b100 )
1+
1-
1.
1/
13
17
#832
0!
0%
0+
0/
03
07
#834
1!
1%
b000 )
1+
0-
1/
13
17
#836
0!
0%
0+
0/
03
07
#838
1!
1%
1+
1/
13
17
#840
0!
0%
0+
0/
03
07
#841
b000 "
b000 &
0,
#842
1!
1%
1+
0.
1/
13
17
#844
0!
0%
0+
0/
03
07
#846
1!
1%
1+
1/
13
17
#848
0!
0%
0+
0/
03
07
#850
1!
1%
1+
1/
13
17
#852
0!
0%
0+
0/
03
07
#853
b100 "
b100 &
1,
#854
1!
1%
b100 )
1+
1-
1.
1/
13
17
#856
0!
0%
0+
0/
03
07
#858
1!
1%
b000 )
1+
0-
1/
13
17
#860
0!
0%
0+
0/
03
07
#862
1!
1%
1+
1/
13
17
#864
0!
0%
0+
0/
03
07
#865
b000 "
b000 &
0,
#866
1!
1%
1+
0.
1/
13
17
#868
0!
0%
0+
0/
03
07
#870
1!
1%
1+
1/
13
17
#872
0!
0%
0+
0/
03
07
#874
1!
1%
1+
1/
13
17
#876
0!
0%
0+
0/
03
07
#877
b001 "
b001 &
14
#878
1!
1%
b001 )
1+
1/
13
15
16
17
#880
0!
0%
0+
0/
03
07
#882
1!
1%
b000 )
1+
1/
13
05
17
#884
0!
0%
0+
0/
03
07
#886
1!
1%
1+
1/
13
17
#888
0!
0%
0+
0/
03
07
#889
b000 "
b000 &
04
#890
1!
1%
1+
1/
13
06
17
#892
0!
0%
0+
0/
03
07
#894
1!
1%
1+
1/
13
17
#896
0!
0%
0+
0/
03
07
#898
1!
1%
1+
1/
13
17
#900
0!
0%
0+
0/
03
07
#901
b100 "
b100 &
1,
#902
1!
1%
b100 )
1+
1-
1.
1/
13
17
#904
0!
0%
0+
0/
03
07
