gdti10/key.vhdl
library ieee;
use ieee.std_logic_1164.all;

entity key is
  port (
    clk : in std_logic;
    echte_taste : in std_logic;
    taste_wurde_gedrueckt : out std_logic
  );
end key;

architecture behav of key is
  signal last_key : std_logic := '0';
begin
  process (clk) begin
    if rising_edge(clk) then
      
      taste_wurde_gedrueckt <= (not last_key) and echte_taste;
      last_key <= echte_taste;

    end if;
  end process;
end architecture;

gdti10/key_tb.vhdl
library ieee;
use ieee.std_logic_1164.all;

entity key_tb is end key_tb;

architecture behav of key_tb is

  component key port (
    clk : in std_logic;
    echte_taste : in std_logic;
    taste_wurde_gedrueckt : out std_logic
  ); end component;
  signal clk : std_logic;
  signal echte_taste : std_logic;
  signal taste_wurde_gedrueckt : std_logic;
begin
  singleton_of_taste: key port map (clk, echte_taste, taste_wurde_gedrueckt);

  process begin
    clk <= '0';
    echte_taste <= '0';
                        clk <= '1'; wait for 1 fs; clk <= '0'; wait for 1 fs;
    -- allow for init, bad but ok
                        clk <= '1'; wait for 1 fs; clk <= '0'; wait for 1 fs;
    assert taste_wurde_gedrueckt = '0' report "hu? Taste von alleine gedrueckt?" severity error;
                        clk <= '1'; wait for 1 fs; clk <= '0'; wait for 1 fs;
    assert taste_wurde_gedrueckt = '0' report "hu? Taste von alleine gedrueckt?" severity error;
                        clk <= '1'; wait for 1 fs; clk <= '0'; wait for 1 fs;
    assert taste_wurde_gedrueckt = '0' report "hu? Taste von alleine gedrueckt?" severity error;

    echte_taste <= '1';
                        clk <= '1'; wait for 1 fs; clk <= '0'; wait for 1 fs;
    assert taste_wurde_gedrueckt = '1' report "taste nicht erkannt" severity error;
                        clk <= '1'; wait for 1 fs; clk <= '0'; wait for 1 fs;
    assert taste_wurde_gedrueckt = '0' report "tastenausgang laenger als einen takt aktiv" severity error;

                        clk <= '1'; wait for 1 fs; clk <= '0'; wait for 1 fs;
    assert taste_wurde_gedrueckt = '0' report "hu? Taste von alleine wieder gedrueckt?" severity error;
                        clk <= '1'; wait for 1 fs; clk <= '0'; wait for 1 fs;
    assert taste_wurde_gedrueckt = '0' report "hu? Taste von alleine wieder gedrueckt?" severity error;
                        clk <= '1'; wait for 1 fs; clk <= '0'; wait for 1 fs;
    assert taste_wurde_gedrueckt = '0' report "hu? Taste von alleine wieder gedrueckt?" severity error;

    echte_taste <= '0';
                        clk <= '1'; wait for 1 fs; clk <= '0'; wait for 1 fs;
    assert taste_wurde_gedrueckt = '0' report "hu? Taste von alleine wieder gedrueckt?" severity error;
                        clk <= '1'; wait for 1 fs; clk <= '0'; wait for 1 fs;
    assert taste_wurde_gedrueckt = '0' report "hu? Taste von alleine wieder gedrueckt?" severity error;
                        clk <= '1'; wait for 1 fs; clk <= '0'; wait for 1 fs;
    assert taste_wurde_gedrueckt = '0' report "hu? Taste von alleine wieder gedrueckt?" severity error;

    echte_taste <= '1';
                        clk <= '1'; wait for 1 fs; clk <= '0'; wait for 1 fs;
    assert taste_wurde_gedrueckt = '1' report "taste nicht erkannt (2)" severity error;
                        clk <= '1'; wait for 1 fs; clk <= '0'; wait for 1 fs;
    assert taste_wurde_gedrueckt = '0' report "tastenausgang laenger als einen takt aktiv (2)" severity error;

                        clk <= '1'; wait for 1 fs; clk <= '0'; wait for 1 fs;
    assert taste_wurde_gedrueckt = '0' report "hu? Taste von alleine wieder gedrueckt? (2)" severity error;
                        clk <= '1'; wait for 1 fs; clk <= '0'; wait for 1 fs;
    assert taste_wurde_gedrueckt = '0' report "hu? Taste von alleine wieder gedrueckt? (2)" severity error;
                        clk <= '1'; wait for 1 fs; clk <= '0'; wait for 1 fs;
    assert taste_wurde_gedrueckt = '0' report "hu? Taste von alleine wieder gedrueckt? (2)" severity error;

    echte_taste <= '0';
                        clk <= '1'; wait for 1 fs; clk <= '0'; wait for 1 fs;
    assert taste_wurde_gedrueckt = '0' report "hu? Taste von alleine wieder gedrueckt?" severity error;
                        clk <= '1'; wait for 1 fs; clk <= '0'; wait for 1 fs;
    assert taste_wurde_gedrueckt = '0' report "hu? Taste von alleine wieder gedrueckt?" severity error;
                        clk <= '1'; wait for 1 fs; clk <= '0'; wait for 1 fs;
    assert taste_wurde_gedrueckt = '0' report "hu? Taste von alleine wieder gedrueckt?" severity error;

    assert false report "end of test" severity note;
    wait; --  Wait forever; this will finish the simulation.
  end process;
end behav;

gdti10/out_key.vcd
$date
  Tue Jan 31 14:09:09 2023
$end
$version
  GHDL v0
$end
$timescale
  1 fs
$end
$scope module standard $end
$upscope $end
$scope module std_logic_1164 $end
$upscope $end
$scope module key_tb $end
$var reg 1 ! clk $end
$var reg 1 " echte_taste $end
$var reg 1 # taste_wurde_gedrueckt $end
$scope module singleton_of_taste $end
$var reg 1 $ clk $end
$var reg 1 % echte_taste $end
$var reg 1 & taste_wurde_gedrueckt $end
$var reg 1 ' last_key $end
$upscope $end
$upscope $end
$enddefinitions $end
#0
1!
0"
U#
1$
0%
U&
0'
#1
0!
0$
#2
1!
0#
1$
0&
#3
0!
0$
#4
1!
1$
#5
0!
0$
#6
1!
1$
#7
0!
0$
#8
1!
1"
1#
1$
1%
1&
1'
#9
0!
0$
#10
1!
0#
1$
0&
#11
0!
0$
#12
1!
1$
#13
0!
0$
#14
1!
1$
#15
0!
0$
#16
1!
1$
#17
0!
0$
#18
1!
0"
1$
0%
0'
#19
0!
0$
#20
1!
1$
#21
0!
0$
#22
1!
1$
#23
0!
0$
#24
1!
1"
1#
1$
1%
1&
1'
#25
0!
0$
#26
1!
0#
1$
0&
#27
0!
0$
#28
1!
1$
#29
0!
0$
#30
1!
1$
#31
0!
0$
#32
1!
1$
#33
0!
0$
#34
1!
0"
1$
0%
0'
