gdti8/mpx4zu1.vhdl
library ieee;
use ieee.std_logic_1164.all;

entity mpx4zu1 is
  port (
    a, b, c, d: in std_logic;
    sel : in std_logic_vector(1 downto 0);
    y : out std_logic
  );
end mpx4zu1;

architecture behav of mpx4zu1 is
begin
  process (a,b,c,d,sel) begin
    case sel is
      when "00" => y <= a;
      when "01" => y <= b;
      when "10" => y <= c;
      when "11" => y <= d;
      when others =>
    end case;
  end process;
end architecture;

gdti8/mpx16zu4.vhdl
library ieee;
use ieee.std_logic_1164.all;

entity mpx16zu4 is
  port (
    a, b, c, d: in std_logic_vector(3 downto 0);
    sel : in std_logic_vector(1 downto 0);
    y : out std_logic_vector(3 downto 0)
  );
end mpx16zu4;

architecture behav of mpx16zu4 is
  component mpx4zu1 is port (
    a, b, c, d: in std_logic;
    sel : in std_logic_vector(1 downto 0);
    y : out std_logic
  ); end component;
begin
  mx1: mpx4zu1 port map(a(0), b(0), c(0), d(0), sel, y(0));
  mx2: mpx4zu1 port map(a(1), b(1), c(1), d(1), sel, y(1));
  mx3: mpx4zu1 port map(a(2), b(2), c(2), d(2), sel, y(2));
  mx4: mpx4zu1 port map(a(3), b(3), c(3), d(3), sel, y(3));

end architecture;

gdti7/full_add.vhdl
library ieee;
use ieee.std_logic_1164.all;

entity full_add is
  port (
    a, b, c_in : in std_logic;
    sum, c_out : out std_logic
  );
end full_add;

architecture behav of full_add is
begin
  sum <= (a xor b) xor c_in;
  c_out <= (c_in and (a xor b)) or (a and b);
end architecture;

gdti7/add4.vhdl
library ieee;
use ieee.std_logic_1164.all;

entity add4 is
  port (
    a, b : in std_logic_vector(3 downto 0);
    sum : out std_logic_vector(3 downto 0);
    carry : out std_logic
  );
end add4;

architecture behav of add4 is
  component full_add
    port (a, b, c_in: in std_logic;  sum, c_out : out std_logic);
  end component;
  -- hier eigene signale
  signal s_sum : std_logic_vector(3 downto 0);
  signal s_carry : std_logic_vector(3 downto 0);
begin
  l_add1: full_add port map(a(0), b(0), '0', sum => s_sum(0), c_out => s_carry(0));
  l_add2: full_add port map(a(1), b(1), s_carry(0), sum => s_sum(1), c_out => s_carry(1));
  l_add3: full_add port map(a(2), b(2), s_carry(1), sum => s_sum(2), c_out => s_carry(2));
  l_add5: full_add port map(a(3), b(3), s_carry(2), sum => s_sum(3), c_out => s_carry(3));
  carry <= s_carry(3);
  sum <= s_sum;
end architecture;

gdti5/alu4exor2.vhdl
library ieee;
use ieee.std_logic_1164.all;

entity alu4exor2 is
  port (
    a, b: in std_logic_vector(3 downto 0);
    y : out std_logic_vector(3 downto 0)
  );
end alu4exor2;

architecture behav of alu4exor2 is
begin
  process (a,b) begin
    y <= a xor b;
  end process;
end architecture;

gdti8/alu4and2.vhdl
library ieee;
use ieee.std_logic_1164.all;

entity alu4and2 is
  port (
    a, b: in std_logic_vector(3 downto 0);
    y : out std_logic_vector(3 downto 0)
  );
end alu4and2;

architecture behav of alu4and2 is
begin
  y <= a and b;
end architecture;

gdti8/lsr.vhdl
library ieee;
use ieee.std_logic_1164.all;

entity lsr is
  port (
    a, b: in std_logic_vector(3 downto 0);
    y : out std_logic_vector(3 downto 0)
  );
end lsr;

architecture behav of lsr is
  begin
    process (a,b) begin
      case b is
        when "0000" => y <= a;
        when "0001" => 
        y(0) <= a(1);
        y(1) <= a(2);
        y(2) <= a(3);
        y(3) <= '0';
        when "0010" => 
        y(0) <= a(2);
        y(1) <= a(3);
        y(2) <= '0';
        y(3) <= '0';
        when "0011" => 
        y(0) <= a(3);
        y(1) <= '0';
        y(2) <= '0';
        y(3) <= '0';
        when "0100" => 
        y(0) <= '0';
        y(1) <= '0';
        y(2) <= '0';
        y(3) <= '0';
        when others =>
      end case;
    end process;

end architecture;

gdti8/alu4_lsr.vhdl
library ieee;
use ieee.std_logic_1164.all;

entity alu4_lsr is
  port (
    a, b : in std_logic_vector(3 downto 0);
    sel : in std_logic_vector(1 downto 0);
    result : out std_logic_vector(3 downto 0)
  );
end alu4_lsr;

architecture behav of alu4_lsr is
  component lsr is
    port ( a, b: in std_logic_vector(3 downto 0); y : out std_logic_vector(3 downto 0));
  end component;
  component alu4and2 is
    port ( a, b: in std_logic_vector(3 downto 0); y : out std_logic_vector(3 downto 0));
  end component;
  component alu4exor2 is
    port ( a, b: in std_logic_vector(3 downto 0); y : out std_logic_vector(3 downto 0));
  end component;
  component add4 is
    port ( a, b : in std_logic_vector(3 downto 0); sum : out std_logic_vector(3 downto 0); carry:out std_logic);
  end component;
  component mpx16zu4 is port (
    a, b, c, d: in std_logic_vector(3 downto 0);
    sel : in std_logic_vector(1 downto 0);
    y : out std_logic_vector(3 downto 0)
  ); end component;

  signal s_result_lsr : std_logic_vector(3 downto 0);
  signal s_result_and : std_logic_vector(3 downto 0);
  signal s_result_exor : std_logic_vector(3 downto 0);
  signal s_result_add : std_logic_vector(3 downto 0);
begin
  l_lsr: lsr port map(a,b, s_result_lsr);
  l_and: alu4and2 port map(a,b, s_result_and);
  l_exor: alu4exor2 port map(a,b, s_result_exor);
  l_add: add4 port map(a,b, s_result_add);

  l_mxp: mpx16zu4 port map(s_result_add, s_result_lsr, s_result_and, s_result_exor, sel, result);

end architecture;

gdti8/alu4_lsr_tb.vhdl
library ieee;
use ieee.std_logic_1164.all;
use ieee.numeric_std.all;

entity alu4_lsr_tb is end alu4_lsr_tb;

architecture behav of alu4_lsr_tb is
  component alu4_lsr is
    port (
      a, b : in std_logic_vector(3 downto 0);
      sel : in std_logic_vector(1 downto 0);
      result : out std_logic_vector(3 downto 0)
    );
  end component;
  signal a, b : std_logic_vector(3 downto 0);
  signal sel : std_logic_vector(1 downto 0);
  signal result : std_logic_vector(3 downto 0);
begin
  the_alu: alu4_lsr port map (a,b,sel,result);

  process
  variable expect : integer;
  begin
    a <= "0101";  b <= "0011";  sel <= "00";
    wait for 1 fs;
    assert result = "1000" report "sel 00 is not ADD" severity error;

    for ai in 0 to 15 loop
      for bi in 0 to 4 loop
        a <= std_logic_vector(to_unsigned(ai, 4));
        b <= std_logic_vector(to_unsigned(bi, 4));
	sel <= "01";
        expect := ai;
        for ci in 1 to bi loop
          expect := expect / 2;
        end loop;
	wait for 1 fs;
	assert result = std_logic_vector(to_unsigned(expect, 4))
                 report "sel 01 is not LSR" severity error;
	wait for 1 fs;
      end loop;
    end loop;

    a <= "0101";  b <= "0011";  sel <= "10";
    wait for 1 fs;
    assert result = "0001" report "sel 10 is not AND" severity error;

    a <= "0101";  b <= "0011";  sel <= "11";
    wait for 1 fs;
    assert result = "0110" report "sel 11 is not EXOR" severity error;

    report "end of test." severity note;
    wait; --  Wait forever; this will finish the simulation.
  end process;
end behav;

gdti8/out_alu4_lsr.vcd
$date
  Tue Jan 17 15:31:06 2023
$end
$version
  GHDL v0
$end
$timescale
  1 fs
$end
$scope module standard $end
$upscope $end
$scope module std_logic_1164 $end
$upscope $end
$scope module numeric_std $end
$upscope $end
$scope module alu4_lsr_tb $end
$var reg 4 ! a[3:0] $end
$var reg 4 " b[3:0] $end
$var reg 2 # sel[1:0] $end
$var reg 4 $ result[3:0] $end
$scope module the_alu $end
$var reg 4 % a[3:0] $end
$var reg 4 & b[3:0] $end
$var reg 2 ' sel[1:0] $end
$var reg 4 ( result[3:0] $end
$var reg 4 ) s_result_lsr[3:0] $end
$var reg 4 * s_result_and[3:0] $end
$var reg 4 + s_result_exor[3:0] $end
$var reg 4 , s_result_add[3:0] $end
$scope module l_lsr $end
$var reg 4 - a[3:0] $end
$var reg 4 . b[3:0] $end
$var reg 4 / y[3:0] $end
$upscope $end
$scope module l_and $end
$var reg 4 0 a[3:0] $end
$var reg 4 1 b[3:0] $end
$var reg 4 2 y[3:0] $end
$upscope $end
$scope module l_exor $end
$var reg 4 3 a[3:0] $end
$var reg 4 4 b[3:0] $end
$var reg 4 5 y[3:0] $end
$upscope $end
$scope module l_add $end
$var reg 4 6 a[3:0] $end
$var reg 4 7 b[3:0] $end
$var reg 4 8 sum[3:0] $end
$var reg 1 9 carry $end
$var reg 4 : s_sum[3:0] $end
$var reg 4 ; s_carry[3:0] $end
$scope module l_add1 $end
$var reg 1 < a $end
$var reg 1 = b $end
$var reg 1 > c_in $end
$var reg 1 ? sum $end
$var reg 1 @ c_out $end
$upscope $end
$scope module l_add2 $end
$var reg 1 A a $end
$var reg 1 B b $end
$var reg 1 C c_in $end
$var reg 1 D sum $end
$var reg 1 E c_out $end
$upscope $end
$scope module l_add3 $end
$var reg 1 F a $end
$var reg 1 G b $end
$var reg 1 H c_in $end
$var reg 1 I sum $end
$var reg 1 J c_out $end
$upscope $end
$scope module l_add5 $end
$var reg 1 K a $end
$var reg 1 L b $end
$var reg 1 M c_in $end
$var reg 1 N sum $end
$var reg 1 O c_out $end
$upscope $end
$upscope $end
$scope module l_mxp $end
$var reg 4 P a[3:0] $end
$var reg 4 Q b[3:0] $end
$var reg 4 R c[3:0] $end
$var reg 4 S d[3:0] $end
$var reg 2 T sel[1:0] $end
$var reg 4 U y[3:0] $end
$scope module mx1 $end
$var reg 1 V a $end
$var reg 1 W b $end
$var reg 1 X c $end
$var reg 1 Y d $end
$var reg 2 Z sel[1:0] $end
$var reg 1 [ y $end
$upscope $end
$scope module mx2 $end
$var reg 1 \ a $end
$var reg 1 ] b $end
$var reg 1 ^ c $end
$var reg 1 _ d $end
$var reg 2 ` sel[1:0] $end
$var reg 1 a y $end
$upscope $end
$scope module mx3 $end
$var reg 1 b a $end
$var reg 1 c b $end
$var reg 1 d c $end
$var reg 1 e d $end
$var reg 2 f sel[1:0] $end
$var reg 1 g y $end
$upscope $end
$scope module mx4 $end
$var reg 1 h a $end
$var reg 1 i b $end
$var reg 1 j c $end
$var reg 1 k d $end
$var reg 2 l sel[1:0] $end
$var reg 1 m y $end
$upscope $end
$upscope $end
$upscope $end
$upscope $end
$enddefinitions $end
#0
b0101 !
b0011 "
b00 #
b1000 $
b0101 %
b0011 &
b00 '
b1000 (
b0000 )
b0001 *
b0110 +
b1000 ,
b0101 -
b0011 .
b0000 /
b0101 0
b0011 1
b0001 2
b0101 3
b0011 4
b0110 5
b0101 6
b0011 7
b1000 8
09
b1000 :
b0111 ;
1<
1=
0>
0?
1@
0A
1B
1C
0D
1E
1F
0G
1H
0I
1J
0K
0L
1M
1N
0O
b1000 P
b0000 Q
b0001 R
b0110 S
b00 T
b1000 U
0V
0W
1X
0Y
b00 Z
0[
0\
0]
0^
1_
b00 `
0a
0b
0c
0d
1e
b00 f
0g
1h
0i
0j
0k
b00 l
1m
#1
b0000 !
b0000 "
b01 #
b0000 $
b0000 %
b0000 &
b01 '
b0000 (
b0000 *
b0000 +
b0000 ,
b0000 -
b0000 .
b0000 0
b0000 1
b0000 2
b0000 3
b0000 4
b0000 5
b0000 6
b0000 7
b0000 8
b0000 :
b0000 ;
0<
0=
0@
0B
0C
0D
0E
0F
0H
0I
0J
0M
0N
b0000 P
b0000 R
b0000 S
b01 T
b0000 U
0X
b01 Z
0\
0_
b01 `
0b
0e
b01 f
0h
b01 l
0m
#2
#3
b0001 "
b0001 &
b0001 +
b0001 ,
b0001 .
b0001 1
b0001 4
b0001 5
b0001 7
b0001 8
b0001 :
1=
1?
b0001 P
b0001 S
1V
1Y
#4
#5
b0010 "
b0010 &
b0010 +
b0010 ,
b0010 .
b0010 1
b0010 4
b0010 5
b0010 7
b0010 8
b0010 :
0=
0?
1B
1D
b0010 P
b0010 S
0V
0Y
1\
1_
#6
#7
b0011 "
b0011 &
b0011 +
b0011 ,
b0011 .
b0011 1
b0011 4
b0011 5
b0011 7
b0011 8
b0011 :
1=
1?
b0011 P
b0011 S
1V
1Y
#8
#9
b0100 "
b0100 &
b0100 +
b0100 ,
b0100 .
b0100 1
b0100 4
b0100 5
b0100 7
b0100 8
b0100 :
0=
0?
0B
0D
1G
1I
b0100 P
b0100 S
0V
0Y
0\
0_
1b
1e
#10
#11
b0001 !
b0000 "
b0001 $
b0001 %
b0000 &
b0001 (
b0001 )
b0001 +
b0001 ,
b0001 -
b0000 .
b0001 /
b0001 0
b0000 1
b0001 3
b0000 4
b0001 5
b0001 6
b0000 7
b0001 8
b0001 :
1<
1?
0G
0I
b0001 P
b0001 Q
b0001 S
b0001 U
1V
1W
1Y
1[
0b
0e
#12
#13
b0001 "
b0000 $
b0001 &
b0000 (
b0000 )
b0001 *
b0000 +
b0010 ,
b0001 .
b0000 /
b0001 1
b0001 2
b0001 4
b0000 5
b0001 7
b0010 8
b0010 :
b0001 ;
1=
0?
1@
1C
1D
b0010 P
b0000 Q
b0001 R
b0000 S
b0000 U
0V
0W
1X
0Y
0[
1\
#14
#15
b0010 "
b0010 &
b0000 *
b0011 +
b0011 ,
b0010 .
b0010 1
b0000 2
b0010 4
b0011 5
b0010 7
b0011 8
b0011 :
b0000 ;
0=
1?
0@
1B
0C
1D
0E
0H
0I
b0011 P
b0000 R
b0011 S
1V
0X
1Y
1\
1_
0b
#16
#17
b0011 "
b0011 &
b0001 *
b0010 +
b0100 ,
b0011 .
b0011 1
b0001 2
b0011 4
b0010 5
b0011 7
b0100 8
b0100 :
b0011 ;
1=
0?
1@
1C
0D
1E
1H
1I
b0100 P
b0001 R
b0010 S
0V
1X
0Y
0\
1b
#18
#19
b0100 "
b0100 &
b0000 *
b0101 +
b0101 ,
b0100 .
b0100 1
b0000 2
b0100 4
b0101 5
b0100 7
b0101 8
b0101 :
b0000 ;
0=
1?
0@
0B
0C
0D
0E
1G
0H
1I
0J
0M
0N
b0101 P
b0000 R
b0101 S
1V
0X
1Y
0\
0_
1b
1e
0h
#20
#21
b0010 !
b0000 "
b0010 $
b0010 %
b0000 &
b0010 (
b0010 )
b0010 +
b0010 ,
b0010 -
b0000 .
b0010 /
b0010 0
b0000 1
b0010 3
b0000 4
b0010 5
b0010 6
b0000 7
b0010 8
b0010 :
0<
0?
1A
1D
0G
0I
b0010 P
b0010 Q
b0010 S
b0010 U
0V
0Y
1\
1]
1_
1a
0b
0e
#22
#23
b0001 "
b0001 $
b0001 &
b0001 (
b0001 )
b0011 +
b0011 ,
b0001 .
b0001 /
b0001 1
b0001 4
b0011 5
b0001 7
b0011 8
b0011 :
1=
1?
b0011 P
b0001 Q
b0011 S
b0001 U
1V
1W
1Y
1[
0]
0a
#24
#25
b0010 "
b0000 $
b0010 &
b0000 (
b0000 )
b0010 *
b0000 +
b0100 ,
b0010 .
b0000 /
b0010 1
b0010 2
b0010 4
b0000 5
b0010 7
b0100 8
b0100 :
b0010 ;
0=
0?
1B
0D
1E
1H
1I
b0100 P
b0000 Q
b0010 R
b0000 S
b0000 U
0V
0W
0Y
0[
0\
1^
0_
1b
#26
#27
b0011 "
b0011 &
b0001 +
b0101 ,
b0011 .
b0011 1
b0011 4
b0001 5
b0011 7
b0101 8
b0101 :
1=
1?
b0101 P
b0001 S
1V
1Y
#28
#29
b0100 "
b0100 &
b0000 *
b0110 +
b0110 ,
b0100 .
b0100 1
b0000 2
b0100 4
b0110 5
b0100 7
b0110 8
b0110 :
b0000 ;
0=
0?
0B
1D
0E
1G
0H
1I
0J
0M
0N
b0110 P
b0000 R
b0110 S
0V
0Y
1\
0^
1_
1b
1e
0h
#30
#31
b0011 !
b0000 "
b0011 $
b0011 %
b0000 &
b0011 (
b0011 )
b0011 +
b0011 ,
b0011 -
b0000 .
b0011 /
b0011 0
b0000 1
b0011 3
b0000 4
b0011 5
b0011 6
b0000 7
b0011 8
b0011 :
1<
1?
0G
0I
b0011 P
b0011 Q
b0011 S
b0011 U
1V
1W
1Y
1[
1]
1a
0b
0e
#32
#33
b0001 "
b0001 $
b0001 &
b0001 (
b0001 )
b0001 *
b0010 +
b0100 ,
b0001 .
b0001 /
b0001 1
b0001 2
b0001 4
b0010 5
b0001 7
b0100 8
b0100 :
b0011 ;
1=
0?
1@
1C
0D
1E
1H
1I
b0100 P
b0001 Q
b0001 R
b0010 S
b0001 U
0V
1X
0Y
0\
0]
0a
1b
#34
#35
b0010 "
b0000 $
b0010 &
b0000 (
b0000 )
b0010 *
b0001 +
b0101 ,
b0010 .
b0000 /
b0010 1
b0010 2
b0010 4
b0001 5
b0010 7
b0101 8
b0101 :
b0010 ;
0=
1?
0@
1B
0C
0D
b0101 P
b0000 Q
b0010 R
b0001 S
b0000 U
1V
0W
0X
1Y
0[
0\
1^
0_
#36
#37
b0011 "
b0011 &
b0011 *
b0000 +
b0110 ,
b0011 .
b0011 1
b0011 2
b0011 4
b0000 5
b0011 7
b0110 8
b0110 :
b0011 ;
1=
0?
1@
1C
1D
b0110 P
b0011 R
b0000 S
0V
1X
0Y
1\
#38
#39
b0100 "
b0100 &
b0000 *
b0111 +
b0111 ,
b0100 .
b0100 1
b0000 2
b0100 4
b0111 5
b0100 7
b0111 8
b0111 :
b0000 ;
0=
1?
0@
0B
0C
1D
0E
1G
0H
1I
0J
0M
0N
b0111 P
b0000 R
b0111 S
1V
0X
1Y
1\
0^
1_
1b
1e
0h
#40
#41
b0100 !
b0000 "
b0100 $
b0100 %
b0000 &
b0100 (
b0100 )
b0100 +
b0100 ,
b0100 -
b0000 .
b0100 /
b0100 0
b0000 1
b0100 3
b0000 4
b0100 5
b0100 6
b0000 7
b0100 8
b0100 :
0<
0?
0A
0D
1F
0G
b0100 P
b0100 Q
b0100 S
b0100 U
0V
0Y
0\
0_
1c
1g
#42
#43
b0001 "
b0010 $
b0001 &
b0010 (
b0010 )
b0101 +
b0101 ,
b0001 .
b0010 /
b0001 1
b0001 4
b0101 5
b0001 7
b0101 8
b0101 :
1=
1?
b0101 P
b0010 Q
b0101 S
b0010 U
1V
1Y
1]
1a
0c
0g
#44
#45
b0010 "
b0001 $
b0010 &
b0001 (
b0001 )
b0110 +
b0110 ,
b0010 .
b0001 /
b0010 1
b0010 4
b0110 5
b0010 7
b0110 8
b0110 :
0=
0?
1B
1D
b0110 P
b0001 Q
b0110 S
b0001 U
0V
1W
0Y
1[
1\
0]
1_
0a
#46
#47
b0011 "
b0000 $
b0011 &
b0000 (
b0000 )
b0111 +
b0111 ,
b0011 .
b0000 /
b0011 1
b0011 4
b0111 5
b0011 7
b0111 8
b0111 :
1=
1?
b0111 P
b0000 Q
b0111 S
b0000 U
1V
0W
1Y
0[
#48
#49
b0100 "
b0100 &
b0100 *
b0000 +
b1000 ,
b0100 .
b0100 1
b0100 2
b0100 4
b0000 5
b0100 7
b1000 8
b1000 :
b0100 ;
0=
0?
0B
0D
1G
0I
1J
1M
1N
b1000 P
b0100 R
b0000 S
0V
0Y
0\
0_
0b
1d
0e
1h
#50
#51
b0101 !
b0000 "
b0101 $
b0101 %
b0000 &
b0101 (
b0101 )
b0000 *
b0101 +
b0101 ,
b0101 -
b0000 .
b0101 /
b0101 0
b0000 1
b0000 2
b0101 3
b0000 4
b0101 5
b0101 6
b0000 7
b0101 8
b0101 :
b0000 ;
1<
1?
0G
1I
0J
0M
0N
b0101 P
b0101 Q
b0000 R
b0101 S
b0101 U
1V
1W
1Y
1[
1b
1c
0d
1e
1g
0h
#52
#53
b0001 "
b0010 $
b0001 &
b0010 (
b0010 )
b0001 *
b0100 +
b0110 ,
b0001 .
b0010 /
b0001 1
b0001 2
b0001 4
b0100 5
b0001 7
b0110 8
b0110 :
b0001 ;
1=
0?
1@
1C
1D
b0110 P
b0010 Q
b0001 R
b0100 S
b0010 U
0V
0W
1X
0Y
0[
1\
1]
1a
0c
0g
#54
#55
b0010 "
b0001 $
b0010 &
b0001 (
b0001 )
b0000 *
b0111 +
b0111 ,
b0010 .
b0001 /
b0010 1
b0000 2
b0010 4
b0111 5
b0010 7
b0111 8
b0111 :
b0000 ;
0=
1?
0@
1B
0C
1D
0E
0H
1I
0J
0M
0N
b0111 P
b0001 Q
b0000 R
b0111 S
b0001 U
1V
1W
0X
1Y
1[
1\
0]
1_
0a
1b
0h
#56
#57
b0011 "
b0000 $
b0011 &
b0000 (
b0000 )
b0001 *
b0110 +
b1000 ,
b0011 .
b0000 /
b0011 1
b0001 2
b0011 4
b0110 5
b0011 7
b1000 8
b1000 :
b0111 ;
1=
0?
1@
1C
0D
1E
1H
0I
1J
1M
1N
b1000 P
b0000 Q
b0001 R
b0110 S
b0000 U
0V
0W
1X
0Y
0[
0\
0b
1h
#58
#59
b0100 "
b0100 &
b0100 *
b0001 +
b1001 ,
b0100 .
b0100 1
b0100 2
b0100 4
b0001 5
b0100 7
b1001 8
b1001 :
b0100 ;
0=
1?
0@
0B
0C
0D
0E
1G
0H
0I
b1001 P
b0100 R
b0001 S
1V
0X
1Y
0\
0_
0b
1d
0e
#60
#61
b0110 !
b0000 "
b0110 $
b0110 %
b0000 &
b0110 (
b0110 )
b0000 *
b0110 +
b0110 ,
b0110 -
b0000 .
b0110 /
b0110 0
b0000 1
b0000 2
b0110 3
b0000 4
b0110 5
b0110 6
b0000 7
b0110 8
b0110 :
b0000 ;
0<
0?
1A
1D
0G
1I
0J
0M
0N
b0110 P
b0110 Q
b0000 R
b0110 S
b0110 U
0V
0Y
1\
1]
1_
1a
1b
1c
0d
1e
1g
0h
#62
#63
b0001 "
b0011 $
b0001 &
b0011 (
b0011 )
b0111 +
b0111 ,
b0001 .
b0011 /
b0001 1
b0001 4
b0111 5
b0001 7
b0111 8
b0111 :
1=
1?
b0111 P
b0011 Q
b0111 S
b0011 U
1V
1W
1Y
1[
0c
0g
#64
#65
b0010 "
b0001 $
b0010 &
b0001 (
b0001 )
b0010 *
b0100 +
b1000 ,
b0010 .
b0001 /
b0010 1
b0010 2
b0010 4
b0100 5
b0010 7
b1000 8
b1000 :
b0110 ;
0=
0?
1B
0D
1E
1H
0I
1J
1M
1N
b1000 P
b0001 Q
b0010 R
b0100 S
b0001 U
0V
0Y
0\
0]
1^
0_
0a
0b
1h
#66
#67
b0011 "
b0000 $
b0011 &
b0000 (
b0000 )
b0101 +
b1001 ,
b0011 .
b0000 /
b0011 1
b0011 4
b0101 5
b0011 7
b1001 8
b1001 :
1=
1?
b1001 P
b0000 Q
b0101 S
b0000 U
1V
0W
1Y
0[
#68
#69
b0100 "
b0100 &
b0100 *
b0010 +
b1010 ,
b0100 .
b0100 1
b0100 2
b0100 4
b0010 5
b0100 7
b1010 8
b1010 :
b0100 ;
0=
0?
0B
1D
0E
1G
0H
0I
b1010 P
b0100 R
b0010 S
0V
0Y
1\
0^
1_
0b
1d
0e
#70
#71
b0111 !
b0000 "
b0111 $
b0111 %
b0000 &
b0111 (
b0111 )
b0000 *
b0111 +
b0111 ,
b0111 -
b0000 .
b0111 /
b0111 0
b0000 1
b0000 2
b0111 3
b0000 4
b0111 5
b0111 6
b0000 7
b0111 8
b0111 :
b0000 ;
1<
1?
0G
1I
0J
0M
0N
b0111 P
b0111 Q
b0000 R
b0111 S
b0111 U
1V
1W
1Y
1[
1]
1a
1b
1c
0d
1e
1g
0h
#72
#73
b0001 "
b0011 $
b0001 &
b0011 (
b0011 )
b0001 *
b0110 +
b1000 ,
b0001 .
b0011 /
b0001 1
b0001 2
b0001 4
b0110 5
b0001 7
b1000 8
b1000 :
b0111 ;
1=
0?
1@
1C
0D
1E
1H
0I
1J
1M
1N
b1000 P
b0011 Q
b0001 R
b0110 S
b0011 U
0V
1X
0Y
0\
0b
0c
0g
1h
#74
#75
b0010 "
b0001 $
b0010 &
b0001 (
b0001 )
b0010 *
b0101 +
b1001 ,
b0010 .
b0001 /
b0010 1
b0010 2
b0010 4
b0101 5
b0010 7
b1001 8
b1001 :
b0110 ;
0=
1?
0@
1B
0C
0D
b1001 P
b0001 Q
b0010 R
b0101 S
b0001 U
1V
0X
1Y
0\
0]
1^
0_
0a
#76
#77
b0011 "
b0000 $
b0011 &
b0000 (
b0000 )
b0011 *
b0100 +
b1010 ,
b0011 .
b0000 /
b0011 1
b0011 2
b0011 4
b0100 5
b0011 7
b1010 8
b1010 :
b0111 ;
1=
0?
1@
1C
1D
b1010 P
b0000 Q
b0011 R
b0100 S
b0000 U
0V
0W
1X
0Y
0[
1\
#78
#79
b0100 "
b0100 &
b0100 *
b0011 +
b1011 ,
b0100 .
b0100 1
b0100 2
b0100 4
b0011 5
b0100 7
b1011 8
b1011 :
b0100 ;
0=
1?
0@
0B
0C
1D
0E
1G
0H
0I
b1011 P
b0100 R
b0011 S
1V
0X
1Y
1\
0^
1_
0b
1d
0e
#80
#81
b1000 !
b0000 "
b1000 $
b1000 %
b0000 &
b1000 (
b1000 )
b0000 *
b1000 +
b1000 ,
b1000 -
b0000 .
b1000 /
b1000 0
b0000 1
b0000 2
b1000 3
b0000 4
b1000 5
b1000 6
b0000 7
b1000 8
09
b1000 :
b0000 ;
0<
0?
0A
0D
0F
0G
0J
1K
0M
1N
0O
b1000 P
b1000 Q
b0000 R
b1000 S
b1000 U
0V
0Y
0\
0_
0d
1h
1i
1k
1m
#82
#83
b0001 "
b0100 $
b0001 &
b0100 (
b0100 )
b1001 +
b1001 ,
b0001 .
b0100 /
b0001 1
b0001 4
b1001 5
b0001 7
b1001 8
b1001 :
1=
1?
b1001 P
b0100 Q
b1001 S
b0100 U
1V
1Y
1c
1g
0i
0m
#84
#85
b0010 "
b0010 $
b0010 &
b0010 (
b0010 )
b1010 +
b1010 ,
b0010 .
b0010 /
b0010 1
b0010 4
b1010 5
b0010 7
b1010 8
b1010 :
0=
0?
1B
1D
b1010 P
b0010 Q
b1010 S
b0010 U
0V
0Y
1\
1]
1_
1a
0c
0g
#86
#87
b0011 "
b0001 $
b0011 &
b0001 (
b0001 )
b1011 +
b1011 ,
b0011 .
b0001 /
b0011 1
b0011 4
b1011 5
b0011 7
b1011 8
b1011 :
1=
1?
b1011 P
b0001 Q
b1011 S
b0001 U
1V
1W
1Y
1[
0]
0a
#88
#89
b0100 "
b0000 $
b0100 &
b0000 (
b0000 )
b1100 +
b1100 ,
b0100 .
b0000 /
b0100 1
b0100 4
b1100 5
b0100 7
b1100 8
b1100 :
0=
0?
0B
0D
1G
1I
b1100 P
b0000 Q
b1100 S
b0000 U
0V
0W
0Y
0[
0\
0_
1b
1e
#90
#91
b1001 !
b0000 "
b1001 $
b1001 %
b0000 &
b1001 (
b1001 )
b1001 +
b1001 ,
b1001 -
b0000 .
b1001 /
b1001 0
b0000 1
b1001 3
b0000 4
b1001 5
b1001 6
b0000 7
b1001 8
b1001 :
1<
1?
0G
0I
b1001 P
b1001 Q
b1001 S
b1001 U
1V
1W
1Y
1[
0b
0e
1i
1m
#92
#93
b0001 "
b0100 $
b0001 &
b0100 (
b0100 )
b0001 *
b1000 +
b1010 ,
b0001 .
b0100 /
b0001 1
b0001 2
b0001 4
b1000 5
b0001 7
b1010 8
b1010 :
b0001 ;
1=
0?
1@
1C
1D
b1010 P
b0100 Q
b0001 R
b1000 S
b0100 U
0V
0W
1X
0Y
0[
1\
1c
1g
0i
0m
#94
#95
b0010 "
b0010 $
b0010 &
b0010 (
b0010 )
b0000 *
b1011 +
b1011 ,
b0010 .
b0010 /
b0010 1
b0000 2
b0010 4
b1011 5
b0010 7
b1011 8
b1011 :
b0000 ;
0=
1?
0@
1B
0C
1D
0E
0H
0I
b1011 P
b0010 Q
b0000 R
b1011 S
b0010 U
1V
0X
1Y
1\
1]
1_
1a
0b
0c
0g
#96
#97
b0011 "
b0001 $
b0011 &
b0001 (
b0001 )
b0001 *
b1010 +
b1100 ,
b0011 .
b0001 /
b0011 1
b0001 2
b0011 4
b1010 5
b0011 7
b1100 8
b1100 :
b0011 ;
1=
0?
1@
1C
0D
1E
1H
1I
b1100 P
b0001 Q
b0001 R
b1010 S
b0001 U
0V
1W
1X
0Y
1[
0\
0]
0a
1b
#98
#99
b0100 "
b0000 $
b0100 &
b0000 (
b0000 )
b0000 *
b1101 +
b1101 ,
b0100 .
b0000 /
b0100 1
b0000 2
b0100 4
b1101 5
b0100 7
b1101 8
09
b1101 :
b0000 ;
0=
1?
0@
0B
0C
0D
0E
1G
0H
1I
0J
0M
1N
0O
b1101 P
b0000 Q
b0000 R
b1101 S
b0000 U
1V
0W
0X
1Y
0[
0\
0_
1b
1e
1h
#100
#101
b1010 !
b0000 "
b1010 $
b1010 %
b0000 &
b1010 (
b1010 )
b1010 +
b1010 ,
b1010 -
b0000 .
b1010 /
b1010 0
b0000 1
b1010 3
b0000 4
b1010 5
b1010 6
b0000 7
b1010 8
b1010 :
0<
0?
1A
1D
0G
0I
b1010 P
b1010 Q
b1010 S
b1010 U
0V
0Y
1\
1]
1_
1a
0b
0e
1i
1m
#102
#103
b0001 "
b0101 $
b0001 &
b0101 (
b0101 )
b1011 +
b1011 ,
b0001 .
b0101 /
b0001 1
b0001 4
b1011 5
b0001 7
b1011 8
b1011 :
1=
1?
b1011 P
b0101 Q
b1011 S
b0101 U
1V
1W
1Y
1[
0]
0a
1c
1g
0i
0m
#104
#105
b0010 "
b0010 $
b0010 &
b0010 (
b0010 )
b0010 *
b1000 +
b1100 ,
b0010 .
b0010 /
b0010 1
b0010 2
b0010 4
b1000 5
b0010 7
b1100 8
b1100 :
b0010 ;
0=
0?
1B
0D
1E
1H
1I
b1100 P
b0010 Q
b0010 R
b1000 S
b0010 U
0V
0W
0Y
0[
0\
1]
1^
0_
1a
1b
0c
0g
#106
#107
b0011 "
b0001 $
b0011 &
b0001 (
b0001 )
b1001 +
b1101 ,
b0011 .
b0001 /
b0011 1
b0011 4
b1001 5
b0011 7
b1101 8
b1101 :
1=
1?
b1101 P
b0001 Q
b1001 S
b0001 U
1V
1W
1Y
1[
0]
0a
#108
