gdti8/mpx4zu1.vhdl
library ieee;
use ieee.std_logic_1164.all;

entity mpx4zu1 is
  port (
    a, b, c, d: in std_logic;
    sel : in std_logic_vector(1 downto 0);
    y : out std_logic
  );
end mpx4zu1;

architecture behav of mpx4zu1 is
begin
  process (a,b,c,d,sel) begin
    case sel is
      when "00" => y <= a;
      when "01" => y <= b;
      when "10" => y <= c;
      when "11" => y <= d;
      when others =>
    end case;
  end process;
end architecture;

gdti8/mpx4zu1_tb.vhdl
library ieee;
use ieee.std_logic_1164.all;
use ieee.numeric_std.all;

entity mpx4zu1_tb is end mpx4zu1_tb;

architecture behav of mpx4zu1_tb is
  component mpx4zu1
    port ( a, b, c, d: in std_logic;
    sel : in std_logic_vector(1 downto 0);
    y : out std_logic
  );
  end component;
  signal a,b,c,d,y : std_logic;
  signal sel : std_logic_vector(1 downto 0);
begin
  mpx4zu1_0: mpx4zu1 port map (a,b,c,d,sel,y);

  process
  variable expect : integer;
  variable errcnt : integer := 0;
  begin
    for op in 0 to 3 loop
      for n in 0 to 15 loop
        if  n    mod 2=1 then a<='1'; else a<='0'; end if;
        if (n/2) mod 2=1 then b<='1'; else b<='0'; end if;
        if (n/4) mod 2=1 then c<='1'; else c<='0'; end if;
        if (n/8) mod 2=1 then d<='1'; else d<='0'; end if;
        sel <= std_logic_vector(to_unsigned(op, 2));
        case op is
          when 0 => expect :=  n    mod 2;
          when 1 => expect := (n/2) mod 2;
          when 2 => expect := (n/4) mod 2;
          when 3 => expect := (n/8) mod 2;
          when others =>
        end case;
        wait for 1 fs;
        if (expect=1 and y='0') or (expect=0 and y='1') then
          errcnt := errcnt + 1;
          report "Expected " & integer'image(expect) severity error;
        end if;
      end loop;
    end loop;
    report "end of test. " & integer'image(errcnt) & " errors" severity note;
    wait; --  Wait forever; this will finish the simulation.
  end process;
end behav;

gdti8/out_mpx4zu1.vcd
$date
  Tue Jan 17 15:10:23 2023
$end
$version
  GHDL v0
$end
$timescale
  1 fs
$end
$scope module standard $end
$upscope $end
$scope module std_logic_1164 $end
$upscope $end
$scope module numeric_std $end
$upscope $end
$scope module mpx4zu1_tb $end
$var reg 1 ! a $end
$var reg 1 " b $end
$var reg 1 # c $end
$var reg 1 $ d $end
$var reg 1 % y $end
$var reg 2 & sel[1:0] $end
$scope module mpx4zu1_0 $end
$var reg 1 ' a $end
$var reg 1 ( b $end
$var reg 1 ) c $end
$var reg 1 * d $end
$var reg 2 + sel[1:0] $end
$var reg 1 , y $end
$upscope $end
$upscope $end
$enddefinitions $end
#0
0!
0"
0#
0$
0%
b00 &
0'
0(
0)
0*
b00 +
0,
#1
1!
1%
1'
1,
#2
0!
1"
0%
0'
1(
0,
#3
1!
1%
1'
1,
#4
0!
0"
1#
0%
0'
0(
1)
0,
#5
1!
1%
1'
1,
#6
0!
1"
0%
0'
1(
0,
#7
1!
1%
1'
1,
#8
0!
0"
0#
1$
0%
0'
0(
0)
1*
0,
#9
1!
1%
1'
1,
#10
0!
1"
0%
0'
1(
0,
#11
1!
1%
1'
1,
#12
0!
0"
1#
0%
0'
0(
1)
0,
#13
1!
1%
1'
1,
#14
0!
1"
0%
0'
1(
0,
#15
1!
1%
1'
1,
#16
0!
0"
0#
0$
0%
b01 &
0'
0(
0)
0*
b01 +
0,
#17
1!
1'
#18
0!
1"
1%
0'
1(
1,
#19
1!
1'
#20
0!
0"
1#
0%
0'
0(
1)
0,
#21
1!
1'
#22
0!
1"
1%
0'
1(
1,
#23
1!
1'
#24
0!
0"
0#
1$
0%
0'
0(
0)
1*
0,
#25
1!
1'
#26
0!
1"
1%
0'
1(
1,
#27
1!
1'
#28
0!
0"
1#
0%
0'
0(
1)
0,
#29
1!
1'
#30
0!
1"
1%
0'
1(
1,
#31
1!
1'
#32
0!
0"
0#
0$
0%
b10 &
0'
0(
0)
0*
b10 +
0,
#33
1!
1'
#34
0!
1"
0'
1(
#35
1!
1'
#36
0!
0"
1#
1%
0'
0(
1)
1,
#37
1!
1'
#38
0!
1"
0'
1(
#39
1!
1'
#40
0!
0"
0#
1$
0%
0'
0(
0)
1*
0,
#41
1!
1'
#42
0!
1"
0'
1(
#43
1!
1'
#44
0!
0"
1#
1%
0'
0(
1)
1,
#45
1!
1'
#46
0!
1"
0'
1(
#47
1!
1'
#48
0!
0"
0#
0$
0%
b11 &
0'
0(
0)
0*
b11 +
0,
#49
1!
1'
#50
0!
1"
0'
1(
#51
1!
1'
#52
0!
0"
1#
0'
0(
1)
#53
1!
1'
#54
0!
1"
0'
1(
#55
1!
1'
#56
0!
0"
0#
1$
1%
0'
0(
0)
1*
1,
#57
1!
1'
#58
0!
1"
0'
1(
#59
1!
1'
#60
0!
0"
1#
0'
0(
1)
#61
1!
1'
#62
0!
1"
0'
1(
#63
1!
1'
