gdti7/full_add.vhdl
library ieee;
use ieee.std_logic_1164.all;

entity full_add is
  port (
    a, b, c_in : in std_logic;
    sum, c_out : out std_logic
  );
end full_add;

architecture behav of full_add is
begin
  sum <= (a xor b) xor c_in;
  c_out <= (c_in and (a xor b)) or (a and b);
end architecture;

gdti7/add4.vhdl
library ieee;
use ieee.std_logic_1164.all;

entity add4 is
  port (
    a, b : in std_logic_vector(3 downto 0);
    sum : out std_logic_vector(3 downto 0);
    carry : out std_logic
  );
end add4;

architecture behav of add4 is
  component full_add
    port (a, b, c_in: in std_logic;  sum, c_out : out std_logic);
  end component;
  -- hier eigene signale
  signal s_sum : std_logic_vector(3 downto 0);
  signal s_carry : std_logic_vector(3 downto 0);
begin
  l_add1: full_add port map(a(0), b(0), '0', sum => s_sum(0), c_out => s_carry(0));
  l_add2: full_add port map(a(1), b(1), s_carry(0), sum => s_sum(1), c_out => s_carry(1));
  l_add3: full_add port map(a(2), b(2), s_carry(1), sum => s_sum(2), c_out => s_carry(2));
  l_add5: full_add port map(a(3), b(3), s_carry(2), sum => s_sum(3), c_out => s_carry(3));
  carry <= s_carry(3);
  sum <= s_sum;
end architecture;

gdti7/add4_tb.vhdl
library ieee;
use ieee.std_logic_1164.all;
use ieee.numeric_std.all;

entity add4_tb is end add4_tb;

architecture behav of add4_tb is
  component add4 port(
    a, b : in std_logic_vector(3 downto 0);
    sum : out std_logic_vector(3 downto 0);
    carry : out std_logic
  ); end component;
  signal a,b,sum : std_logic_vector(3 downto 0);
  signal carry : std_logic;
begin
  add4_0: add4 port map (a, b,  sum, carry);

  process
    variable si, errcnt : integer;
  begin
    errcnt := 0;
    for bi in 0 to 15 loop
      for ai in 0 to 15 loop
        a <= std_logic_vector(to_unsigned(ai, 4));
        b <= std_logic_vector(to_unsigned(bi, 4));
        wait for 1 fs;
        si := to_integer(unsigned(sum));
        if carry = '1' then si := si + 16; end if;
        if (ai+bi) mod 32 /= si then
          errcnt := errcnt + 1;
          report integer'image(ai) & "+" & integer'image(bi) & " ==> " & integer'image(ai+bi) & " but simulation returns " & integer'image(si) severity error;
        end if;
        wait for 1 fs;
      end loop;
    end loop;
    if errcnt=0 then
      report "Had no errors";
    else
      report "Had " & integer'image(errcnt) & " errors";
    end if;
    report "end of test.";
    wait; --  Wait forever; this will finish the simulation.
  end process;
end behav;

gdti7/out_add4.vcd
$date
  Tue Jan 10 14:42:26 2023
$end
$version
  GHDL v0
$end
$timescale
  1 fs
$end
$scope module standard $end
$upscope $end
$scope module std_logic_1164 $end
$upscope $end
$scope module numeric_std $end
$upscope $end
$scope module add4_tb $end
$var reg 4 ! a[3:0] $end
$var reg 4 " b[3:0] $end
$var reg 4 # sum[3:0] $end
$var reg 1 $ carry $end
$scope module add4_0 $end
$var reg 4 % a[3:0] $end
$var reg 4 & b[3:0] $end
$var reg 4 ' sum[3:0] $end
$var reg 1 ( carry $end
$var reg 4 ) s_sum[3:0] $end
$var reg 4 * s_carry[3:0] $end
$scope module l_add1 $end
$var reg 1 + a $end
$var reg 1 , b $end
$var reg 1 - c_in $end
$var reg 1 . sum $end
$var reg 1 / c_out $end
$upscope $end
$scope module l_add2 $end
$var reg 1 0 a $end
$var reg 1 1 b $end
$var reg 1 2 c_in $end
$var reg 1 3 sum $end
$var reg 1 4 c_out $end
$upscope $end
$scope module l_add3 $end
$var reg 1 5 a $end
$var reg 1 6 b $end
$var reg 1 7 c_in $end
$var reg 1 8 sum $end
$var reg 1 9 c_out $end
$upscope $end
$scope module l_add5 $end
$var reg 1 : a $end
$var reg 1 ; b $end
$var reg 1 < c_in $end
$var reg 1 = sum $end
$var reg 1 > c_out $end
$upscope $end
$upscope $end
$upscope $end
$enddefinitions $end
#0
b0000 !
b0000 "
b0000 #
0$
b0000 %
b0000 &
b0000 '
0(
b0000 )
b0000 *
0+
0,
0-
0.
0/
00
01
02
03
04
05
06
07
08
09
0:
0;
0<
0=
0>
#1
#2
b0001 !
b0001 #
b0001 %
b0001 '
b0001 )
1+
1.
#3
#4
b0010 !
b0010 #
b0010 %
b0010 '
b0010 )
0+
0.
10
13
#5
#6
b0011 !
b0011 #
b0011 %
b0011 '
b0011 )
1+
1.
#7
#8
b0100 !
b0100 #
b0100 %
b0100 '
b0100 )
0+
0.
00
03
15
18
#9
#10
b0101 !
b0101 #
b0101 %
b0101 '
b0101 )
1+
1.
#11
#12
b0110 !
b0110 #
b0110 %
b0110 '
b0110 )
0+
0.
10
13
#13
#14
b0111 !
b0111 #
b0111 %
b0111 '
b0111 )
1+
1.
#15
#16
b1000 !
b1000 #
b1000 %
b1000 '
b1000 )
0+
0.
00
03
05
08
1:
1=
#17
#18
b1001 !
b1001 #
b1001 %
b1001 '
b1001 )
1+
1.
#19
#20
b1010 !
b1010 #
b1010 %
b1010 '
b1010 )
0+
0.
10
13
#21
#22
b1011 !
b1011 #
b1011 %
b1011 '
b1011 )
1+
1.
#23
#24
b1100 !
b1100 #
b1100 %
b1100 '
b1100 )
0+
0.
00
03
15
18
#25
#26
b1101 !
b1101 #
b1101 %
b1101 '
b1101 )
1+
1.
#27
#28
b1110 !
b1110 #
b1110 %
b1110 '
b1110 )
0+
0.
10
13
#29
#30
b1111 !
b1111 #
b1111 %
b1111 '
b1111 )
1+
1.
#31
#32
b0000 !
b0001 "
b0001 #
b0000 %
b0001 &
b0001 '
b0001 )
0+
1,
00
03
05
08
0:
0=
#33
#34
b0001 !
b0010 #
b0001 %
b0010 '
b0010 )
b0001 *
1+
0.
1/
12
13
#35
#36
b0010 !
b0011 #
b0010 %
b0011 '
b0011 )
b0000 *
0+
1.
0/
10
02
13
04
07
08
#37
#38
b0011 !
b0100 #
b0011 %
b0100 '
b0100 )
b0011 *
1+
0.
1/
12
03
14
17
18
#39
#40
b0100 !
b0101 #
b0100 %
b0101 '
b0101 )
b0000 *
0+
1.
0/
00
02
03
04
15
07
18
09
0<
0=
#41
#42
b0101 !
b0110 #
b0101 %
b0110 '
b0110 )
b0001 *
1+
0.
1/
12
13
#43
#44
b0110 !
b0111 #
b0110 %
b0111 '
b0111 )
b0000 *
0+
1.
0/
10
02
13
04
07
18
09
0<
0=
#45
#46
b0111 !
b1000 #
b0111 %
b1000 '
b1000 )
b0111 *
1+
0.
1/
12
03
14
17
08
19
1<
1=
#47
#48
b1000 !
b1001 #
0$
b1000 %
b1001 '
0(
b1001 )
b0000 *
0+
1.
0/
00
02
03
04
05
07
08
09
1:
0<
1=
0>
#49
#50
b1001 !
b1010 #
b1001 %
b1010 '
b1010 )
b0001 *
1+
0.
1/
12
13
#51
#52
b1010 !
b1011 #
b1010 %
b1011 '
b1011 )
b0000 *
0+
1.
0/
10
02
13
04
07
08
#53
#54
b1011 !
b1100 #
b1011 %
b1100 '
b1100 )
b0011 *
1+
0.
1/
12
03
14
17
18
#55
#56
b1100 !
b1101 #
0$
b1100 %
b1101 '
0(
b1101 )
b0000 *
0+
1.
0/
00
02
03
04
15
07
18
09
0<
1=
0>
#57
#58
b1101 !
b1110 #
b1101 %
b1110 '
b1110 )
b0001 *
1+
0.
1/
12
13
#59
#60
b1110 !
b1111 #
0$
b1110 %
b1111 '
0(
b1111 )
b0000 *
0+
1.
0/
10
02
13
04
07
18
09
0<
1=
0>
#61
#62
b1111 !
b0000 #
1$
b1111 %
b0000 '
1(
b0000 )
b1111 *
1+
0.
1/
12
03
14
17
08
19
1<
0=
1>
#63
#64
b0000 !
b0010 "
b0010 #
0$
b0000 %
b0010 &
b0010 '
0(
b0010 )
b0000 *
0+
0,
0/
00
11
02
13
04
05
07
08
09
0:
0<
0=
0>
#65
#66
b0001 !
b0011 #
b0001 %
b0011 '
b0011 )
1+
1.
#67
#68
b0010 !
b0100 #
b0010 %
b0100 '
b0100 )
b0010 *
0+
0.
10
03
14
17
18
#69
#70
b0011 !
b0101 #
b0011 %
b0101 '
b0101 )
1+
1.
#71
#72
b0100 !
b0110 #
b0100 %
b0110 '
b0110 )
b0000 *
0+
0.
00
13
04
15
07
18
09
0<
0=
#73
#74
b0101 !
b0111 #
b0101 %
b0111 '
b0111 )
1+
1.
#75
#76
b0110 !
b1000 #
b0110 %
b1000 '
b1000 )
b0110 *
0+
0.
10
03
14
17
08
19
1<
1=
#77
#78
b0111 !
b1001 #
b0111 %
b1001 '
b1001 )
1+
1.
#79
#80
b1000 !
b1010 #
0$
b1000 %
b1010 '
0(
b1010 )
b0000 *
0+
0.
00
13
04
05
07
08
09
1:
0<
1=
0>
#81
#82
b1001 !
b1011 #
b1001 %
b1011 '
b1011 )
1+
1.
#83
#84
b1010 !
b1100 #
b1010 %
b1100 '
b1100 )
b0010 *
0+
0.
10
03
14
17
18
#85
#86
b1011 !
b1101 #
b1011 %
b1101 '
b1101 )
1+
1.
#87
#88
b1100 !
b1110 #
0$
b1100 %
b1110 '
0(
b1110 )
b0000 *
0+
0.
00
13
04
15
07
18
09
0<
1=
0>
#89
#90
b1101 !
b1111 #
b1101 %
b1111 '
b1111 )
1+
1.
#91
#92
b1110 !
b0000 #
1$
b1110 %
b0000 '
1(
b0000 )
b1110 *
0+
0.
10
03
14
17
08
19
1<
0=
1>
#93
#94
b1111 !
b0001 #
b1111 %
b0001 '
b0001 )
1+
1.
#95
#96
b0000 !
b0011 "
b0011 #
0$
b0000 %
b0011 &
b0011 '
0(
b0011 )
b0000 *
0+
1,
00
13
04
05
07
08
09
0:
0<
0=
0>
#97
#98
b0001 !
b0100 #
b0001 %
b0100 '
b0100 )
b0011 *
1+
0.
1/
12
03
14
17
18
#99
#100
b0010 !
b0101 #
b0010 %
b0101 '
b0101 )
b0010 *
0+
1.
0/
10
02
03
#101
#102
b0011 !
b0110 #
b0011 %
b0110 '
b0110 )
b0011 *
1+
0.
1/
12
13
#103
#104
b0100 !
b0111 #
b0100 %
b0111 '
b0111 )
b0000 *
0+
1.
0/
00
02
13
04
15
07
18
09
0<
0=
#105
#106
b0101 !
b1000 #
b0101 %
b1000 '
b1000 )
b0111 *
1+
0.
1/
12
03
14
17
08
19
1<
1=
#107
#108
b0110 !
b1001 #
b0110 %
b1001 '
b1001 )
b0110 *
0+
1.
0/
10
02
03
#109
#110
b0111 !
b1010 #
b0111 %
b1010 '
b1010 )
b0111 *
1+
0.
1/
12
13
#111
#112
b1000 !
b1011 #
0$
b1000 %
b1011 '
0(
b1011 )
b0000 *
0+
1.
0/
00
02
13
04
05
07
08
09
1:
0<
1=
0>
#113
#114
b1001 !
b1100 #
b1001 %
b1100 '
b1100 )
b0011 *
1+
0.
1/
12
03
14
17
18
#115
#116
b1010 !
b1101 #
b1010 %
b1101 '
b1101 )
b0010 *
0+
1.
0/
10
02
03
#117
#118
b1011 !
b1110 #
b1011 %
b1110 '
b1110 )
b0011 *
1+
0.
1/
12
13
#119
#120
b1100 !
b1111 #
0$
b1100 %
b1111 '
0(
b1111 )
b0000 *
0+
1.
0/
00
02
13
04
15
07
18
09
0<
1=
0>
#121
#122
b1101 !
b0000 #
1$
b1101 %
b0000 '
1(
b0000 )
b1111 *
1+
0.
1/
12
03
14
17
08
19
1<
0=
1>
#123
#124
b1110 !
b0001 #
b1110 %
b0001 '
b0001 )
b1110 *
0+
1.
0/
10
02
03
#125
#126
b1111 !
b0010 #
b1111 %
b0010 '
b0010 )
b1111 *
1+
0.
1/
12
13
#127
#128
b0000 !
b0100 "
b0100 #
0$
b0000 %
b0100 &
b0100 '
0(
b0100 )
b0000 *
0+
0,
0/
00
01
02
03
04
05
16
07
18
09
0:
0<
0=
0>
#129
#130
b0001 !
b0101 #
b0001 %
b0101 '
b0101 )
1+
1.
#131
#132
b0010 !
b0110 #
b0010 %
b0110 '
b0110 )
0+
0.
10
13
#133
#134
b0011 !
b0111 #
b0011 %
b0111 '
b0111 )
1+
1.
#135
#136
b0100 !
b1000 #
b0100 %
b1000 '
b1000 )
b0100 *
0+
0.
00
03
15
08
19
1<
1=
#137
#138
b0101 !
b1001 #
b0101 %
b1001 '
b1001 )
1+
1.
#139
#140
b0110 !
b1010 #
b0110 %
b1010 '
b1010 )
0+
0.
10
13
#141
#142
b0111 !
b1011 #
b0111 %
b1011 '
b1011 )
1+
1.
#143
#144
b1000 !
b1100 #
0$
b1000 %
b1100 '
0(
b1100 )
b0000 *
0+
0.
00
03
05
18
09
1:
0<
1=
0>
#145
#146
b1001 !
b1101 #
b1001 %
b1101 '
b1101 )
1+
1.
#147
#148
b1010 !
b1110 #
b1010 %
b1110 '
b1110 )
0+
0.
10
13
#149
#150
b1011 !
b1111 #
b1011 %
b1111 '
b1111 )
1+
1.
#151
#152
b1100 !
b0000 #
1$
b1100 %
b0000 '
1(
b0000 )
b1100 *
0+
0.
00
03
15
08
19
1<
0=
1>
#153
#154
b1101 !
b0001 #
b1101 %
b0001 '
b0001 )
1+
1.
#155
#156
b1110 !
b0010 #
b1110 %
b0010 '
b0010 )
0+
0.
10
13
#157
#158
b1111 !
b0011 #
b1111 %
b0011 '
b0011 )
1+
1.
#159
#160
b0000 !
b0101 "
b0101 #
0$
b0000 %
b0101 &
b0101 '
0(
b0101 )
b0000 *
0+
1,
00
03
05
18
09
0:
0<
0=
0>
#161
#162
b0001 !
b0110 #
b0001 %
b0110 '
b0110 )
b0001 *
1+
0.
1/
12
13
#163
#164
b0010 !
b0111 #
b0010 %
b0111 '
b0111 )
b0000 *
0+
1.
0/
10
02
13
04
07
18
09
0<
0=
#165
#166
b0011 !
b1000 #
b0011 %
b1000 '
b1000 )
b0111 *
1+
0.
1/
12
03
14
17
08
19
1<
1=
#167
#168
b0100 !
b1001 #
b0100 %
b1001 '
b1001 )
b0100 *
0+
1.
0/
00
02
03
04
15
07
08
#169
#170
b0101 !
b1010 #
b0101 %
b1010 '
b1010 )
b0101 *
1+
0.
1/
12
13
#171
#172
b0110 !
b1011 #
b0110 %
b1011 '
b1011 )
b0100 *
0+
1.
0/
10
02
13
04
07
08
#173
#174
b0111 !
b1100 #
b0111 %
b1100 '
b1100 )
b0111 *
1+
0.
1/
12
03
14
17
18
#175
#176
b1000 !
b1101 #
0$
b1000 %
b1101 '
0(
b1101 )
b0000 *
0+
1.
0/
00
02
03
04
05
07
18
09
1:
0<
1=
0>
#177
#178
b1001 !
b1110 #
b1001 %
b1110 '
b1110 )
b0001 *
1+
0.
1/
12
13
#179
#180
b1010 !
b1111 #
0$
b1010 %
b1111 '
0(
b1111 )
b0000 *
0+
1.
0/
10
02
13
04
07
18
09
0<
1=
0>
#181
#182
b1011 !
b0000 #
1$
b1011 %
b0000 '
1(
b0000 )
b1111 *
1+
0.
1/
12
03
14
17
08
19
1<
0=
1>
#183
#184
b1100 !
b0001 #
b1100 %
b0001 '
b0001 )
b1100 *
0+
1.
0/
00
02
03
04
15
07
08
#185
#186
b1101 !
b0010 #
b1101 %
b0010 '
b0010 )
b1101 *
1+
0.
1/
12
13
#187
#188
b1110 !
b0011 #
b1110 %
b0011 '
b0011 )
b1100 *
0+
1.
0/
10
02
13
04
07
08
#189
#190
b1111 !
b0100 #
b1111 %
b0100 '
b0100 )
b1111 *
1+
0.
1/
12
03
14
17
18
#191
#192
b0000 !
b0110 "
b0110 #
0$
b0000 %
b0110 &
b0110 '
0(
b0110 )
b0000 *
0+
0,
0/
00
11
02
13
04
05
07
18
09
0:
0<
0=
0>
#193
#194
b0001 !
b0111 #
b0001 %
b0111 '
b0111 )
1+
1.
#195
#196
b0010 !
b1000 #
b0010 %
b1000 '
b1000 )
b0110 *
0+
0.
10
03
14
17
08
19
1<
1=
#197
#198
b0011 !
b1001 #
b0011 %
b1001 '
b1001 )
1+
1.
#199
#200
b0100 !
b1010 #
b0100 %
b1010 '
b1010 )
b0100 *
0+
0.
00
13
04
15
07
08
#201
#202
b0101 !
b1011 #
b0101 %
b1011 '
b1011 )
1+
1.
#203
#204
b0110 !
b1100 #
b0110 %
b1100 '
b1100 )
b0110 *
0+
0.
10
03
14
17
18
#205
#206
b0111 !
b1101 #
b0111 %
b1101 '
b1101 )
1+
1.
#207
#208
b1000 !
b1110 #
0$
b1000 %
b1110 '
0(
b1110 )
b0000 *
0+
0.
00
13
04
05
07
18
09
1:
0<
1=
0>
#209
#210
b1001 !
b1111 #
b1001 %
b1111 '
b1111 )
1+
1.
#211
#212
b1010 !
b0000 #
1$
b1010 %
b0000 '
1(
b0000 )
b1110 *
0+
0.
10
03
14
17
08
19
1<
0=
1>
#213
#214
b1011 !
b0001 #
b1011 %
b0001 '
b0001 )
1+
1.
#215
#216
b1100 !
b0010 #
b1100 %
b0010 '
b0010 )
b1100 *
0+
0.
00
13
04
15
07
08
#217
#218
b1101 !
b0011 #
b1101 %
b0011 '
b0011 )
1+
1.
#219
#220
b1110 !
b0100 #
b1110 %
b0100 '
b0100 )
b1110 *
0+
0.
10
03
14
17
18
#221
#222
b1111 !
b0101 #
b1111 %
b0101 '
b0101 )
1+
1.
#223
#224
b0000 !
b0111 "
b0111 #
0$
b0000 %
b0111 &
b0111 '
0(
b0111 )
b0000 *
0+
1,
00
13
04
05
07
18
09
0:
0<
0=
0>
#225
#226
b0001 !
b1000 #
b0001 %
b1000 '
b1000 )
b0111 *
1+
0.
1/
12
03
14
17
08
19
1<
1=
#227
#228
b0010 !
b1001 #
b0010 %
b1001 '
b1001 )
b0110 *
0+
1.
0/
10
02
03
#229
#230
b0011 !
b1010 #
b0011 %
b1010 '
b1010 )
b0111 *
1+
0.
1/
12
13
#231
#232
b0100 !
b1011 #
b0100 %
b1011 '
b1011 )
b0100 *
0+
1.
0/
00
02
13
04
15
07
08
#233
#234
b0101 !
b1100 #
b0101 %
b1100 '
b1100 )
b0111 *
1+
0.
1/
12
03
14
17
18
#235
#236
b0110 !
b1101 #
b0110 %
b1101 '
b1101 )
b0110 *
0+
1.
0/
10
02
03
#237
#238
b0111 !
b1110 #
b0111 %
b1110 '
b1110 )
b0111 *
1+
0.
1/
12
13
#239
#240
b1000 !
b1111 #
0$
b1000 %
b1111 '
0(
b1111 )
b0000 *
0+
1.
0/
00
02
13
04
05
07
18
09
1:
0<
1=
0>
#241
#242
b1001 !
b0000 #
1$
b1001 %
b0000 '
1(
b0000 )
b1111 *
1+
0.
1/
12
03
14
17
08
19
1<
0=
1>
#243
#244
b1010 !
b0001 #
b1010 %
b0001 '
b0001 )
b1110 *
0+
1.
0/
10
02
03
#245
#246
b1011 !
b0010 #
b1011 %
b0010 '
b0010 )
b1111 *
1+
0.
1/
12
13
#247
#248
b1100 !
b0011 #
b1100 %
b0011 '
b0011 )
b1100 *
0+
1.
0/
00
02
13
04
15
07
08
#249
#250
b1101 !
b0100 #
b1101 %
b0100 '
b0100 )
b1111 *
1+
0.
1/
12
03
14
17
18
#251
#252
b1110 !
b0101 #
b1110 %
b0101 '
b0101 )
b1110 *
0+
1.
0/
10
02
03
#253
#254
b1111 !
b0110 #
b1111 %
b0110 '
b0110 )
b1111 *
1+
0.
1/
12
13
#255
#256
b0000 !
b1000 "
b1000 #
0$
b0000 %
b1000 &
b1000 '
0(
b1000 )
b0000 *
0+
0,
0/
00
01
02
03
04
05
06
07
08
09
0:
1;
0<
1=
0>
#257
#258
b0001 !
b1001 #
b0001 %
b1001 '
b1001 )
1+
1.
#259
#260
b0010 !
b1010 #
b0010 %
b1010 '
b1010 )
0+
0.
10
13
#261
#262
b0011 !
b1011 #
b0011 %
b1011 '
b1011 )
1+
1.
#263
#264
b0100 !
b1100 #
b0100 %
b1100 '
b1100 )
0+
0.
00
03
15
18
#265
#266
b0101 !
b1101 #
b0101 %
b1101 '
b1101 )
1+
1.
#267
#268
b0110 !
b1110 #
b0110 %
b1110 '
b1110 )
0+
0.
10
13
#269
#270
b0111 !
b1111 #
b0111 %
b1111 '
b1111 )
1+
1.
#271
#272
b1000 !
b0000 #
1$
b1000 %
b0000 '
1(
b0000 )
b1000 *
0+
0.
00
03
05
08
1:
0=
1>
#273
#274
b1001 !
b0001 #
b1001 %
b0001 '
b0001 )
1+
1.
#275
#276
b1010 !
b0010 #
b1010 %
b0010 '
b0010 )
0+
0.
10
13
#277
#278
b1011 !
b0011 #
b1011 %
b0011 '
b0011 )
1+
1.
#279
#280
b1100 !
b0100 #
b1100 %
b0100 '
b0100 )
0+
0.
00
03
15
18
#281
#282
b1101 !
b0101 #
b1101 %
b0101 '
b0101 )
1+
1.
#283
#284
b1110 !
b0110 #
b1110 %
b0110 '
b0110 )
0+
0.
10
13
#285
#286
b1111 !
b0111 #
b1111 %
b0111 '
b0111 )
1+
1.
#287
#288
b0000 !
b1001 "
b1001 #
0$
b0000 %
b1001 &
b1001 '
0(
b1001 )
b0000 *
0+
1,
00
03
05
08
0:
1=
0>
#289
#290
b0001 !
b1010 #
b0001 %
b1010 '
b1010 )
b0001 *
1+
0.
1/
12
13
#291
#292
b0010 !
b1011 #
b0010 %
b1011 '
b1011 )
b0000 *
0+
1.
0/
10
02
13
04
07
08
#293
#294
b0011 !
b1100 #
b0011 %
b1100 '
b1100 )
b0011 *
1+
0.
1/
12
03
14
17
18
#295
#296
b0100 !
b1101 #
0$
b0100 %
b1101 '
0(
b1101 )
b0000 *
0+
1.
0/
00
02
03
04
15
07
18
09
0<
1=
0>
#297
#298
b0101 !
b1110 #
b0101 %
b1110 '
b1110 )
b0001 *
1+
0.
1/
12
13
#299
#300
b0110 !
b1111 #
0$
b0110 %
b1111 '
0(
b1111 )
b0000 *
0+
1.
0/
10
02
13
04
07
18
09
0<
1=
0>
#301
#302
b0111 !
b0000 #
1$
b0111 %
b0000 '
1(
b0000 )
b1111 *
1+
0.
1/
12
03
14
17
08
19
1<
0=
1>
#303
#304
b1000 !
b0001 #
b1000 %
b0001 '
b0001 )
b1000 *
0+
1.
0/
00
02
03
04
05
07
08
09
1:
0<
0=
#305
#306
b1001 !
b0010 #
b1001 %
b0010 '
b0010 )
b1001 *
1+
0.
1/
12
13
#307
#308
b1010 !
b0011 #
b1010 %
b0011 '
b0011 )
b1000 *
0+
1.
0/
10
02
13
04
07
08
#309
#310
b1011 !
b0100 #
b1011 %
b0100 '
b0100 )
b1011 *
1+
0.
1/
12
03
14
17
18
#311
#312
b1100 !
b0101 #
b1100 %
b0101 '
b0101 )
b1000 *
0+
1.
0/
00
02
03
04
15
07
18
09
0<
0=
#313
#314
b1101 !
b0110 #
b1101 %
b0110 '
b0110 )
b1001 *
1+
0.
1/
12
13
#315
#316
b1110 !
b0111 #
b1110 %
b0111 '
b0111 )
b1000 *
0+
1.
0/
10
02
13
04
07
18
09
0<
0=
#317
#318
b1111 !
b1000 #
b1111 %
b1000 '
b1000 )
b1111 *
1+
0.
1/
12
03
14
17
08
19
1<
1=
#319
#320
b0000 !
b1010 "
b1010 #
0$
b0000 %
b1010 &
b1010 '
0(
b1010 )
b0000 *
0+
0,
0/
00
11
02
13
04
05
07
08
09
0:
0<
1=
0>
#321
#322
b0001 !
b1011 #
b0001 %
b1011 '
b1011 )
1+
1.
#323
#324
b0010 !
b1100 #
b0010 %
b1100 '
b1100 )
b0010 *
0+
0.
10
03
14
17
18
#325
#326
b0011 !
b1101 #
b0011 %
b1101 '
b1101 )
1+
1.
#327
#328
b0100 !
b1110 #
0$
b0100 %
b1110 '
0(
b1110 )
b0000 *
0+
0.
00
13
04
15
07
18
09
0<
1=
0>
#329
#330
b0101 !
b1111 #
b0101 %
b1111 '
b1111 )
1+
1.
#331
#332
b0110 !
b0000 #
1$
b0110 %
b0000 '
1(
b0000 )
b1110 *
0+
0.
10
03
14
17
08
19
1<
0=
1>
#333
#334
b0111 !
b0001 #
b0111 %
b0001 '
b0001 )
1+
1.
#335
#336
b1000 !
b0010 #
b1000 %
b0010 '
b0010 )
b1000 *
0+
0.
00
13
04
05
07
08
09
1:
0<
0=
#337
#338
b1001 !
b0011 #
b1001 %
b0011 '
b0011 )
1+
1.
#339
#340
b1010 !
b0100 #
b1010 %
b0100 '
b0100 )
b1010 *
0+
0.
10
03
14
17
18
#341
#342
b1011 !
b0101 #
b1011 %
b0101 '
b0101 )
1+
1.
#343
#344
b1100 !
b0110 #
b1100 %
b0110 '
b0110 )
b1000 *
0+
0.
00
13
04
15
07
18
09
0<
0=
#345
#346
b1101 !
b0111 #
b1101 %
b0111 '
b0111 )
1+
1.
#347
#348
b1110 !
b1000 #
b1110 %
b1000 '
b1000 )
b1110 *
0+
0.
10
03
14
17
08
19
1<
1=
#349
#350
b1111 !
b1001 #
b1111 %
b1001 '
b1001 )
1+
1.
#351
#352
b0000 !
b1011 "
b1011 #
0$
b0000 %
b1011 &
b1011 '
0(
b1011 )
b0000 *
0+
1,
00
13
04
05
07
08
09
0:
0<
1=
0>
#353
#354
b0001 !
b1100 #
b0001 %
b1100 '
b1100 )
b0011 *
1+
0.
1/
12
03
14
17
18
#355
#356
b0010 !
b1101 #
b0010 %
b1101 '
b1101 )
b0010 *
0+
1.
0/
10
02
03
#357
#358
b0011 !
b1110 #
b0011 %
b1110 '
b1110 )
b0011 *
1+
0.
1/
12
13
#359
#360
b0100 !
b1111 #
0$
b0100 %
b1111 '
0(
b1111 )
b0000 *
0+
1.
0/
00
02
13
04
15
07
18
09
0<
1=
0>
#361
#362
b0101 !
b0000 #
1$
b0101 %
b0000 '
1(
b0000 )
b1111 *
1+
0.
1/
12
03
14
17
08
19
1<
0=
1>
#363
#364
b0110 !
b0001 #
b0110 %
b0001 '
b0001 )
b1110 *
0+
1.
0/
10
02
03
#365
#366
b0111 !
b0010 #
b0111 %
b0010 '
b0010 )
b1111 *
1+
0.
1/
12
13
#367
#368
b1000 !
b0011 #
b1000 %
b0011 '
b0011 )
b1000 *
0+
1.
0/
00
02
13
04
05
07
08
09
1:
0<
0=
#369
#370
b1001 !
b0100 #
b1001 %
b0100 '
b0100 )
b1011 *
1+
0.
1/
12
03
14
17
18
#371
#372
b1010 !
b0101 #
b1010 %
b0101 '
b0101 )
b1010 *
0+
1.
0/
10
02
03
#373
#374
b1011 !
b0110 #
b1011 %
b0110 '
b0110 )
b1011 *
1+
0.
1/
12
13
#375
#376
b1100 !
b0111 #
b1100 %
b0111 '
b0111 )
b1000 *
0+
1.
0/
00
02
13
04
15
07
18
09
0<
0=
#377
#378
b1101 !
b1000 #
b1101 %
b1000 '
b1000 )
b1111 *
1+
0.
1/
12
03
14
17
08
19
1<
1=
#379
#380
b1110 !
b1001 #
b1110 %
b1001 '
b1001 )
b1110 *
0+
1.
0/
10
02
03
#381
#382
b1111 !
b1010 #
b1111 %
b1010 '
b1010 )
b1111 *
1+
0.
1/
12
13
#383
#384
b0000 !
b1100 "
b1100 #
0$
b0000 %
b1100 &
b1100 '
0(
b1100 )
b0000 *
0+
0,
0/
00
01
02
03
04
05
16
07
18
09
0:
0<
1=
0>
#385
#386
b0001 !
b1101 #
b0001 %
b1101 '
b1101 )
1+
1.
#387
#388
b0010 !
b1110 #
b0010 %
b1110 '
b1110 )
0+
0.
10
13
#389
#390
b0011 !
b1111 #
b0011 %
b1111 '
b1111 )
1+
1.
#391
#392
b0100 !
b0000 #
1$
b0100 %
b0000 '
1(
b0000 )
b1100 *
0+
0.
00
03
15
08
19
1<
0=
1>
#393
#394
b0101 !
b0001 #
b0101 %
b0001 '
b0001 )
1+
1.
#395
#396
b0110 !
b0010 #
b0110 %
b0010 '
b0010 )
0+
0.
10
13
#397
#398
b0111 !
b0011 #
b0111 %
b0011 '
b0011 )
1+
1.
#399
#400
b1000 !
b0100 #
b1000 %
b0100 '
b0100 )
b1000 *
0+
0.
00
03
05
18
09
1:
0<
0=
#401
#402
b1001 !
b0101 #
b1001 %
b0101 '
b0101 )
1+
1.
#403
#404
b1010 !
b0110 #
b1010 %
b0110 '
b0110 )
0+
0.
10
13
#405
#406
b1011 !
b0111 #
b1011 %
b0111 '
b0111 )
1+
1.
#407
#408
b1100 !
b1000 #
b1100 %
b1000 '
b1000 )
b1100 *
0+
0.
00
03
15
08
19
1<
1=
#409
#410
b1101 !
b1001 #
b1101 %
b1001 '
b1001 )
1+
1.
#411
#412
b1110 !
b1010 #
b1110 %
b1010 '
b1010 )
0+
0.
10
13
#413
#414
b1111 !
b1011 #
b1111 %
b1011 '
b1011 )
1+
1.
#415
#416
b0000 !
b1101 "
b1101 #
0$
b0000 %
b1101 &
b1101 '
0(
b1101 )
b0000 *
0+
1,
00
03
05
18
09
0:
0<
1=
0>
#417
#418
b0001 !
b1110 #
b0001 %
b1110 '
b1110 )
b0001 *
1+
0.
1/
12
13
#419
#420
b0010 !
b1111 #
0$
b0010 %
b1111 '
0(
b1111 )
b0000 *
0+
1.
0/
10
02
13
04
07
18
09
0<
1=
0>
#421
#422
b0011 !
b0000 #
1$
b0011 %
b0000 '
1(
b0000 )
b1111 *
1+
0.
1/
12
03
14
17
08
19
1<
0=
1>
#423
#424
b0100 !
b0001 #
b0100 %
b0001 '
b0001 )
b1100 *
0+
1.
0/
00
02
03
04
15
07
08
#425
#426
b0101 !
b0010 #
b0101 %
b0010 '
b0010 )
b1101 *
1+
0.
1/
12
13
#427
#428
b0110 !
b0011 #
b0110 %
b0011 '
b0011 )
b1100 *
0+
1.
0/
10
02
13
04
07
08
#429
#430
b0111 !
b0100 #
b0111 %
b0100 '
b0100 )
b1111 *
1+
0.
1/
12
03
14
17
18
#431
#432
b1000 !
b0101 #
b1000 %
b0101 '
b0101 )
b1000 *
0+
1.
0/
00
02
03
04
05
07
18
09
1:
0<
0=
#433
#434
b1001 !
b0110 #
b1001 %
b0110 '
b0110 )
b1001 *
1+
0.
1/
12
13
#435
#436
b1010 !
b0111 #
b1010 %
b0111 '
b0111 )
b1000 *
0+
1.
0/
10
02
13
04
07
18
09
0<
0=
#437
#438
b1011 !
b1000 #
b1011 %
b1000 '
b1000 )
b1111 *
1+
0.
1/
12
03
14
17
08
19
1<
1=
#439
