gdti7/full_add.vhdl
library ieee;
use ieee.std_logic_1164.all;

entity full_add is
  port (
    a, b, c_in : in std_logic;
    sum, c_out : out std_logic
  );
end full_add;

architecture behav of full_add is
begin
  sum <= (a xor b) xor c_in;
  c_out <= (c_in and (a xor b)) or (a and b);
end architecture;

gdti7/addsub4.vhdl
library ieee;
use ieee.std_logic_1164.all;

entity addsub4 is
  port (
    a, b : in std_logic_vector(3 downto 0);
    do_add : in std_logic;
    sum : out std_logic_vector(3 downto 0);
    carry : out std_logic
  );
end addsub4;

architecture behav of addsub4 is
  component full_add
    port (a, b, c_in: in std_logic;  sum, c_out : out std_logic);
  end component;
  
  signal s_sum : std_logic_vector(3 downto 0);
  signal s_carry : std_logic_vector(3 downto 0);
  signal s_b : std_logic_vector(3 downto 0);
  signal s_do_sub : std_logic;
begin
  gen: for i in 0 to 3 generate
    s_b(i) <= b(i) xor (not do_add);
  end generate;

  s_do_sub <= not do_add;

  l_add1: full_add port map(a(0), s_b(0), s_do_sub, sum => s_sum(0), c_out => s_carry(0));
  l_add2: full_add port map(a(1), s_b(1), s_carry(0), sum => s_sum(1), c_out => s_carry(1));
  l_add3: full_add port map(a(2), s_b(2), s_carry(1), sum => s_sum(2), c_out => s_carry(2));
  l_add5: full_add port map(a(3), s_b(3), s_carry(2), sum => s_sum(3), c_out => s_carry(3));
  carry <= s_carry(3);
  sum <= s_sum;
end architecture;

gdti7/addsub4_tb.vhdl
library ieee;
use ieee.std_logic_1164.all;
use ieee.numeric_std.all;

entity addsub4_tb is end addsub4_tb;

architecture behav of addsub4_tb is
  component addsub4 port(
    a, b : in std_logic_vector(3 downto 0);
    do_add : in std_logic;
    sum : out std_logic_vector(3 downto 0);
    carry : out std_logic
  ); end component;
  signal a,b,sum : std_logic_vector(3 downto 0);
  signal c_in, do_add, carry : std_logic;
begin
  addsub4_0: addsub4 port map (a, b, do_add,  sum, carry);

  process
    variable si, errcnt : integer;
    variable aii, bii : integer;
  begin
    errcnt := 0;
    for bi in 0 to 15 loop
      for ai in 0 to 15 loop
        a <= std_logic_vector(to_unsigned(ai, 4));
        b <= std_logic_vector(to_unsigned(bi, 4));
        do_add <= '1';
        wait for 1 fs;
        si := to_integer(unsigned(sum));
        if carry='1' then si := si + 16; end if;
        if (ai+bi) mod 32 /= si then
          errcnt := errcnt + 1;
          report integer'image(ai) & "+" & integer'image(bi) & " ==> " & integer'image(ai+bi) & " but simulation returns " & integer'image(si) severity error;
        end if;
        wait for 1 fs;
      end loop;
    end loop;

    for bi in 0 to 15 loop
      for ai in 0 to 15 loop
        a <= std_logic_vector(to_unsigned(ai, 4));
        b <= std_logic_vector(to_unsigned(bi, 4));
        do_add <= '0';
        wait for 1 fs;
        si := to_integer(unsigned(sum));
        if carry='0' then si := si - 16; end if;
        if ai>7 then aii := -(16-ai);  else  aii := ai; end if;
        if bi>7 then bii := -(16-bi);  else  bii := bi; end if;
        if (ai-bi) /= si then 
	  errcnt := errcnt + 1;
	  report integer'image(ai) & "+" & integer'image(bi) & " ==> " & integer'image(ai-bi) & " but simulation returns " & integer'image(si) severity error;
	end if;
        wait for 1 fs;
      end loop;
    end loop;
    if errcnt=0 then
      report "Had no errors";
    else
      report "Had " & integer'image(errcnt) & " errors";
    end if;
    report "end of test.";
    wait; --  Wait forever; this will finish the simulation.
  end process;
end behav;

gdti7/out_addsub4.vcd
$date
  Tue Jan 10 14:43:00 2023
$end
$version
  GHDL v0
$end
$timescale
  1 fs
$end
$scope module standard $end
$upscope $end
$scope module std_logic_1164 $end
$upscope $end
$scope module numeric_std $end
$upscope $end
$scope module addsub4_tb $end
$var reg 4 ! a[3:0] $end
$var reg 4 " b[3:0] $end
$var reg 4 # sum[3:0] $end
$var reg 1 $ c_in $end
$var reg 1 % do_add $end
$var reg 1 & carry $end
$scope module addsub4_0 $end
$var reg 4 ' a[3:0] $end
$var reg 4 ( b[3:0] $end
$var reg 1 ) do_add $end
$var reg 4 * sum[3:0] $end
$var reg 1 + carry $end
$var reg 4 , s_sum[3:0] $end
$var reg 4 - s_carry[3:0] $end
$var reg 4 . s_b[3:0] $end
$var reg 1 / s_do_sub $end
$scope module gen(0) $end
$upscope $end
$scope module gen(1) $end
$upscope $end
$scope module gen(2) $end
$upscope $end
$scope module gen(3) $end
$upscope $end
$scope module l_add1 $end
$var reg 1 0 a $end
$var reg 1 1 b $end
$var reg 1 2 c_in $end
$var reg 1 3 sum $end
$var reg 1 4 c_out $end
$upscope $end
$scope module l_add2 $end
$var reg 1 5 a $end
$var reg 1 6 b $end
$var reg 1 7 c_in $end
$var reg 1 8 sum $end
$var reg 1 9 c_out $end
$upscope $end
$scope module l_add3 $end
$var reg 1 : a $end
$var reg 1 ; b $end
$var reg 1 < c_in $end
$var reg 1 = sum $end
$var reg 1 > c_out $end
$upscope $end
$scope module l_add5 $end
$var reg 1 ? a $end
$var reg 1 @ b $end
$var reg 1 A c_in $end
$var reg 1 B sum $end
$var reg 1 C c_out $end
$upscope $end
$upscope $end
$upscope $end
$enddefinitions $end
#0
b0000 !
b0000 "
b0000 #
U$
1%
0&
b0000 '
b0000 (
1)
b0000 *
0+
b0000 ,
b0000 -
b0000 .
0/
00
01
02
03
04
05
06
07
08
09
0:
0;
0<
0=
0>
0?
0@
0A
0B
0C
#1
#2
b0001 !
b0001 #
b0001 '
b0001 *
b0001 ,
10
13
#3
#4
b0010 !
b0010 #
b0010 '
b0010 *
b0010 ,
00
03
15
18
#5
#6
b0011 !
b0011 #
b0011 '
b0011 *
b0011 ,
10
13
#7
#8
b0100 !
b0100 #
b0100 '
b0100 *
b0100 ,
00
03
05
08
1:
1=
#9
#10
b0101 !
b0101 #
b0101 '
b0101 *
b0101 ,
10
13
#11
#12
b0110 !
b0110 #
b0110 '
b0110 *
b0110 ,
00
03
15
18
#13
#14
b0111 !
b0111 #
b0111 '
b0111 *
b0111 ,
10
13
#15
#16
b1000 !
b1000 #
b1000 '
b1000 *
b1000 ,
00
03
05
08
0:
0=
1?
1B
#17
#18
b1001 !
b1001 #
b1001 '
b1001 *
b1001 ,
10
13
#19
#20
b1010 !
b1010 #
b1010 '
b1010 *
b1010 ,
00
03
15
18
#21
#22
b1011 !
b1011 #
b1011 '
b1011 *
b1011 ,
10
13
#23
#24
b1100 !
b1100 #
b1100 '
b1100 *
b1100 ,
00
03
05
08
1:
1=
#25
#26
b1101 !
b1101 #
b1101 '
b1101 *
b1101 ,
10
13
#27
#28
b1110 !
b1110 #
b1110 '
b1110 *
b1110 ,
00
03
15
18
#29
#30
b1111 !
b1111 #
b1111 '
b1111 *
b1111 ,
10
13
#31
#32
b0000 !
b0001 "
b0001 #
b0000 '
b0001 (
b0001 *
b0001 ,
b0001 .
00
11
13
05
08
0:
0=
0?
0B
#33
#34
b0001 !
b0010 #
b0001 '
b0010 *
b0010 ,
b0001 -
10
03
14
17
18
#35
#36
b0010 !
b0011 #
b0010 '
b0011 *
b0011 ,
b0000 -
00
13
04
15
07
18
09
0<
0=
#37
#38
b0011 !
b0100 #
b0011 '
b0100 *
b0100 ,
b0011 -
10
03
14
17
08
19
1<
1=
#39
#40
b0100 !
b0101 #
b0100 '
b0101 *
b0101 ,
b0000 -
00
13
04
05
07
08
09
1:
0<
1=
0>
0A
0B
#41
#42
b0101 !
b0110 #
b0101 '
b0110 *
b0110 ,
b0001 -
10
03
14
17
18
#43
#44
b0110 !
b0111 #
b0110 '
b0111 *
b0111 ,
b0000 -
00
13
04
15
07
18
09
0<
1=
0>
0A
0B
#45
#46
b0111 !
b1000 #
b0111 '
b1000 *
b1000 ,
b0111 -
10
03
14
17
08
19
1<
0=
1>
1A
1B
#47
#48
b1000 !
b1001 #
0&
b1000 '
b1001 *
0+
b1001 ,
b0000 -
00
13
04
05
07
08
09
0:
0<
0=
0>
1?
0A
1B
0C
#49
#50
b1001 !
b1010 #
b1001 '
b1010 *
b1010 ,
b0001 -
10
03
14
17
18
#51
#52
b1010 !
b1011 #
b1010 '
b1011 *
b1011 ,
b0000 -
00
13
04
15
07
18
09
0<
0=
#53
#54
b1011 !
b1100 #
b1011 '
b1100 *
b1100 ,
b0011 -
10
03
14
17
08
19
1<
1=
#55
#56
b1100 !
b1101 #
0&
b1100 '
b1101 *
0+
b1101 ,
b0000 -
00
13
04
05
07
08
09
1:
0<
1=
0>
0A
1B
0C
#57
#58
b1101 !
b1110 #
b1101 '
b1110 *
b1110 ,
b0001 -
10
03
14
17
18
#59
#60
b1110 !
b1111 #
0&
b1110 '
b1111 *
0+
b1111 ,
b0000 -
00
13
04
15
07
18
09
0<
1=
0>
0A
1B
0C
#61
#62
b1111 !
b0000 #
1&
b1111 '
b0000 *
1+
b0000 ,
b1111 -
10
03
14
17
08
19
1<
0=
1>
1A
0B
1C
#63
#64
b0000 !
b0010 "
b0010 #
0&
b0000 '
b0010 (
b0010 *
0+
b0010 ,
b0000 -
b0010 .
00
01
03
04
05
16
07
18
09
0:
0<
0=
0>
0?
0A
0B
0C
#65
#66
b0001 !
b0011 #
b0001 '
b0011 *
b0011 ,
10
13
#67
#68
b0010 !
b0100 #
b0010 '
b0100 *
b0100 ,
b0010 -
00
03
15
08
19
1<
1=
#69
#70
b0011 !
b0101 #
b0011 '
b0101 *
b0101 ,
10
13
#71
#72
b0100 !
b0110 #
b0100 '
b0110 *
b0110 ,
b0000 -
00
03
05
18
09
1:
0<
1=
0>
0A
0B
#73
#74
b0101 !
b0111 #
b0101 '
b0111 *
b0111 ,
10
13
#75
#76
b0110 !
b1000 #
b0110 '
b1000 *
b1000 ,
b0110 -
00
03
15
08
19
1<
0=
1>
1A
1B
#77
#78
b0111 !
b1001 #
b0111 '
b1001 *
b1001 ,
10
13
#79
#80
b1000 !
b1010 #
0&
b1000 '
b1010 *
0+
b1010 ,
b0000 -
00
03
05
18
09
0:
0<
0=
0>
1?
0A
1B
0C
#81
#82
b1001 !
b1011 #
b1001 '
b1011 *
b1011 ,
10
13
#83
#84
b1010 !
b1100 #
b1010 '
b1100 *
b1100 ,
b0010 -
00
03
15
08
19
1<
1=
#85
#86
b1011 !
b1101 #
b1011 '
b1101 *
b1101 ,
10
13
#87
#88
b1100 !
b1110 #
0&
b1100 '
b1110 *
0+
b1110 ,
b0000 -
00
03
05
18
09
1:
0<
1=
0>
0A
1B
0C
#89
#90
b1101 !
b1111 #
b1101 '
b1111 *
b1111 ,
10
13
#91
#92
b1110 !
b0000 #
1&
b1110 '
b0000 *
1+
b0000 ,
b1110 -
00
03
15
08
19
1<
0=
1>
1A
0B
1C
#93
#94
b1111 !
b0001 #
b1111 '
b0001 *
b0001 ,
10
13
#95
#96
b0000 !
b0011 "
b0011 #
0&
b0000 '
b0011 (
b0011 *
0+
b0011 ,
b0000 -
b0011 .
00
11
13
05
18
09
0:
0<
0=
0>
0?
0A
0B
0C
#97
#98
b0001 !
b0100 #
b0001 '
b0100 *
b0100 ,
b0011 -
10
03
14
17
08
19
1<
1=
#99
#100
b0010 !
b0101 #
b0010 '
b0101 *
b0101 ,
b0010 -
00
13
04
15
07
08
#101
#102
b0011 !
b0110 #
b0011 '
b0110 *
b0110 ,
b0011 -
10
03
14
17
18
#103
#104
b0100 !
b0111 #
b0100 '
b0111 *
b0111 ,
b0000 -
00
13
04
05
07
18
09
1:
0<
1=
0>
0A
0B
#105
#106
b0101 !
b1000 #
b0101 '
b1000 *
b1000 ,
b0111 -
10
03
14
17
08
19
1<
0=
1>
1A
1B
#107
#108
b0110 !
b1001 #
b0110 '
b1001 *
b1001 ,
b0110 -
00
13
04
15
07
08
#109
#110
b0111 !
b1010 #
b0111 '
b1010 *
b1010 ,
b0111 -
10
03
14
17
18
#111
#112
b1000 !
b1011 #
0&
b1000 '
b1011 *
0+
b1011 ,
b0000 -
00
13
04
05
07
18
09
0:
0<
0=
0>
1?
0A
1B
0C
#113
#114
b1001 !
b1100 #
b1001 '
b1100 *
b1100 ,
b0011 -
10
03
14
17
08
19
1<
1=
#115
#116
b1010 !
b1101 #
b1010 '
b1101 *
b1101 ,
b0010 -
00
13
04
15
07
08
#117
#118
b1011 !
b1110 #
b1011 '
b1110 *
b1110 ,
b0011 -
10
03
14
17
18
#119
#120
b1100 !
b1111 #
0&
b1100 '
b1111 *
0+
b1111 ,
b0000 -
00
13
04
05
07
18
09
1:
0<
1=
0>
0A
1B
0C
#121
#122
b1101 !
b0000 #
1&
b1101 '
b0000 *
1+
b0000 ,
b1111 -
10
03
14
17
08
19
1<
0=
1>
1A
0B
1C
#123
#124
b1110 !
b0001 #
b1110 '
b0001 *
b0001 ,
b1110 -
00
13
04
15
07
08
#125
#126
b1111 !
b0010 #
b1111 '
b0010 *
b0010 ,
b1111 -
10
03
14
17
18
#127
#128
b0000 !
b0100 "
b0100 #
0&
b0000 '
b0100 (
b0100 *
0+
b0100 ,
b0000 -
b0100 .
00
01
03
04
05
06
07
08
09
0:
1;
0<
1=
0>
0?
0A
0B
0C
#129
#130
b0001 !
b0101 #
b0001 '
b0101 *
b0101 ,
10
13
#131
#132
b0010 !
b0110 #
b0010 '
b0110 *
b0110 ,
00
03
15
18
#133
#134
b0011 !
b0111 #
b0011 '
b0111 *
b0111 ,
10
13
#135
#136
b0100 !
b1000 #
b0100 '
b1000 *
b1000 ,
b0100 -
00
03
05
08
1:
0=
1>
1A
1B
#137
#138
b0101 !
b1001 #
b0101 '
b1001 *
b1001 ,
10
13
#139
#140
b0110 !
b1010 #
b0110 '
b1010 *
b1010 ,
00
03
15
18
#141
#142
b0111 !
b1011 #
b0111 '
b1011 *
b1011 ,
10
13
#143
#144
b1000 !
b1100 #
0&
b1000 '
b1100 *
0+
b1100 ,
b0000 -
00
03
05
08
0:
1=
0>
1?
0A
1B
0C
#145
#146
b1001 !
b1101 #
b1001 '
b1101 *
b1101 ,
10
13
#147
#148
b1010 !
b1110 #
b1010 '
b1110 *
b1110 ,
00
03
15
18
#149
#150
b1011 !
b1111 #
b1011 '
b1111 *
b1111 ,
10
13
#151
#152
b1100 !
b0000 #
1&
b1100 '
b0000 *
1+
b0000 ,
b1100 -
00
03
05
08
1:
0=
1>
1A
0B
1C
#153
#154
b1101 !
b0001 #
b1101 '
b0001 *
b0001 ,
10
13
#155
#156
b1110 !
b0010 #
b1110 '
b0010 *
b0010 ,
00
03
15
18
#157
#158
b1111 !
b0011 #
b1111 '
b0011 *
b0011 ,
10
13
#159
#160
b0000 !
b0101 "
b0101 #
0&
b0000 '
b0101 (
b0101 *
0+
b0101 ,
b0000 -
b0101 .
00
11
13
05
08
0:
1=
0>
0?
0A
0B
0C
#161
#162
b0001 !
b0110 #
b0001 '
b0110 *
b0110 ,
b0001 -
10
03
14
17
18
#163
#164
b0010 !
b0111 #
b0010 '
b0111 *
b0111 ,
b0000 -
00
13
04
15
07
18
09
0<
1=
0>
0A
0B
#165
#166
b0011 !
b1000 #
b0011 '
b1000 *
b1000 ,
b0111 -
10
03
14
17
08
19
1<
0=
1>
1A
1B
#167
#168
b0100 !
b1001 #
b0100 '
b1001 *
b1001 ,
b0100 -
00
13
04
05
07
08
09
1:
0<
0=
#169
#170
b0101 !
b1010 #
b0101 '
b1010 *
b1010 ,
b0101 -
10
03
14
17
18
#171
#172
b0110 !
b1011 #
b0110 '
b1011 *
b1011 ,
b0100 -
00
13
04
15
07
18
09
0<
0=
#173
#174
b0111 !
b1100 #
b0111 '
b1100 *
b1100 ,
b0111 -
10
03
14
17
08
19
1<
1=
#175
#176
b1000 !
b1101 #
0&
b1000 '
b1101 *
0+
b1101 ,
b0000 -
00
13
04
05
07
08
09
0:
0<
1=
0>
1?
0A
1B
0C
#177
#178
b1001 !
b1110 #
b1001 '
b1110 *
b1110 ,
b0001 -
10
03
14
17
18
#179
#180
b1010 !
b1111 #
0&
b1010 '
b1111 *
0+
b1111 ,
b0000 -
00
13
04
15
07
18
09
0<
1=
0>
0A
1B
0C
#181
#182
b1011 !
b0000 #
1&
b1011 '
b0000 *
1+
b0000 ,
b1111 -
10
03
14
17
08
19
1<
0=
1>
1A
0B
1C
#183
#184
b1100 !
b0001 #
b1100 '
b0001 *
b0001 ,
b1100 -
00
13
04
05
07
08
09
1:
0<
0=
#185
#186
b1101 !
b0010 #
b1101 '
b0010 *
b0010 ,
b1101 -
10
03
14
17
18
#187
#188
b1110 !
b0011 #
b1110 '
b0011 *
b0011 ,
b1100 -
00
13
04
15
07
18
09
0<
0=
#189
#190
b1111 !
b0100 #
b1111 '
b0100 *
b0100 ,
b1111 -
10
03
14
17
08
19
1<
1=
#191
#192
b0000 !
b0110 "
b0110 #
0&
b0000 '
b0110 (
b0110 *
0+
b0110 ,
b0000 -
b0110 .
00
01
03
04
05
16
07
18
09
0:
0<
1=
0>
0?
0A
0B
0C
#193
#194
b0001 !
b0111 #
b0001 '
b0111 *
b0111 ,
10
13
#195
#196
b0010 !
b1000 #
b0010 '
b1000 *
b1000 ,
b0110 -
00
03
15
08
19
1<
0=
1>
1A
1B
#197
#198
b0011 !
b1001 #
b0011 '
b1001 *
b1001 ,
10
13
#199
#200
b0100 !
b1010 #
b0100 '
b1010 *
b1010 ,
b0100 -
00
03
05
18
09
1:
0<
0=
#201
#202
b0101 !
b1011 #
b0101 '
b1011 *
b1011 ,
10
13
#203
#204
b0110 !
b1100 #
b0110 '
b1100 *
b1100 ,
b0110 -
00
03
15
08
19
1<
1=
#205
#206
b0111 !
b1101 #
b0111 '
b1101 *
b1101 ,
10
13
#207
#208
b1000 !
b1110 #
0&
b1000 '
b1110 *
0+
b1110 ,
b0000 -
00
03
05
18
09
0:
0<
1=
0>
1?
0A
1B
0C
#209
#210
b1001 !
b1111 #
b1001 '
b1111 *
b1111 ,
10
13
#211
#212
b1010 !
b0000 #
1&
b1010 '
b0000 *
1+
b0000 ,
b1110 -
00
03
15
08
19
1<
0=
1>
1A
0B
1C
#213
#214
b1011 !
b0001 #
b1011 '
b0001 *
b0001 ,
10
13
#215
#216
b1100 !
b0010 #
b1100 '
b0010 *
b0010 ,
b1100 -
00
03
05
18
09
1:
0<
0=
#217
#218
b1101 !
b0011 #
b1101 '
b0011 *
b0011 ,
10
13
#219
#220
b1110 !
b0100 #
b1110 '
b0100 *
b0100 ,
b1110 -
00
03
15
08
19
1<
1=
#221
#222
b1111 !
b0101 #
b1111 '
b0101 *
b0101 ,
10
13
#223
#224
b0000 !
b0111 "
b0111 #
0&
b0000 '
b0111 (
b0111 *
0+
b0111 ,
b0000 -
b0111 .
00
11
13
05
18
09
0:
0<
1=
0>
0?
0A
0B
0C
#225
#226
b0001 !
b1000 #
b0001 '
b1000 *
b1000 ,
b0111 -
10
03
14
17
08
19
1<
0=
1>
1A
1B
#227
#228
b0010 !
b1001 #
b0010 '
b1001 *
b1001 ,
b0110 -
00
13
04
15
07
08
#229
#230
b0011 !
b1010 #
b0011 '
b1010 *
b1010 ,
b0111 -
10
03
14
17
18
#231
#232
b0100 !
b1011 #
b0100 '
b1011 *
b1011 ,
b0100 -
00
13
04
05
07
18
09
1:
0<
0=
#233
#234
b0101 !
b1100 #
b0101 '
b1100 *
b1100 ,
b0111 -
10
03
14
17
08
19
1<
1=
#235
#236
b0110 !
b1101 #
b0110 '
b1101 *
b1101 ,
b0110 -
00
13
04
15
07
08
#237
#238
b0111 !
b1110 #
b0111 '
b1110 *
b1110 ,
b0111 -
10
03
14
17
18
#239
#240
b1000 !
b1111 #
0&
b1000 '
b1111 *
0+
b1111 ,
b0000 -
00
13
04
05
07
18
09
0:
0<
1=
0>
1?
0A
1B
0C
#241
#242
b1001 !
b0000 #
1&
b1001 '
b0000 *
1+
b0000 ,
b1111 -
10
03
14
17
08
19
1<
0=
1>
1A
0B
1C
#243
#244
b1010 !
b0001 #
b1010 '
b0001 *
b0001 ,
b1110 -
00
13
04
15
07
08
#245
#246
b1011 !
b0010 #
b1011 '
b0010 *
b0010 ,
b1111 -
10
03
14
17
18
#247
#248
b1100 !
b0011 #
b1100 '
b0011 *
b0011 ,
b1100 -
00
13
04
05
07
18
09
1:
0<
0=
#249
#250
b1101 !
b0100 #
b1101 '
b0100 *
b0100 ,
b1111 -
10
03
14
17
08
19
1<
1=
#251
#252
b1110 !
b0101 #
b1110 '
b0101 *
b0101 ,
b1110 -
00
13
04
15
07
08
#253
#254
b1111 !
b0110 #
b1111 '
b0110 *
b0110 ,
b1111 -
10
03
14
17
18
#255
#256
b0000 !
b1000 "
b1000 #
0&
b0000 '
b1000 (
b1000 *
0+
b1000 ,
b0000 -
b1000 .
00
01
03
04
05
06
07
08
09
0:
0;
0<
0=
0>
0?
1@
0A
1B
0C
#257
#258
b0001 !
b1001 #
b0001 '
b1001 *
b1001 ,
10
13
#259
#260
b0010 !
b1010 #
b0010 '
b1010 *
b1010 ,
00
03
15
18
#261
#262
b0011 !
b1011 #
b0011 '
b1011 *
b1011 ,
10
13
#263
#264
b0100 !
b1100 #
b0100 '
b1100 *
b1100 ,
00
03
05
08
1:
1=
#265
#266
b0101 !
b1101 #
b0101 '
b1101 *
b1101 ,
10
13
#267
#268
b0110 !
b1110 #
b0110 '
b1110 *
b1110 ,
00
03
15
18
#269
#270
b0111 !
b1111 #
b0111 '
b1111 *
b1111 ,
10
13
#271
#272
b1000 !
b0000 #
1&
b1000 '
b0000 *
1+
b0000 ,
b1000 -
00
03
05
08
0:
0=
1?
0B
1C
#273
#274
b1001 !
b0001 #
b1001 '
b0001 *
b0001 ,
10
13
#275
#276
b1010 !
b0010 #
b1010 '
b0010 *
b0010 ,
00
03
15
18
#277
#278
b1011 !
b0011 #
b1011 '
b0011 *
b0011 ,
10
13
#279
#280
b1100 !
b0100 #
b1100 '
b0100 *
b0100 ,
00
03
05
08
1:
1=
#281
#282
b1101 !
b0101 #
b1101 '
b0101 *
b0101 ,
10
13
#283
#284
b1110 !
b0110 #
b1110 '
b0110 *
b0110 ,
00
03
15
18
#285
#286
b1111 !
b0111 #
b1111 '
b0111 *
b0111 ,
10
13
#287
#288
b0000 !
b1001 "
b1001 #
0&
b0000 '
b1001 (
b1001 *
0+
b1001 ,
b0000 -
b1001 .
00
11
13
05
08
0:
0=
0?
1B
0C
#289
#290
b0001 !
b1010 #
b0001 '
b1010 *
b1010 ,
b0001 -
10
03
14
17
18
#291
#292
b0010 !
b1011 #
b0010 '
b1011 *
b1011 ,
b0000 -
00
13
04
15
07
18
09
0<
0=
#293
#294
b0011 !
b1100 #
b0011 '
b1100 *
b1100 ,
b0011 -
10
03
14
17
08
19
1<
1=
#295
#296
b0100 !
b1101 #
0&
b0100 '
b1101 *
0+
b1101 ,
b0000 -
00
13
04
05
07
08
09
1:
0<
1=
0>
0A
1B
0C
#297
#298
b0101 !
b1110 #
b0101 '
b1110 *
b1110 ,
b0001 -
10
03
14
17
18
#299
#300
b0110 !
b1111 #
0&
b0110 '
b1111 *
0+
b1111 ,
b0000 -
00
13
04
15
07
18
09
0<
1=
0>
0A
1B
0C
#301
#302
b0111 !
b0000 #
1&
b0111 '
b0000 *
1+
b0000 ,
b1111 -
10
03
14
17
08
19
1<
0=
1>
1A
0B
1C
#303
#304
b1000 !
b0001 #
b1000 '
b0001 *
b0001 ,
b1000 -
00
13
04
05
07
08
09
0:
0<
0=
0>
1?
0A
0B
#305
#306
b1001 !
b0010 #
b1001 '
b0010 *
b0010 ,
b1001 -
10
03
14
17
18
#307
#308
b1010 !
b0011 #
b1010 '
b0011 *
b0011 ,
b1000 -
00
13
04
15
07
18
09
0<
0=
#309
#310
b1011 !
b0100 #
b1011 '
b0100 *
b0100 ,
b1011 -
10
03
14
17
08
19
1<
1=
#311
#312
b1100 !
b0101 #
b1100 '
b0101 *
b0101 ,
b1000 -
00
13
04
05
07
08
09
1:
0<
1=
0>
0A
0B
#313
#314
b1101 !
b0110 #
b1101 '
b0110 *
b0110 ,
b1001 -
10
03
14
17
18
#315
#316
b1110 !
b0111 #
b1110 '
b0111 *
b0111 ,
b1000 -
00
13
04
15
07
18
09
0<
1=
0>
0A
0B
#317
#318
b1111 !
b1000 #
b1111 '
b1000 *
b1000 ,
b1111 -
10
03
14
17
08
19
1<
0=
1>
1A
1B
#319
#320
b0000 !
b1010 "
b1010 #
0&
b0000 '
b1010 (
b1010 *
0+
b1010 ,
b0000 -
b1010 .
00
01
03
04
05
16
07
18
09
0:
0<
0=
0>
0?
0A
1B
0C
#321
#322
b0001 !
b1011 #
b0001 '
b1011 *
b1011 ,
10
13
#323
#324
b0010 !
b1100 #
b0010 '
b1100 *
b1100 ,
b0010 -
00
03
15
08
19
1<
1=
#325
#326
b0011 !
b1101 #
b0011 '
b1101 *
b1101 ,
10
13
#327
#328
b0100 !
b1110 #
0&
b0100 '
b1110 *
0+
b1110 ,
b0000 -
00
03
05
18
09
1:
0<
1=
0>
0A
1B
0C
#329
#330
b0101 !
b1111 #
b0101 '
b1111 *
b1111 ,
10
13
#331
#332
b0110 !
b0000 #
1&
b0110 '
b0000 *
1+
b0000 ,
b1110 -
00
03
15
08
19
1<
0=
1>
1A
0B
1C
#333
#334
b0111 !
b0001 #
b0111 '
b0001 *
b0001 ,
10
13
#335
#336
b1000 !
b0010 #
b1000 '
b0010 *
b0010 ,
b1000 -
00
03
05
18
09
0:
0<
0=
0>
1?
0A
0B
#337
#338
b1001 !
b0011 #
b1001 '
b0011 *
b0011 ,
10
13
#339
#340
b1010 !
b0100 #
b1010 '
b0100 *
b0100 ,
b1010 -
00
03
15
08
19
1<
1=
#341
#342
b1011 !
b0101 #
b1011 '
b0101 *
b0101 ,
10
13
#343
#344
b1100 !
b0110 #
b1100 '
b0110 *
b0110 ,
b1000 -
00
03
05
18
09
1:
0<
1=
0>
0A
0B
#345
#346
b1101 !
b0111 #
b1101 '
b0111 *
b0111 ,
10
13
#347
#348
b1110 !
b1000 #
b1110 '
b1000 *
b1000 ,
b1110 -
00
03
15
08
19
1<
0=
1>
1A
1B
#349
#350
b1111 !
b1001 #
b1111 '
b1001 *
b1001 ,
10
13
#351
#352
b0000 !
b1011 "
b1011 #
0&
b0000 '
b1011 (
b1011 *
0+
b1011 ,
b0000 -
b1011 .
00
11
13
05
18
09
0:
0<
0=
0>
0?
0A
1B
0C
#353
#354
b0001 !
b1100 #
b0001 '
b1100 *
b1100 ,
b0011 -
10
03
14
17
08
19
1<
1=
#355
#356
b0010 !
b1101 #
b0010 '
b1101 *
b1101 ,
b0010 -
00
13
04
15
07
08
#357
#358
b0011 !
b1110 #
b0011 '
b1110 *
b1110 ,
b0011 -
10
03
14
17
18
#359
#360
b0100 !
b1111 #
0&
b0100 '
b1111 *
0+
b1111 ,
b0000 -
00
13
04
05
07
18
09
1:
0<
1=
0>
0A
1B
0C
#361
#362
b0101 !
b0000 #
1&
b0101 '
b0000 *
1+
b0000 ,
b1111 -
10
03
14
17
08
19
1<
0=
1>
1A
0B
1C
#363
#364
b0110 !
b0001 #
b0110 '
b0001 *
b0001 ,
b1110 -
00
13
04
15
07
08
#365
#366
b0111 !
b0010 #
b0111 '
b0010 *
b0010 ,
b1111 -
10
03
14
17
18
#367
#368
b1000 !
b0011 #
b1000 '
b0011 *
b0011 ,
b1000 -
00
13
04
05
07
18
09
0:
0<
0=
0>
1?
0A
0B
#369
#370
b1001 !
b0100 #
b1001 '
b0100 *
b0100 ,
b1011 -
10
03
14
17
08
19
1<
1=
#371
#372
b1010 !
b0101 #
b1010 '
b0101 *
b0101 ,
b1010 -
00
13
04
15
07
08
#373
#374
b1011 !
b0110 #
b1011 '
b0110 *
b0110 ,
b1011 -
10
03
14
17
18
#375
#376
b1100 !
b0111 #
b1100 '
b0111 *
b0111 ,
b1000 -
00
13
04
05
07
18
09
1:
0<
1=
0>
0A
0B
#377
#378
b1101 !
b1000 #
b1101 '
b1000 *
b1000 ,
b1111 -
10
03
14
17
08
19
1<
0=
1>
1A
1B
#379
#380
b1110 !
b1001 #
b1110 '
b1001 *
b1001 ,
b1110 -
00
13
04
15
07
08
#381
#382
b1111 !
b1010 #
b1111 '
b1010 *
b1010 ,
b1111 -
10
03
14
17
18
#383
#384
b0000 !
b1100 "
b1100 #
0&
b0000 '
b1100 (
b1100 *
0+
b1100 ,
b0000 -
b1100 .
00
01
03
04
05
06
07
08
09
0:
1;
0<
1=
0>
0?
0A
1B
0C
#385
#386
b0001 !
b1101 #
b0001 '
b1101 *
b1101 ,
10
13
#387
#388
b0010 !
b1110 #
b0010 '
b1110 *
b1110 ,
00
03
15
18
#389
#390
b0011 !
b1111 #
b0011 '
b1111 *
b1111 ,
10
13
#391
#392
b0100 !
b0000 #
1&
b0100 '
b0000 *
1+
b0000 ,
b1100 -
00
03
05
08
1:
0=
1>
1A
0B
1C
#393
#394
b0101 !
b0001 #
b0101 '
b0001 *
b0001 ,
10
13
#395
#396
b0110 !
b0010 #
b0110 '
b0010 *
b0010 ,
00
03
15
18
#397
#398
b0111 !
b0011 #
b0111 '
b0011 *
b0011 ,
10
13
#399
#400
b1000 !
b0100 #
b1000 '
b0100 *
b0100 ,
b1000 -
00
03
05
08
0:
1=
0>
1?
0A
0B
#401
#402
b1001 !
b0101 #
b1001 '
b0101 *
b0101 ,
10
13
#403
#404
b1010 !
b0110 #
b1010 '
b0110 *
b0110 ,
00
03
15
18
#405
#406
b1011 !
b0111 #
b1011 '
b0111 *
b0111 ,
10
13
#407
#408
b1100 !
b1000 #
b1100 '
b1000 *
b1000 ,
b1100 -
00
03
05
08
1:
0=
1>
1A
1B
#409
#410
b1101 !
b1001 #
b1101 '
b1001 *
b1001 ,
10
13
#411
#412
b1110 !
b1010 #
b1110 '
b1010 *
b1010 ,
00
03
15
18
#413
#414
b1111 !
b1011 #
b1111 '
b1011 *
b1011 ,
10
13
#415
