gdti7/full_add.vhdl
library ieee;
use ieee.std_logic_1164.all;

entity full_add is
  port (
    a, b, c_in : in std_logic;
    sum, c_out : out std_logic
  );
end full_add;

architecture behav of full_add is
begin
  sum <= (a xor b) xor c_in;
  c_out <= (c_in and (a xor b)) or (a and b);
end architecture;

gdti7/full_add_tb.vhdl
library ieee;
use ieee.std_logic_1164.all;

entity full_add_tb is end full_add_tb;

architecture behav of full_add_tb is
  component full_add
    port (a, b, c_in: in std_logic;  sum, c_out : out std_logic);
  end component;
  signal a,b,c_in,sum,c_out : std_logic;
begin
  full_add_0: full_add port map (a, b, c_in,  sum, c_out);

  process begin
    -- diese und die folgende Zeile ersetzen durch geeignete Testfaelle
    -- report "testbench selbst erstellen!" severity error;

    a <= '0';
    b <= '0';
    c_in <= '0';
    wait for 1 fs;
    assert sum = '0' report "bad result for input 0 0 0" severity error;
    assert c_out = '0' report "bad result for input 0 0 0" severity error;
    wait for 1 fs;

    a <= '1';
    b <= '0';
    c_in <= '0';
    wait for 1 fs;
    assert sum = '1' report "bad result for input 1 0 0" severity error;
    assert c_out = '0' report "bad result for input 1 0 0" severity error;
    wait for 1 fs;

    a <= '1';
    b <= '1';
    c_in <= '0';
    wait for 1 fs;
    assert sum = '0' report "bad result for input 1 1 0" severity error;
    assert c_out = '1' report "bad result for input 1 1 0" severity error;
    wait for 1 fs;

    a <= '1';
    b <= '1';
    c_in <= '1';
    wait for 1 fs;
    assert sum = '1' report "bad result for input 1 1 1" severity error;
    assert c_out = '1' report "bad result for input 1 1 1" severity error;
    wait for 1 fs;

    
    a <= '0';
    b <= '1';
    c_in <= '0';
    wait for 1 fs;
    assert sum = '1' report "bad result for input 0 1 0" severity error;
    assert c_out = '0' report "bad result for input 0 1 0" severity error;
    wait for 1 fs;

    a <= '0';
    b <= '1';
    c_in <= '1';
    wait for 1 fs;
    assert sum = '0' report "bad result for input 0 1 1" severity error;
    assert c_out = '1' report "bad result for input 0 1 1" severity error;
    wait for 1 fs;

    a <= '0';
    b <= '0';
    c_in <= '1';
    wait for 1 fs;
    assert sum = '1' report "bad result for input 0 0 1" severity error;
    assert c_out = '0' report "bad result for input 0 0 1" severity error;
    wait for 1 fs;


    a <= '1';
    b <= '0';
    c_in <= '1';
    wait for 1 fs;
    assert sum = '0' report "bad result for input 1 0 1" severity error;
    assert c_out = '1' report "bad result for input 1 0 1" severity error;
    wait for 1 fs;

    assert false report "end of test" severity note;
    wait; --  Wait forever; this will finish the simulation.
  end process;
end behav;

gdti7/out_full_add.vcd
$date
  Tue Jan 10 14:41:08 2023
$end
$version
  GHDL v0
$end
$timescale
  1 fs
$end
$scope module standard $end
$upscope $end
$scope module std_logic_1164 $end
$upscope $end
$scope module full_add_tb $end
$var reg 1 ! a $end
$var reg 1 " b $end
$var reg 1 # c_in $end
$var reg 1 $ sum $end
$var reg 1 % c_out $end
$scope module full_add_0 $end
$var reg 1 & a $end
$var reg 1 ' b $end
$var reg 1 ( c_in $end
$var reg 1 ) sum $end
$var reg 1 * c_out $end
$upscope $end
$upscope $end
$enddefinitions $end
#0
0!
0"
0#
0$
0%
0&
0'
0(
0)
0*
#1
#2
1!
1$
1&
1)
#3
#4
1"
0$
1%
1'
0)
1*
#5
#6
1#
1$
1(
1)
#7
#8
0!
0#
0%
0&
0(
0*
#9
#10
1#
0$
1%
1(
0)
1*
#11
#12
0"
1$
0%
0'
1)
0*
#13
#14
1!
0$
1%
1&
0)
1*
