gdti5/oder.vhdl
library ieee;
use ieee.std_logic_1164.all;

entity oder is
  port (
    a, b: in std_logic;
    y : out std_logic
  );
end oder;

architecture behav of oder is
begin
  y <= a or b;
end architecture;

gdti5/alu4or2.vhdl
library ieee;
use ieee.std_logic_1164.all;

entity alu4or2 is
  port (
    a, b: in std_logic_vector(3 downto 0);
    y : out std_logic_vector(3 downto 0)
  );
end alu4or2;

architecture behav of alu4or2 is
  component oder is port (a, b: in std_logic; y : out std_logic); end component;
begin
  or1: oder port map(a => a(0),b => b(0),y => y(0));
  or2: oder port map(a => a(1),b => b(1),y => y(1));
  or3: oder port map(a => a(2),b => b(2),y => y(2));
  or4: oder port map(a => a(3),b => b(3),y => y(3));
end architecture;

gdti5/alu4or2_tb.vhdl
library ieee;
use ieee.std_logic_1164.all;
use ieee.numeric_std.all;

entity alu4or2_tb is end alu4or2_tb;

architecture behav of alu4or2_tb is
  component alu4or2
    port ( a, b: in std_logic_vector(3 downto 0);
           y : out std_logic_vector(3 downto 0));
  end component;
  signal in1, in2, result : std_logic_vector(3 downto 0);
  signal expect : std_logic_vector(3 downto 0);
begin
  or2_0: alu4or2 port map (a=>in1, b=>in2, y=>result);

  process
    variable errcnt : integer:= 0;
    variable a,b,y : integer;
  begin
    for ai in 0 to 15 loop
      for bi in 0 to 15 loop
        in1 <= std_logic_vector(to_unsigned(ai, 4));
        in2 <= std_logic_vector(to_unsigned(bi, 4));
        for i in 0 to 3 loop
          a := (ai / (2**i)) mod 2;
          b := (bi / (2**i)) mod 2;
    -- die folgende Zeile muss and/or/xor machen, je nachdem was geprueft werden soll
          if (a=1) or (b=1) then y:=1; else y:=0; end if;
          if y=1 then expect(i)<='1'; else expect(i)<='0'; end if;
        end loop;
        wait for 1 fs;
        if expect /= result then
          errcnt := errcnt + 1;
          report "falsch" severity error;
        end if;
        wait for 1 fs;
      end loop;
    end loop;
    if errcnt=0 then
      report "Had no errors";
    else
      report "Had " & integer'image(errcnt) & " errors";
    end if;
    assert false report "end of test" severity note;
    wait; --  Wait forever; this will finish the simulation.
  end process;
end behav;

gdti5/out_alu4or2.vcd
$date
  Tue Dec  6 14:57:59 2022
$end
$version
  GHDL v0
$end
$timescale
  1 fs
$end
$scope module standard $end
$upscope $end
$scope module std_logic_1164 $end
$upscope $end
$scope module numeric_std $end
$upscope $end
$scope module alu4or2_tb $end
$var reg 4 ! in1[3:0] $end
$var reg 4 " in2[3:0] $end
$var reg 4 # result[3:0] $end
$var reg 4 $ expect[3:0] $end
$scope module or2_0 $end
$var reg 4 % a[3:0] $end
$var reg 4 & b[3:0] $end
$var reg 4 ' y[3:0] $end
$scope module or1 $end
$var reg 1 ( a $end
$var reg 1 ) b $end
$var reg 1 * y $end
$upscope $end
$scope module or2 $end
$var reg 1 + a $end
$var reg 1 , b $end
$var reg 1 - y $end
$upscope $end
$scope module or3 $end
$var reg 1 . a $end
$var reg 1 / b $end
$var reg 1 0 y $end
$upscope $end
$scope module or4 $end
$var reg 1 1 a $end
$var reg 1 2 b $end
$var reg 1 3 y $end
$upscope $end
$upscope $end
$upscope $end
$enddefinitions $end
#0
b0000 !
b0000 "
b0000 #
b0000 $
b0000 %
b0000 &
b0000 '
0(
0)
0*
0+
0,
0-
0.
0/
00
01
02
03
#1
#2
b0001 "
b0001 #
b0001 $
b0001 &
b0001 '
1)
1*
#3
#4
b0010 "
b0010 #
b0010 $
b0010 &
b0010 '
0)
0*
1,
1-
#5
#6
b0011 "
b0011 #
b0011 $
b0011 &
b0011 '
1)
1*
#7
#8
b0100 "
b0100 #
b0100 $
b0100 &
b0100 '
0)
0*
0,
0-
1/
10
#9
#10
b0101 "
b0101 #
b0101 $
b0101 &
b0101 '
1)
1*
#11
#12
b0110 "
b0110 #
b0110 $
b0110 &
b0110 '
0)
0*
1,
1-
#13
#14
b0111 "
b0111 #
b0111 $
b0111 &
b0111 '
1)
1*
#15
#16
b1000 "
b1000 #
b1000 $
b1000 &
b1000 '
0)
0*
0,
0-
0/
00
12
13
#17
#18
b1001 "
b1001 #
b1001 $
b1001 &
b1001 '
1)
1*
#19
#20
b1010 "
b1010 #
b1010 $
b1010 &
b1010 '
0)
0*
1,
1-
#21
#22
b1011 "
b1011 #
b1011 $
b1011 &
b1011 '
1)
1*
#23
#24
b1100 "
b1100 #
b1100 $
b1100 &
b1100 '
0)
0*
0,
0-
1/
10
#25
#26
b1101 "
b1101 #
b1101 $
b1101 &
b1101 '
1)
1*
#27
#28
b1110 "
b1110 #
b1110 $
b1110 &
b1110 '
0)
0*
1,
1-
#29
#30
b1111 "
b1111 #
b1111 $
b1111 &
b1111 '
1)
1*
#31
#32
b0001 !
b0000 "
b0001 #
b0001 $
b0001 %
b0000 &
b0001 '
1(
0)
0,
0-
0/
00
02
03
#33
#34
b0001 "
b0001 &
1)
#35
#36
b0010 "
b0011 #
b0011 $
b0010 &
b0011 '
0)
1,
1-
#37
#38
b0011 "
b0011 &
1)
#39
#40
b0100 "
b0101 #
b0101 $
b0100 &
b0101 '
0)
0,
0-
1/
10
#41
#42
b0101 "
b0101 &
1)
#43
#44
b0110 "
b0111 #
b0111 $
b0110 &
b0111 '
0)
1,
1-
#45
#46
b0111 "
b0111 &
1)
#47
#48
b1000 "
b1001 #
b1001 $
b1000 &
b1001 '
0)
0,
0-
0/
00
12
13
#49
#50
b1001 "
b1001 &
1)
#51
#52
b1010 "
b1011 #
b1011 $
b1010 &
b1011 '
0)
1,
1-
#53
#54
b1011 "
b1011 &
1)
#55
#56
b1100 "
b1101 #
b1101 $
b1100 &
b1101 '
0)
0,
0-
1/
10
#57
#58
b1101 "
b1101 &
1)
#59
#60
b1110 "
b1111 #
b1111 $
b1110 &
b1111 '
0)
1,
1-
#61
#62
b1111 "
b1111 &
1)
#63
#64
b0010 !
b0000 "
b0010 #
b0010 $
b0010 %
b0000 &
b0010 '
0(
0)
0*
1+
0,
0/
00
02
03
#65
#66
b0001 "
b0011 #
b0011 $
b0001 &
b0011 '
1)
1*
#67
#68
b0010 "
b0010 #
b0010 $
b0010 &
b0010 '
0)
0*
1,
#69
#70
b0011 "
b0011 #
b0011 $
b0011 &
b0011 '
1)
1*
#71
#72
b0100 "
b0110 #
b0110 $
b0100 &
b0110 '
0)
0*
0,
1/
10
#73
#74
b0101 "
b0111 #
b0111 $
b0101 &
b0111 '
1)
1*
#75
#76
b0110 "
b0110 #
b0110 $
b0110 &
b0110 '
0)
0*
1,
#77
#78
b0111 "
b0111 #
b0111 $
b0111 &
b0111 '
1)
1*
#79
#80
b1000 "
b1010 #
b1010 $
b1000 &
b1010 '
0)
0*
0,
0/
00
12
13
#81
#82
b1001 "
b1011 #
b1011 $
b1001 &
b1011 '
1)
1*
#83
#84
b1010 "
b1010 #
b1010 $
b1010 &
b1010 '
0)
0*
1,
#85
#86
b1011 "
b1011 #
b1011 $
b1011 &
b1011 '
1)
1*
#87
#88
b1100 "
b1110 #
b1110 $
b1100 &
b1110 '
0)
0*
0,
1/
10
#89
#90
b1101 "
b1111 #
b1111 $
b1101 &
b1111 '
1)
1*
#91
#92
b1110 "
b1110 #
b1110 $
b1110 &
b1110 '
0)
0*
1,
#93
#94
b1111 "
b1111 #
b1111 $
b1111 &
b1111 '
1)
1*
#95
#96
b0011 !
b0000 "
b0011 #
b0011 $
b0011 %
b0000 &
b0011 '
1(
0)
0,
0/
00
02
03
#97
#98
b0001 "
b0001 &
1)
#99
#100
b0010 "
b0010 &
0)
1,
#101
#102
b0011 "
b0011 &
1)
#103
#104
b0100 "
b0111 #
b0111 $
b0100 &
b0111 '
0)
0,
1/
10
#105
#106
b0101 "
b0101 &
1)
#107
#108
b0110 "
b0110 &
0)
1,
#109
#110
b0111 "
b0111 &
1)
#111
#112
b1000 "
b1011 #
b1011 $
b1000 &
b1011 '
0)
0,
0/
00
12
13
#113
#114
b1001 "
b1001 &
1)
#115
#116
b1010 "
b1010 &
0)
1,
#117
#118
b1011 "
b1011 &
1)
#119
#120
b1100 "
b1111 #
b1111 $
b1100 &
b1111 '
0)
0,
1/
10
#121
#122
b1101 "
b1101 &
1)
#123
#124
b1110 "
b1110 &
0)
1,
#125
#126
b1111 "
b1111 &
1)
#127
#128
b0100 !
b0000 "
b0100 #
b0100 $
b0100 %
b0000 &
b0100 '
0(
0)
0*
0+
0,
0-
1.
0/
02
03
#129
#130
b0001 "
b0101 #
b0101 $
b0001 &
b0101 '
1)
1*
#131
#132
b0010 "
b0110 #
b0110 $
b0010 &
b0110 '
0)
0*
1,
1-
#133
#134
b0011 "
b0111 #
b0111 $
b0011 &
b0111 '
1)
1*
#135
#136
b0100 "
b0100 #
b0100 $
b0100 &
b0100 '
0)
0*
0,
0-
1/
#137
#138
b0101 "
b0101 #
b0101 $
b0101 &
b0101 '
1)
1*
#139
#140
b0110 "
b0110 #
b0110 $
b0110 &
b0110 '
0)
0*
1,
1-
#141
#142
b0111 "
b0111 #
b0111 $
b0111 &
b0111 '
1)
1*
#143
#144
b1000 "
b1100 #
b1100 $
b1000 &
b1100 '
0)
0*
0,
0-
0/
12
13
#145
#146
b1001 "
b1101 #
b1101 $
b1001 &
b1101 '
1)
1*
#147
#148
b1010 "
b1110 #
b1110 $
b1010 &
b1110 '
0)
0*
1,
1-
#149
#150
b1011 "
b1111 #
b1111 $
b1011 &
b1111 '
1)
1*
#151
#152
b1100 "
b1100 #
b1100 $
b1100 &
b1100 '
0)
0*
0,
0-
1/
#153
#154
b1101 "
b1101 #
b1101 $
b1101 &
b1101 '
1)
1*
#155
#156
b1110 "
b1110 #
b1110 $
b1110 &
b1110 '
0)
0*
1,
1-
#157
#158
b1111 "
b1111 #
b1111 $
b1111 &
b1111 '
1)
1*
#159
#160
b0101 !
b0000 "
b0101 #
b0101 $
b0101 %
b0000 &
b0101 '
1(
0)
0,
0-
0/
02
03
#161
#162
b0001 "
b0001 &
1)
#163
#164
b0010 "
b0111 #
b0111 $
b0010 &
b0111 '
0)
1,
1-
#165
#166
b0011 "
b0011 &
1)
#167
#168
b0100 "
b0101 #
b0101 $
b0100 &
b0101 '
0)
0,
0-
1/
#169
#170
b0101 "
b0101 &
1)
#171
#172
b0110 "
b0111 #
b0111 $
b0110 &
b0111 '
0)
1,
1-
#173
#174
b0111 "
b0111 &
1)
#175
#176
b1000 "
b1101 #
b1101 $
b1000 &
b1101 '
0)
0,
0-
0/
12
13
#177
#178
b1001 "
b1001 &
1)
#179
#180
b1010 "
b1111 #
b1111 $
b1010 &
b1111 '
0)
1,
1-
#181
#182
b1011 "
b1011 &
1)
#183
#184
b1100 "
b1101 #
b1101 $
b1100 &
b1101 '
0)
0,
0-
1/
#185
#186
b1101 "
b1101 &
1)
#187
#188
b1110 "
b1111 #
b1111 $
b1110 &
b1111 '
0)
1,
1-
#189
#190
b1111 "
b1111 &
1)
#191
#192
b0110 !
b0000 "
b0110 #
b0110 $
b0110 %
b0000 &
b0110 '
0(
0)
0*
1+
0,
0/
02
03
#193
#194
b0001 "
b0111 #
b0111 $
b0001 &
b0111 '
1)
1*
#195
#196
b0010 "
b0110 #
b0110 $
b0010 &
b0110 '
0)
0*
1,
#197
#198
b0011 "
b0111 #
b0111 $
b0011 &
b0111 '
1)
1*
#199
#200
b0100 "
b0110 #
b0110 $
b0100 &
b0110 '
0)
0*
0,
1/
#201
#202
b0101 "
b0111 #
b0111 $
b0101 &
b0111 '
1)
1*
#203
#204
b0110 "
b0110 #
b0110 $
b0110 &
b0110 '
0)
0*
1,
#205
#206
b0111 "
b0111 #
b0111 $
b0111 &
b0111 '
1)
1*
#207
#208
b1000 "
b1110 #
b1110 $
b1000 &
b1110 '
0)
0*
0,
0/
12
13
#209
#210
b1001 "
b1111 #
b1111 $
b1001 &
b1111 '
1)
1*
#211
#212
b1010 "
b1110 #
b1110 $
b1010 &
b1110 '
0)
0*
1,
#213
#214
b1011 "
b1111 #
b1111 $
b1011 &
b1111 '
1)
1*
#215
#216
b1100 "
b1110 #
b1110 $
b1100 &
b1110 '
0)
0*
0,
1/
#217
#218
b1101 "
b1111 #
b1111 $
b1101 &
b1111 '
1)
1*
#219
#220
b1110 "
b1110 #
b1110 $
b1110 &
b1110 '
0)
0*
1,
#221
#222
b1111 "
b1111 #
b1111 $
b1111 &
b1111 '
1)
1*
#223
#224
b0111 !
b0000 "
b0111 #
b0111 $
b0111 %
b0000 &
b0111 '
1(
0)
0,
0/
02
03
#225
#226
b0001 "
b0001 &
1)
#227
#228
b0010 "
b0010 &
0)
1,
#229
#230
b0011 "
b0011 &
1)
#231
#232
b0100 "
b0100 &
0)
0,
1/
#233
#234
b0101 "
b0101 &
1)
#235
#236
b0110 "
b0110 &
0)
1,
#237
#238
b0111 "
b0111 &
1)
#239
#240
b1000 "
b1111 #
b1111 $
b1000 &
b1111 '
0)
0,
0/
12
13
#241
#242
b1001 "
b1001 &
1)
#243
#244
b1010 "
b1010 &
0)
1,
#245
#246
b1011 "
b1011 &
1)
#247
#248
b1100 "
b1100 &
0)
0,
1/
#249
#250
b1101 "
b1101 &
1)
#251
#252
b1110 "
b1110 &
0)
1,
#253
#254
b1111 "
b1111 &
1)
#255
#256
b1000 !
b0000 "
b1000 #
b1000 $
b1000 %
b0000 &
b1000 '
0(
0)
0*
0+
0,
0-
0.
0/
00
11
02
#257
#258
b0001 "
b1001 #
b1001 $
b0001 &
b1001 '
1)
1*
#259
#260
b0010 "
b1010 #
b1010 $
b0010 &
b1010 '
0)
0*
1,
1-
#261
#262
b0011 "
b1011 #
b1011 $
b0011 &
b1011 '
1)
1*
#263
#264
b0100 "
b1100 #
b1100 $
b0100 &
b1100 '
0)
0*
0,
0-
1/
10
#265
#266
b0101 "
b1101 #
b1101 $
b0101 &
b1101 '
1)
1*
#267
#268
b0110 "
b1110 #
b1110 $
b0110 &
b1110 '
0)
0*
1,
1-
#269
#270
b0111 "
b1111 #
b1111 $
b0111 &
b1111 '
1)
1*
#271
#272
b1000 "
b1000 #
b1000 $
b1000 &
b1000 '
0)
0*
0,
0-
0/
00
12
#273
#274
b1001 "
b1001 #
b1001 $
b1001 &
b1001 '
1)
1*
#275
#276
b1010 "
b1010 #
b1010 $
b1010 &
b1010 '
0)
0*
1,
1-
#277
#278
b1011 "
b1011 #
b1011 $
b1011 &
b1011 '
1)
1*
#279
#280
b1100 "
b1100 #
b1100 $
b1100 &
b1100 '
0)
0*
0,
0-
1/
10
#281
#282
b1101 "
b1101 #
b1101 $
b1101 &
b1101 '
1)
1*
#283
#284
b1110 "
b1110 #
b1110 $
b1110 &
b1110 '
0)
0*
1,
1-
#285
#286
b1111 "
b1111 #
b1111 $
b1111 &
b1111 '
1)
1*
#287
#288
b1001 !
b0000 "
b1001 #
b1001 $
b1001 %
b0000 &
b1001 '
1(
0)
0,
0-
0/
00
02
#289
#290
b0001 "
b0001 &
1)
#291
#292
b0010 "
b1011 #
b1011 $
b0010 &
b1011 '
0)
1,
1-
#293
#294
b0011 "
b0011 &
1)
#295
#296
b0100 "
b1101 #
b1101 $
b0100 &
b1101 '
0)
0,
0-
1/
10
#297
#298
b0101 "
b0101 &
1)
#299
#300
b0110 "
b1111 #
b1111 $
b0110 &
b1111 '
0)
1,
1-
#301
#302
b0111 "
b0111 &
1)
#303
#304
b1000 "
b1001 #
b1001 $
b1000 &
b1001 '
0)
0,
0-
0/
00
12
#305
#306
b1001 "
b1001 &
1)
#307
#308
b1010 "
b1011 #
b1011 $
b1010 &
b1011 '
0)
1,
1-
#309
#310
b1011 "
b1011 &
1)
#311
#312
b1100 "
b1101 #
b1101 $
b1100 &
b1101 '
0)
0,
0-
1/
10
#313
#314
b1101 "
b1101 &
1)
#315
#316
b1110 "
b1111 #
b1111 $
b1110 &
b1111 '
0)
1,
1-
#317
#318
b1111 "
b1111 &
1)
#319
#320
b1010 !
b0000 "
b1010 #
b1010 $
b1010 %
b0000 &
b1010 '
0(
0)
0*
1+
0,
0/
00
02
#321
#322
b0001 "
b1011 #
b1011 $
b0001 &
b1011 '
1)
1*
#323
#324
b0010 "
b1010 #
b1010 $
b0010 &
b1010 '
0)
0*
1,
#325
#326
b0011 "
b1011 #
b1011 $
b0011 &
b1011 '
1)
1*
#327
#328
b0100 "
b1110 #
b1110 $
b0100 &
b1110 '
0)
0*
0,
1/
10
#329
#330
b0101 "
b1111 #
b1111 $
b0101 &
b1111 '
1)
1*
#331
#332
b0110 "
b1110 #
b1110 $
b0110 &
b1110 '
0)
0*
1,
#333
#334
b0111 "
b1111 #
b1111 $
b0111 &
b1111 '
1)
1*
#335
#336
b1000 "
b1010 #
b1010 $
b1000 &
b1010 '
0)
0*
0,
0/
00
12
#337
#338
b1001 "
b1011 #
b1011 $
b1001 &
b1011 '
1)
1*
#339
#340
b1010 "
b1010 #
b1010 $
b1010 &
b1010 '
0)
0*
1,
#341
#342
b1011 "
b1011 #
b1011 $
b1011 &
b1011 '
1)
1*
#343
#344
b1100 "
b1110 #
b1110 $
b1100 &
b1110 '
0)
0*
0,
1/
10
#345
#346
b1101 "
b1111 #
b1111 $
b1101 &
b1111 '
1)
1*
#347
#348
b1110 "
b1110 #
b1110 $
b1110 &
b1110 '
0)
0*
1,
#349
#350
b1111 "
b1111 #
b1111 $
b1111 &
b1111 '
1)
1*
#351
#352
b1011 !
b0000 "
b1011 #
b1011 $
b1011 %
b0000 &
b1011 '
1(
0)
0,
0/
00
02
#353
#354
b0001 "
b0001 &
1)
#355
#356
b0010 "
b0010 &
0)
1,
#357
#358
b0011 "
b0011 &
1)
#359
#360
b0100 "
b1111 #
b1111 $
b0100 &
b1111 '
0)
0,
1/
10
#361
#362
b0101 "
b0101 &
1)
#363
#364
b0110 "
b0110 &
0)
1,
#365
#366
b0111 "
b0111 &
1)
#367
#368
b1000 "
b1011 #
b1011 $
b1000 &
b1011 '
0)
0,
0/
00
12
#369
#370
b1001 "
b1001 &
1)
#371
#372
b1010 "
b1010 &
0)
1,
#373
#374
b1011 "
b1011 &
1)
#375
#376
b1100 "
b1111 #
b1111 $
b1100 &
b1111 '
0)
0,
1/
10
#377
#378
b1101 "
b1101 &
1)
#379
#380
b1110 "
b1110 &
0)
1,
#381
#382
b1111 "
b1111 &
1)
#383
#384
b1100 !
b0000 "
b1100 #
b1100 $
b1100 %
b0000 &
b1100 '
0(
0)
0*
0+
0,
0-
1.
0/
02
#385
#386
b0001 "
b1101 #
b1101 $
b0001 &
b1101 '
1)
1*
#387
#388
b0010 "
b1110 #
b1110 $
b0010 &
b1110 '
0)
0*
1,
1-
#389
#390
b0011 "
b1111 #
b1111 $
b0011 &
b1111 '
1)
1*
#391
#392
b0100 "
b1100 #
b1100 $
b0100 &
b1100 '
0)
0*
0,
0-
1/
#393
#394
b0101 "
b1101 #
b1101 $
b0101 &
b1101 '
1)
1*
#395
#396
b0110 "
b1110 #
b1110 $
b0110 &
b1110 '
0)
0*
1,
1-
#397
#398
b0111 "
b1111 #
b1111 $
b0111 &
b1111 '
1)
1*
#399
#400
b1000 "
b1100 #
b1100 $
b1000 &
b1100 '
0)
0*
0,
0-
0/
12
#401
#402
b1001 "
b1101 #
b1101 $
b1001 &
b1101 '
1)
1*
#403
#404
b1010 "
b1110 #
b1110 $
b1010 &
b1110 '
0)
0*
1,
1-
#405
#406
b1011 "
b1111 #
b1111 $
b1011 &
b1111 '
1)
1*
#407
#408
b1100 "
b1100 #
b1100 $
b1100 &
b1100 '
0)
0*
0,
0-
1/
#409
#410
b1101 "
b1101 #
b1101 $
b1101 &
b1101 '
1)
1*
#411
#412
b1110 "
b1110 #
b1110 $
b1110 &
b1110 '
0)
0*
1,
1-
#413
#414
b1111 "
b1111 #
b1111 $
b1111 &
b1111 '
1)
1*
#415
#416
b1101 !
b0000 "
b1101 #
b1101 $
b1101 %
b0000 &
b1101 '
1(
0)
0,
0-
0/
02
#417
#418
b0001 "
b0001 &
1)
#419
#420
b0010 "
b1111 #
b1111 $
b0010 &
b1111 '
0)
1,
1-
#421
#422
b0011 "
b0011 &
1)
#423
#424
b0100 "
b1101 #
b1101 $
b0100 &
b1101 '
0)
0,
0-
1/
#425
#426
b0101 "
b0101 &
1)
#427
#428
b0110 "
b1111 #
b1111 $
b0110 &
b1111 '
0)
1,
1-
#429
#430
b0111 "
b0111 &
1)
#431
#432
b1000 "
b1101 #
b1101 $
b1000 &
b1101 '
0)
0,
0-
0/
12
#433
#434
b1001 "
b1001 &
1)
#435
#436
b1010 "
b1111 #
b1111 $
b1010 &
b1111 '
0)
1,
1-
#437
#438
b1011 "
b1011 &
1)
#439
#440
b1100 "
b1101 #
b1101 $
b1100 &
b1101 '
0)
0,
0-
1/
#441
#442
b1101 "
b1101 &
1)
#443
#444
b1110 "
b1111 #
b1111 $
b1110 &
b1111 '
0)
1,
1-
#445
#446
b1111 "
b1111 &
1)
#447
#448
b1110 !
b0000 "
b1110 #
b1110 $
b1110 %
b0000 &
b1110 '
0(
0)
0*
1+
0,
0/
02
#449
#450
b0001 "
b1111 #
b1111 $
b0001 &
b1111 '
1)
1*
#451
#452
b0010 "
b1110 #
b1110 $
b0010 &
b1110 '
0)
0*
1,
#453
#454
b0011 "
b1111 #
b1111 $
b0011 &
b1111 '
1)
1*
#455
#456
b0100 "
b1110 #
b1110 $
b0100 &
b1110 '
0)
0*
0,
1/
#457
#458
b0101 "
b1111 #
b1111 $
b0101 &
b1111 '
1)
1*
#459
#460
b0110 "
b1110 #
b1110 $
b0110 &
b1110 '
0)
0*
1,
#461
#462
b0111 "
b1111 #
b1111 $
b0111 &
b1111 '
1)
1*
#463
#464
b1000 "
b1110 #
b1110 $
b1000 &
b1110 '
0)
0*
0,
0/
12
#465
#466
b1001 "
b1111 #
b1111 $
b1001 &
b1111 '
1)
1*
#467
#468
b1010 "
b1110 #
b1110 $
b1010 &
b1110 '
0)
0*
1,
#469
#470
b1011 "
b1111 #
b1111 $
b1011 &
b1111 '
1)
1*
#471
#472
b1100 "
b1110 #
b1110 $
b1100 &
b1110 '
0)
0*
0,
1/
#473
#474
b1101 "
b1111 #
b1111 $
b1101 &
b1111 '
1)
1*
#475
#476
b1110 "
b1110 #
b1110 $
b1110 &
b1110 '
0)
0*
1,
#477
#478
b1111 "
b1111 #
b1111 $
b1111 &
b1111 '
1)
1*
#479
#480
b1111 !
b0000 "
b1111 %
b0000 &
1(
0)
0,
0/
02
#481
#482
b0001 "
b0001 &
1)
#483
#484
b0010 "
b0010 &
0)
1,
#485
#486
b0011 "
b0011 &
1)
#487
#488
b0100 "
b0100 &
0)
0,
1/
#489
#490
b0101 "
b0101 &
1)
#491
#492
b0110 "
b0110 &
0)
1,
#493
#494
b0111 "
b0111 &
1)
#495
#496
b1000 "
b1000 &
0)
0,
0/
12
#497
#498
b1001 "
b1001 &
1)
#499
#500
b1010 "
b1010 &
0)
1,
#501
#502
b1011 "
b1011 &
1)
#503
#504
b1100 "
b1100 &
0)
0,
1/
#505
#506
b1101 "
b1101 &
1)
#507
#508
b1110 "
b1110 &
0)
1,
#509
#510
b1111 "
b1111 &
1)
