gdti8/alu4and2.vhdl
library ieee;
use ieee.std_logic_1164.all;

entity alu4and2 is
  port (
    a, b: in std_logic_vector(3 downto 0);
    y : out std_logic_vector(3 downto 0)
  );
end alu4and2;

architecture behav of alu4and2 is
begin
  y <= a and b;
end architecture;

gdti5/alu4and2_tb.vhdl
library ieee;
use ieee.std_logic_1164.all;
use ieee.numeric_std.all;

entity alu4and2_tb is end alu4and2_tb;

architecture behav of alu4and2_tb is
  component alu4and2
    port ( a, b: in std_logic_vector(3 downto 0);
           y : out std_logic_vector(3 downto 0));
  end component;
  signal in1, in2, result : std_logic_vector(3 downto 0);
  signal expect : std_logic_vector(3 downto 0);
begin
  or2_0: alu4and2 port map (a=>in1, b=>in2, y=>result);

  process
    variable errcnt : integer:= 0;
    variable a,b,y : integer;
  begin
    for ai in 0 to 15 loop
      for bi in 0 to 15 loop
        in1 <= std_logic_vector(to_unsigned(ai, 4));
        in2 <= std_logic_vector(to_unsigned(bi, 4));
        for i in 0 to 3 loop
          a := (ai / (2**i)) mod 2;
          b := (bi / (2**i)) mod 2;
    -- die folgende Zeile muss and/or/xor machen, je nachdem was geprueft werden soll
          if (a=1) and (b=1) then y:=1; else y:=0; end if;
          if y=1 then expect(i)<='1'; else expect(i)<='0'; end if;
        end loop;
        wait for 1 fs;
        if expect /= result then
          errcnt := errcnt + 1;
          report "falsch" severity error;
        end if;
        wait for 1 fs;
      end loop;
    end loop;
    if errcnt=0 then
      report "Had no errors";
    else
      report "Had " & integer'image(errcnt) & " errors";
    end if;
    assert false report "end of test" severity note;
    wait; --  Wait forever; this will finish the simulation.
  end process;
end behav;

gdti5/out_alu4and2.vcd
$date
  Tue Dec  6 14:58:07 2022
$end
$version
  GHDL v0
$end
$timescale
  1 fs
$end
$scope module standard $end
$upscope $end
$scope module std_logic_1164 $end
$upscope $end
$scope module numeric_std $end
$upscope $end
$scope module alu4and2_tb $end
$var reg 4 ! in1[3:0] $end
$var reg 4 " in2[3:0] $end
$var reg 4 # result[3:0] $end
$var reg 4 $ expect[3:0] $end
$scope module or2_0 $end
$var reg 4 % a[3:0] $end
$var reg 4 & b[3:0] $end
$var reg 4 ' y[3:0] $end
$upscope $end
$upscope $end
$enddefinitions $end
#0
b0000 !
b0000 "
b0000 #
b0000 $
b0000 %
b0000 &
b0000 '
#1
#2
b0001 "
b0001 &
#3
#4
b0010 "
b0010 &
#5
#6
b0011 "
b0011 &
#7
#8
b0100 "
b0100 &
#9
#10
b0101 "
b0101 &
#11
#12
b0110 "
b0110 &
#13
#14
b0111 "
b0111 &
#15
#16
b1000 "
b1000 &
#17
#18
b1001 "
b1001 &
#19
#20
b1010 "
b1010 &
#21
#22
b1011 "
b1011 &
#23
#24
b1100 "
b1100 &
#25
#26
b1101 "
b1101 &
#27
#28
b1110 "
b1110 &
#29
#30
b1111 "
b1111 &
#31
#32
b0001 !
b0000 "
b0001 %
b0000 &
#33
#34
b0001 "
b0001 #
b0001 $
b0001 &
b0001 '
#35
#36
b0010 "
b0000 #
b0000 $
b0010 &
b0000 '
#37
#38
b0011 "
b0001 #
b0001 $
b0011 &
b0001 '
#39
#40
b0100 "
b0000 #
b0000 $
b0100 &
b0000 '
#41
#42
b0101 "
b0001 #
b0001 $
b0101 &
b0001 '
#43
#44
b0110 "
b0000 #
b0000 $
b0110 &
b0000 '
#45
#46
b0111 "
b0001 #
b0001 $
b0111 &
b0001 '
#47
#48
b1000 "
b0000 #
b0000 $
b1000 &
b0000 '
#49
#50
b1001 "
b0001 #
b0001 $
b1001 &
b0001 '
#51
#52
b1010 "
b0000 #
b0000 $
b1010 &
b0000 '
#53
#54
b1011 "
b0001 #
b0001 $
b1011 &
b0001 '
#55
#56
b1100 "
b0000 #
b0000 $
b1100 &
b0000 '
#57
#58
b1101 "
b0001 #
b0001 $
b1101 &
b0001 '
#59
#60
b1110 "
b0000 #
b0000 $
b1110 &
b0000 '
#61
#62
b1111 "
b0001 #
b0001 $
b1111 &
b0001 '
#63
#64
b0010 !
b0000 "
b0000 #
b0000 $
b0010 %
b0000 &
b0000 '
#65
#66
b0001 "
b0001 &
#67
#68
b0010 "
b0010 #
b0010 $
b0010 &
b0010 '
#69
#70
b0011 "
b0011 &
#71
#72
b0100 "
b0000 #
b0000 $
b0100 &
b0000 '
#73
#74
b0101 "
b0101 &
#75
#76
b0110 "
b0010 #
b0010 $
b0110 &
b0010 '
#77
#78
b0111 "
b0111 &
#79
#80
b1000 "
b0000 #
b0000 $
b1000 &
b0000 '
#81
#82
b1001 "
b1001 &
#83
#84
b1010 "
b0010 #
b0010 $
b1010 &
b0010 '
#85
#86
b1011 "
b1011 &
#87
#88
b1100 "
b0000 #
b0000 $
b1100 &
b0000 '
#89
#90
b1101 "
b1101 &
#91
#92
b1110 "
b0010 #
b0010 $
b1110 &
b0010 '
#93
#94
b1111 "
b1111 &
#95
#96
b0011 !
b0000 "
b0000 #
b0000 $
b0011 %
b0000 &
b0000 '
#97
#98
b0001 "
b0001 #
b0001 $
b0001 &
b0001 '
#99
#100
b0010 "
b0010 #
b0010 $
b0010 &
b0010 '
#101
#102
b0011 "
b0011 #
b0011 $
b0011 &
b0011 '
#103
#104
b0100 "
b0000 #
b0000 $
b0100 &
b0000 '
#105
#106
b0101 "
b0001 #
b0001 $
b0101 &
b0001 '
#107
#108
b0110 "
b0010 #
b0010 $
b0110 &
b0010 '
#109
#110
b0111 "
b0011 #
b0011 $
b0111 &
b0011 '
#111
#112
b1000 "
b0000 #
b0000 $
b1000 &
b0000 '
#113
#114
b1001 "
b0001 #
b0001 $
b1001 &
b0001 '
#115
#116
b1010 "
b0010 #
b0010 $
b1010 &
b0010 '
#117
#118
b1011 "
b0011 #
b0011 $
b1011 &
b0011 '
#119
#120
b1100 "
b0000 #
b0000 $
b1100 &
b0000 '
#121
#122
b1101 "
b0001 #
b0001 $
b1101 &
b0001 '
#123
#124
b1110 "
b0010 #
b0010 $
b1110 &
b0010 '
#125
#126
b1111 "
b0011 #
b0011 $
b1111 &
b0011 '
#127
#128
b0100 !
b0000 "
b0000 #
b0000 $
b0100 %
b0000 &
b0000 '
#129
#130
b0001 "
b0001 &
#131
#132
b0010 "
b0010 &
#133
#134
b0011 "
b0011 &
#135
#136
b0100 "
b0100 #
b0100 $
b0100 &
b0100 '
#137
#138
b0101 "
b0101 &
#139
#140
b0110 "
b0110 &
#141
#142
b0111 "
b0111 &
#143
#144
b1000 "
b0000 #
b0000 $
b1000 &
b0000 '
#145
#146
b1001 "
b1001 &
#147
#148
b1010 "
b1010 &
#149
#150
b1011 "
b1011 &
#151
#152
b1100 "
b0100 #
b0100 $
b1100 &
b0100 '
#153
#154
b1101 "
b1101 &
#155
#156
b1110 "
b1110 &
#157
#158
b1111 "
b1111 &
#159
#160
b0101 !
b0000 "
b0000 #
b0000 $
b0101 %
b0000 &
b0000 '
#161
#162
b0001 "
b0001 #
b0001 $
b0001 &
b0001 '
#163
#164
b0010 "
b0000 #
b0000 $
b0010 &
b0000 '
#165
#166
b0011 "
b0001 #
b0001 $
b0011 &
b0001 '
#167
#168
b0100 "
b0100 #
b0100 $
b0100 &
b0100 '
#169
#170
b0101 "
b0101 #
b0101 $
b0101 &
b0101 '
#171
#172
b0110 "
b0100 #
b0100 $
b0110 &
b0100 '
#173
#174
b0111 "
b0101 #
b0101 $
b0111 &
b0101 '
#175
#176
b1000 "
b0000 #
b0000 $
b1000 &
b0000 '
#177
#178
b1001 "
b0001 #
b0001 $
b1001 &
b0001 '
#179
#180
b1010 "
b0000 #
b0000 $
b1010 &
b0000 '
#181
#182
b1011 "
b0001 #
b0001 $
b1011 &
b0001 '
#183
#184
b1100 "
b0100 #
b0100 $
b1100 &
b0100 '
#185
#186
b1101 "
b0101 #
b0101 $
b1101 &
b0101 '
#187
#188
b1110 "
b0100 #
b0100 $
b1110 &
b0100 '
#189
#190
b1111 "
b0101 #
b0101 $
b1111 &
b0101 '
#191
#192
b0110 !
b0000 "
b0000 #
b0000 $
b0110 %
b0000 &
b0000 '
#193
#194
b0001 "
b0001 &
#195
#196
b0010 "
b0010 #
b0010 $
b0010 &
b0010 '
#197
#198
b0011 "
b0011 &
#199
#200
b0100 "
b0100 #
b0100 $
b0100 &
b0100 '
#201
#202
b0101 "
b0101 &
#203
#204
b0110 "
b0110 #
b0110 $
b0110 &
b0110 '
#205
#206
b0111 "
b0111 &
#207
#208
b1000 "
b0000 #
b0000 $
b1000 &
b0000 '
#209
#210
b1001 "
b1001 &
#211
#212
b1010 "
b0010 #
b0010 $
b1010 &
b0010 '
#213
#214
b1011 "
b1011 &
#215
#216
b1100 "
b0100 #
b0100 $
b1100 &
b0100 '
#217
#218
b1101 "
b1101 &
#219
#220
b1110 "
b0110 #
b0110 $
b1110 &
b0110 '
#221
#222
b1111 "
b1111 &
#223
#224
b0111 !
b0000 "
b0000 #
b0000 $
b0111 %
b0000 &
b0000 '
#225
#226
b0001 "
b0001 #
b0001 $
b0001 &
b0001 '
#227
#228
b0010 "
b0010 #
b0010 $
b0010 &
b0010 '
#229
#230
b0011 "
b0011 #
b0011 $
b0011 &
b0011 '
#231
#232
b0100 "
b0100 #
b0100 $
b0100 &
b0100 '
#233
#234
b0101 "
b0101 #
b0101 $
b0101 &
b0101 '
#235
#236
b0110 "
b0110 #
b0110 $
b0110 &
b0110 '
#237
#238
b0111 "
b0111 #
b0111 $
b0111 &
b0111 '
#239
#240
b1000 "
b0000 #
b0000 $
b1000 &
b0000 '
#241
#242
b1001 "
b0001 #
b0001 $
b1001 &
b0001 '
#243
#244
b1010 "
b0010 #
b0010 $
b1010 &
b0010 '
#245
#246
b1011 "
b0011 #
b0011 $
b1011 &
b0011 '
#247
#248
b1100 "
b0100 #
b0100 $
b1100 &
b0100 '
#249
#250
b1101 "
b0101 #
b0101 $
b1101 &
b0101 '
#251
#252
b1110 "
b0110 #
b0110 $
b1110 &
b0110 '
#253
#254
b1111 "
b0111 #
b0111 $
b1111 &
b0111 '
#255
#256
b1000 !
b0000 "
b0000 #
b0000 $
b1000 %
b0000 &
b0000 '
#257
#258
b0001 "
b0001 &
#259
#260
b0010 "
b0010 &
#261
#262
b0011 "
b0011 &
#263
#264
b0100 "
b0100 &
#265
#266
b0101 "
b0101 &
#267
#268
b0110 "
b0110 &
#269
#270
b0111 "
b0111 &
#271
#272
b1000 "
b1000 #
b1000 $
b1000 &
b1000 '
#273
#274
b1001 "
b1001 &
#275
#276
b1010 "
b1010 &
#277
#278
b1011 "
b1011 &
#279
#280
b1100 "
b1100 &
#281
#282
b1101 "
b1101 &
#283
#284
b1110 "
b1110 &
#285
#286
b1111 "
b1111 &
#287
#288
b1001 !
b0000 "
b0000 #
b0000 $
b1001 %
b0000 &
b0000 '
#289
#290
b0001 "
b0001 #
b0001 $
b0001 &
b0001 '
#291
#292
b0010 "
b0000 #
b0000 $
b0010 &
b0000 '
#293
#294
b0011 "
b0001 #
b0001 $
b0011 &
b0001 '
#295
#296
b0100 "
b0000 #
b0000 $
b0100 &
b0000 '
#297
#298
b0101 "
b0001 #
b0001 $
b0101 &
b0001 '
#299
#300
b0110 "
b0000 #
b0000 $
b0110 &
b0000 '
#301
#302
b0111 "
b0001 #
b0001 $
b0111 &
b0001 '
#303
#304
b1000 "
b1000 #
b1000 $
b1000 &
b1000 '
#305
#306
b1001 "
b1001 #
b1001 $
b1001 &
b1001 '
#307
#308
b1010 "
b1000 #
b1000 $
b1010 &
b1000 '
#309
#310
b1011 "
b1001 #
b1001 $
b1011 &
b1001 '
#311
#312
b1100 "
b1000 #
b1000 $
b1100 &
b1000 '
#313
#314
b1101 "
b1001 #
b1001 $
b1101 &
b1001 '
#315
#316
b1110 "
b1000 #
b1000 $
b1110 &
b1000 '
#317
#318
b1111 "
b1001 #
b1001 $
b1111 &
b1001 '
#319
#320
b1010 !
b0000 "
b0000 #
b0000 $
b1010 %
b0000 &
b0000 '
#321
#322
b0001 "
b0001 &
#323
#324
b0010 "
b0010 #
b0010 $
b0010 &
b0010 '
#325
#326
b0011 "
b0011 &
#327
#328
b0100 "
b0000 #
b0000 $
b0100 &
b0000 '
#329
#330
b0101 "
b0101 &
#331
#332
b0110 "
b0010 #
b0010 $
b0110 &
b0010 '
#333
#334
b0111 "
b0111 &
#335
#336
b1000 "
b1000 #
b1000 $
b1000 &
b1000 '
#337
#338
b1001 "
b1001 &
#339
#340
b1010 "
b1010 #
b1010 $
b1010 &
b1010 '
#341
#342
b1011 "
b1011 &
#343
#344
b1100 "
b1000 #
b1000 $
b1100 &
b1000 '
#345
#346
b1101 "
b1101 &
#347
#348
b1110 "
b1010 #
b1010 $
b1110 &
b1010 '
#349
#350
b1111 "
b1111 &
#351
#352
b1011 !
b0000 "
b0000 #
b0000 $
b1011 %
b0000 &
b0000 '
#353
#354
b0001 "
b0001 #
b0001 $
b0001 &
b0001 '
#355
#356
b0010 "
b0010 #
b0010 $
b0010 &
b0010 '
#357
#358
b0011 "
b0011 #
b0011 $
b0011 &
b0011 '
#359
#360
b0100 "
b0000 #
b0000 $
b0100 &
b0000 '
#361
#362
b0101 "
b0001 #
b0001 $
b0101 &
b0001 '
#363
#364
b0110 "
b0010 #
b0010 $
b0110 &
b0010 '
#365
#366
b0111 "
b0011 #
b0011 $
b0111 &
b0011 '
#367
#368
b1000 "
b1000 #
b1000 $
b1000 &
b1000 '
#369
#370
b1001 "
b1001 #
b1001 $
b1001 &
b1001 '
#371
#372
b1010 "
b1010 #
b1010 $
b1010 &
b1010 '
#373
#374
b1011 "
b1011 #
b1011 $
b1011 &
b1011 '
#375
#376
b1100 "
b1000 #
b1000 $
b1100 &
b1000 '
#377
#378
b1101 "
b1001 #
b1001 $
b1101 &
b1001 '
#379
#380
b1110 "
b1010 #
b1010 $
b1110 &
b1010 '
#381
#382
b1111 "
b1011 #
b1011 $
b1111 &
b1011 '
#383
#384
b1100 !
b0000 "
b0000 #
b0000 $
b1100 %
b0000 &
b0000 '
#385
#386
b0001 "
b0001 &
#387
#388
b0010 "
b0010 &
#389
#390
b0011 "
b0011 &
#391
#392
b0100 "
b0100 #
b0100 $
b0100 &
b0100 '
#393
#394
b0101 "
b0101 &
#395
#396
b0110 "
b0110 &
#397
#398
b0111 "
b0111 &
#399
#400
b1000 "
b1000 #
b1000 $
b1000 &
b1000 '
#401
#402
b1001 "
b1001 &
#403
#404
b1010 "
b1010 &
#405
#406
b1011 "
b1011 &
#407
#408
b1100 "
b1100 #
b1100 $
b1100 &
b1100 '
#409
#410
b1101 "
b1101 &
#411
#412
b1110 "
b1110 &
#413
#414
b1111 "
b1111 &
#415
#416
b1101 !
b0000 "
b0000 #
b0000 $
b1101 %
b0000 &
b0000 '
#417
#418
b0001 "
b0001 #
b0001 $
b0001 &
b0001 '
#419
#420
b0010 "
b0000 #
b0000 $
b0010 &
b0000 '
#421
#422
b0011 "
b0001 #
b0001 $
b0011 &
b0001 '
#423
#424
b0100 "
b0100 #
b0100 $
b0100 &
b0100 '
#425
#426
b0101 "
b0101 #
b0101 $
b0101 &
b0101 '
#427
#428
b0110 "
b0100 #
b0100 $
b0110 &
b0100 '
#429
#430
b0111 "
b0101 #
b0101 $
b0111 &
b0101 '
#431
#432
b1000 "
b1000 #
b1000 $
b1000 &
b1000 '
#433
#434
b1001 "
b1001 #
b1001 $
b1001 &
b1001 '
#435
#436
b1010 "
b1000 #
b1000 $
b1010 &
b1000 '
#437
#438
b1011 "
b1001 #
b1001 $
b1011 &
b1001 '
#439
#440
b1100 "
b1100 #
b1100 $
b1100 &
b1100 '
#441
#442
b1101 "
b1101 #
b1101 $
b1101 &
b1101 '
#443
#444
b1110 "
b1100 #
b1100 $
b1110 &
b1100 '
#445
#446
b1111 "
b1101 #
b1101 $
b1111 &
b1101 '
#447
#448
b1110 !
b0000 "
b0000 #
b0000 $
b1110 %
b0000 &
b0000 '
#449
#450
b0001 "
b0001 &
#451
#452
b0010 "
b0010 #
b0010 $
b0010 &
b0010 '
#453
#454
b0011 "
b0011 &
#455
#456
b0100 "
b0100 #
b0100 $
b0100 &
b0100 '
#457
#458
b0101 "
b0101 &
#459
#460
b0110 "
b0110 #
b0110 $
b0110 &
b0110 '
#461
#462
b0111 "
b0111 &
#463
#464
b1000 "
b1000 #
b1000 $
b1000 &
b1000 '
#465
#466
b1001 "
b1001 &
#467
#468
b1010 "
b1010 #
b1010 $
b1010 &
b1010 '
#469
#470
b1011 "
b1011 &
#471
#472
b1100 "
b1100 #
b1100 $
b1100 &
b1100 '
#473
#474
b1101 "
b1101 &
#475
#476
b1110 "
b1110 #
b1110 $
b1110 &
b1110 '
#477
#478
b1111 "
b1111 &
#479
#480
b1111 !
b0000 "
b0000 #
b0000 $
b1111 %
b0000 &
b0000 '
#481
#482
b0001 "
b0001 #
b0001 $
b0001 &
b0001 '
#483
#484
b0010 "
b0010 #
b0010 $
b0010 &
b0010 '
#485
#486
b0011 "
b0011 #
b0011 $
b0011 &
b0011 '
#487
#488
b0100 "
b0100 #
b0100 $
b0100 &
b0100 '
#489
#490
b0101 "
b0101 #
b0101 $
b0101 &
b0101 '
#491
#492
b0110 "
b0110 #
b0110 $
b0110 &
b0110 '
#493
#494
b0111 "
b0111 #
b0111 $
b0111 &
b0111 '
#495
#496
b1000 "
b1000 #
b1000 $
b1000 &
b1000 '
#497
#498
b1001 "
b1001 #
b1001 $
b1001 &
b1001 '
#499
#500
b1010 "
b1010 #
b1010 $
b1010 &
b1010 '
#501
#502
b1011 "
b1011 #
b1011 $
b1011 &
b1011 '
#503
#504
b1100 "
b1100 #
b1100 $
b1100 &
b1100 '
#505
#506
b1101 "
b1101 #
b1101 $
b1101 &
b1101 '
#507
#508
b1110 "
b1110 #
b1110 $
b1110 &
b1110 '
#509
#510
b1111 "
b1111 #
b1111 $
b1111 &
b1111 '
