gdti5/alu_n_and2.vhdl
library ieee;
use ieee.std_logic_1164.all;

entity alu_n_and2 is
  generic(width: integer);
  port (
    a, b: in std_logic_vector(width-1 downto 0);
    y : out std_logic_vector(width-1 downto 0)
  );
end alu_n_and2;

architecture behav of alu_n_and2 is
begin
-- die schmarte lösung: 
--  y <= a and b;

-- loopy doopy
  gen: for i in 0 to width-1 generate
    y(i) <= a(i) and b(i); 
  end generate;
end architecture;

gdti5/alu_n_and2_tb.vhdl
library ieee;
use ieee.std_logic_1164.all;
use ieee.numeric_std.all;

entity alu_n_and2_tb is end alu_n_and2_tb;

architecture behav of alu_n_and2_tb is
  constant my_width : integer := 7;
  constant pow2_of_my_width : integer := 2**my_width - 1;
  component alu_n_and2
    generic (width : integer := 4);
    port ( a, b: in std_logic_vector(width-1 downto 0);
           y : out std_logic_vector(width-1 downto 0));
  end component;
  signal in1, in2, result : std_logic_vector(my_width-1 downto 0);
  signal expect : std_logic_vector(my_width-1 downto 0);
begin
  and2_0: alu_n_and2 generic map(width=>my_width) port map (a=>in1, b=>in2, y=>result);

  process
    variable cnt : integer:= 0;
    variable errcnt : integer:= 0;
    variable a,b,y : integer;
  begin
    for ai in 0 to pow2_of_my_width loop
      for bi in 0 to pow2_of_my_width loop
        in1 <= std_logic_vector(to_unsigned(ai, my_width));
        in2 <= std_logic_vector(to_unsigned(bi, my_width));
        for i in 0 to my_width-1 loop
          a := (ai / (2**i)) mod 2;
          b := (bi / (2**i)) mod 2;
    -- die folgende Zeile muss and/or/xor machen, je nachdem was geprueft werden soll
          if (a=1) and (b=1) then y:=1; else y:=0; end if;
          if y=1 then expect(i)<='1'; else expect(i)<='0'; end if;
        end loop;
        wait for 1 fs;
        if expect /= result then
          errcnt := errcnt + 1;
          report "falsch" severity error;
        end if;
        wait for 1 fs;
        cnt := cnt + 1;
      end loop;
    end loop;
    if errcnt=0 then
      report integer'image(cnt) & " tests done. Had no errors";
    else
      report "Had " & integer'image(errcnt) & " errors";
    end if;
    assert false report "end of test" severity note;
    wait; --  Wait forever; this will finish the simulation.
  end process;
end behav;

gdti5/out_alu_n_and2.vcd
$date
  Tue Dec  6 14:58:31 2022
$end
$version
  GHDL v0
$end
$timescale
  1 fs
$end
$scope module standard $end
$upscope $end
$scope module std_logic_1164 $end
$upscope $end
$scope module numeric_std $end
$upscope $end
$scope module alu_n_and2_tb $end
$var reg 7 ! in1[6:0] $end
$var reg 7 " in2[6:0] $end
$var reg 7 # result[6:0] $end
$var reg 7 $ expect[6:0] $end
$scope module and2_0 $end
$var reg 7 % a[6:0] $end
$var reg 7 & b[6:0] $end
$var reg 7 ' y[6:0] $end
$scope module gen(0) $end
$upscope $end
$scope module gen(1) $end
$upscope $end
$scope module gen(2) $end
$upscope $end
$scope module gen(3) $end
$upscope $end
$scope module gen(4) $end
$upscope $end
$scope module gen(5) $end
$upscope $end
$scope module gen(6) $end
$upscope $end
$upscope $end
$upscope $end
$enddefinitions $end
#0
b0000000 !
b0000000 "
b0000000 #
b0000000 $
b0000000 %
b0000000 &
b0000000 '
#1
#2
b0000001 "
b0000001 &
#3
#4
b0000010 "
b0000010 &
#5
#6
b0000011 "
b0000011 &
#7
#8
b0000100 "
b0000100 &
#9
#10
b0000101 "
b0000101 &
#11
#12
b0000110 "
b0000110 &
#13
#14
b0000111 "
b0000111 &
#15
#16
b0001000 "
b0001000 &
#17
#18
b0001001 "
b0001001 &
#19
#20
b0001010 "
b0001010 &
#21
#22
b0001011 "
b0001011 &
#23
#24
b0001100 "
b0001100 &
#25
#26
b0001101 "
b0001101 &
#27
#28
b0001110 "
b0001110 &
#29
#30
b0001111 "
b0001111 &
#31
#32
b0010000 "
b0010000 &
#33
#34
b0010001 "
b0010001 &
#35
#36
b0010010 "
b0010010 &
#37
#38
b0010011 "
b0010011 &
#39
#40
b0010100 "
b0010100 &
#41
#42
b0010101 "
b0010101 &
#43
#44
b0010110 "
b0010110 &
#45
#46
b0010111 "
b0010111 &
#47
#48
b0011000 "
b0011000 &
#49
#50
b0011001 "
b0011001 &
#51
#52
b0011010 "
b0011010 &
#53
#54
b0011011 "
b0011011 &
#55
#56
b0011100 "
b0011100 &
#57
#58
b0011101 "
b0011101 &
#59
#60
b0011110 "
b0011110 &
#61
#62
b0011111 "
b0011111 &
#63
#64
b0100000 "
b0100000 &
#65
#66
b0100001 "
b0100001 &
#67
#68
b0100010 "
b0100010 &
#69
#70
b0100011 "
b0100011 &
#71
#72
b0100100 "
b0100100 &
#73
#74
b0100101 "
b0100101 &
#75
#76
b0100110 "
b0100110 &
#77
#78
b0100111 "
b0100111 &
#79
#80
b0101000 "
b0101000 &
#81
#82
b0101001 "
b0101001 &
#83
#84
b0101010 "
b0101010 &
#85
#86
b0101011 "
b0101011 &
#87
#88
b0101100 "
b0101100 &
#89
#90
b0101101 "
b0101101 &
#91
#92
b0101110 "
b0101110 &
#93
#94
b0101111 "
b0101111 &
#95
#96
b0110000 "
b0110000 &
#97
#98
b0110001 "
b0110001 &
#99
#100
b0110010 "
b0110010 &
#101
#102
b0110011 "
b0110011 &
#103
#104
b0110100 "
b0110100 &
#105
#106
b0110101 "
b0110101 &
#107
#108
b0110110 "
b0110110 &
#109
#110
b0110111 "
b0110111 &
#111
#112
b0111000 "
b0111000 &
#113
#114
b0111001 "
b0111001 &
#115
#116
b0111010 "
b0111010 &
#117
#118
b0111011 "
b0111011 &
#119
#120
b0111100 "
b0111100 &
#121
#122
b0111101 "
b0111101 &
#123
#124
b0111110 "
b0111110 &
#125
#126
b0111111 "
b0111111 &
#127
#128
b1000000 "
b1000000 &
#129
#130
b1000001 "
b1000001 &
#131
#132
b1000010 "
b1000010 &
#133
#134
b1000011 "
b1000011 &
#135
#136
b1000100 "
b1000100 &
#137
#138
b1000101 "
b1000101 &
#139
#140
b1000110 "
b1000110 &
#141
#142
b1000111 "
b1000111 &
#143
#144
b1001000 "
b1001000 &
#145
#146
b1001001 "
b1001001 &
#147
#148
b1001010 "
b1001010 &
#149
#150
b1001011 "
b1001011 &
#151
#152
b1001100 "
b1001100 &
#153
#154
b1001101 "
b1001101 &
#155
#156
b1001110 "
b1001110 &
#157
#158
b1001111 "
b1001111 &
#159
#160
b1010000 "
b1010000 &
#161
#162
b1010001 "
b1010001 &
#163
#164
b1010010 "
b1010010 &
#165
#166
b1010011 "
b1010011 &
#167
#168
b1010100 "
b1010100 &
#169
#170
b1010101 "
b1010101 &
#171
#172
b1010110 "
b1010110 &
#173
#174
b1010111 "
b1010111 &
#175
#176
b1011000 "
b1011000 &
#177
#178
b1011001 "
b1011001 &
#179
#180
b1011010 "
b1011010 &
#181
#182
b1011011 "
b1011011 &
#183
#184
b1011100 "
b1011100 &
#185
#186
b1011101 "
b1011101 &
#187
#188
b1011110 "
b1011110 &
#189
#190
b1011111 "
b1011111 &
#191
#192
b1100000 "
b1100000 &
#193
#194
b1100001 "
b1100001 &
#195
#196
b1100010 "
b1100010 &
#197
#198
b1100011 "
b1100011 &
#199
#200
b1100100 "
b1100100 &
#201
#202
b1100101 "
b1100101 &
#203
#204
b1100110 "
b1100110 &
#205
#206
b1100111 "
b1100111 &
#207
#208
b1101000 "
b1101000 &
#209
#210
b1101001 "
b1101001 &
#211
#212
b1101010 "
b1101010 &
#213
#214
b1101011 "
b1101011 &
#215
#216
b1101100 "
b1101100 &
#217
#218
b1101101 "
b1101101 &
#219
#220
b1101110 "
b1101110 &
#221
#222
b1101111 "
b1101111 &
#223
#224
b1110000 "
b1110000 &
#225
#226
b1110001 "
b1110001 &
#227
#228
b1110010 "
b1110010 &
#229
#230
b1110011 "
b1110011 &
#231
#232
b1110100 "
b1110100 &
#233
#234
b1110101 "
b1110101 &
#235
#236
b1110110 "
b1110110 &
#237
#238
b1110111 "
b1110111 &
#239
#240
b1111000 "
b1111000 &
#241
#242
b1111001 "
b1111001 &
#243
#244
b1111010 "
b1111010 &
#245
#246
b1111011 "
b1111011 &
#247
#248
b1111100 "
b1111100 &
#249
#250
b1111101 "
b1111101 &
#251
#252
b1111110 "
b1111110 &
#253
#254
b1111111 "
b1111111 &
#255
#256
b0000001 !
b0000000 "
b0000001 %
b0000000 &
#257
#258
b0000001 "
b0000001 #
b0000001 $
b0000001 &
b0000001 '
#259
#260
b0000010 "
b0000000 #
b0000000 $
b0000010 &
b0000000 '
#261
#262
b0000011 "
b0000001 #
b0000001 $
b0000011 &
b0000001 '
#263
#264
b0000100 "
b0000000 #
b0000000 $
b0000100 &
b0000000 '
#265
#266
b0000101 "
b0000001 #
b0000001 $
b0000101 &
b0000001 '
#267
#268
b0000110 "
b0000000 #
b0000000 $
b0000110 &
b0000000 '
#269
#270
b0000111 "
b0000001 #
b0000001 $
b0000111 &
b0000001 '
#271
#272
b0001000 "
b0000000 #
b0000000 $
b0001000 &
b0000000 '
#273
#274
b0001001 "
b0000001 #
b0000001 $
b0001001 &
b0000001 '
#275
#276
b0001010 "
b0000000 #
b0000000 $
b0001010 &
b0000000 '
#277
#278
b0001011 "
b0000001 #
b0000001 $
b0001011 &
b0000001 '
#279
#280
b0001100 "
b0000000 #
b0000000 $
b0001100 &
b0000000 '
#281
#282
b0001101 "
b0000001 #
b0000001 $
b0001101 &
b0000001 '
#283
#284
b0001110 "
b0000000 #
b0000000 $
b0001110 &
b0000000 '
#285
#286
b0001111 "
b0000001 #
b0000001 $
b0001111 &
b0000001 '
#287
#288
b0010000 "
b0000000 #
b0000000 $
b0010000 &
b0000000 '
#289
#290
b0010001 "
b0000001 #
b0000001 $
b0010001 &
b0000001 '
#291
#292
b0010010 "
b0000000 #
b0000000 $
b0010010 &
b0000000 '
#293
#294
b0010011 "
b0000001 #
b0000001 $
b0010011 &
b0000001 '
#295
#296
b0010100 "
b0000000 #
b0000000 $
b0010100 &
b0000000 '
#297
#298
b0010101 "
b0000001 #
b0000001 $
b0010101 &
b0000001 '
#299
#300
b0010110 "
b0000000 #
b0000000 $
b0010110 &
b0000000 '
#301
#302
b0010111 "
b0000001 #
b0000001 $
b0010111 &
b0000001 '
#303
#304
b0011000 "
b0000000 #
b0000000 $
b0011000 &
b0000000 '
#305
#306
b0011001 "
b0000001 #
b0000001 $
b0011001 &
b0000001 '
#307
#308
b0011010 "
b0000000 #
b0000000 $
b0011010 &
b0000000 '
#309
#310
b0011011 "
b0000001 #
b0000001 $
b0011011 &
b0000001 '
#311
#312
b0011100 "
b0000000 #
b0000000 $
b0011100 &
b0000000 '
#313
#314
b0011101 "
b0000001 #
b0000001 $
b0011101 &
b0000001 '
#315
#316
b0011110 "
b0000000 #
b0000000 $
b0011110 &
b0000000 '
#317
#318
b0011111 "
b0000001 #
b0000001 $
b0011111 &
b0000001 '
#319
#320
b0100000 "
b0000000 #
b0000000 $
b0100000 &
b0000000 '
#321
#322
b0100001 "
b0000001 #
b0000001 $
b0100001 &
b0000001 '
#323
#324
b0100010 "
b0000000 #
b0000000 $
b0100010 &
b0000000 '
#325
#326
b0100011 "
b0000001 #
b0000001 $
b0100011 &
b0000001 '
#327
#328
b0100100 "
b0000000 #
b0000000 $
b0100100 &
b0000000 '
#329
#330
b0100101 "
b0000001 #
b0000001 $
b0100101 &
b0000001 '
#331
#332
b0100110 "
b0000000 #
b0000000 $
b0100110 &
b0000000 '
#333
#334
b0100111 "
b0000001 #
b0000001 $
b0100111 &
b0000001 '
#335
#336
b0101000 "
b0000000 #
b0000000 $
b0101000 &
b0000000 '
#337
#338
b0101001 "
b0000001 #
b0000001 $
b0101001 &
b0000001 '
#339
#340
b0101010 "
b0000000 #
b0000000 $
b0101010 &
b0000000 '
#341
#342
b0101011 "
b0000001 #
b0000001 $
b0101011 &
b0000001 '
#343
#344
b0101100 "
b0000000 #
b0000000 $
b0101100 &
b0000000 '
#345
#346
b0101101 "
b0000001 #
b0000001 $
b0101101 &
b0000001 '
#347
#348
b0101110 "
b0000000 #
b0000000 $
b0101110 &
b0000000 '
#349
#350
b0101111 "
b0000001 #
b0000001 $
b0101111 &
b0000001 '
#351
#352
b0110000 "
b0000000 #
b0000000 $
b0110000 &
b0000000 '
#353
#354
b0110001 "
b0000001 #
b0000001 $
b0110001 &
b0000001 '
#355
#356
b0110010 "
b0000000 #
b0000000 $
b0110010 &
b0000000 '
#357
#358
b0110011 "
b0000001 #
b0000001 $
b0110011 &
b0000001 '
#359
#360
b0110100 "
b0000000 #
b0000000 $
b0110100 &
b0000000 '
#361
#362
b0110101 "
b0000001 #
b0000001 $
b0110101 &
b0000001 '
#363
#364
b0110110 "
b0000000 #
b0000000 $
b0110110 &
b0000000 '
#365
#366
b0110111 "
b0000001 #
b0000001 $
b0110111 &
b0000001 '
#367
#368
b0111000 "
b0000000 #
b0000000 $
b0111000 &
b0000000 '
#369
#370
b0111001 "
b0000001 #
b0000001 $
b0111001 &
b0000001 '
#371
#372
b0111010 "
b0000000 #
b0000000 $
b0111010 &
b0000000 '
#373
#374
b0111011 "
b0000001 #
b0000001 $
b0111011 &
b0000001 '
#375
#376
b0111100 "
b0000000 #
b0000000 $
b0111100 &
b0000000 '
#377
#378
b0111101 "
b0000001 #
b0000001 $
b0111101 &
b0000001 '
#379
#380
b0111110 "
b0000000 #
b0000000 $
b0111110 &
b0000000 '
#381
#382
b0111111 "
b0000001 #
b0000001 $
b0111111 &
b0000001 '
#383
#384
b1000000 "
b0000000 #
b0000000 $
b1000000 &
b0000000 '
#385
#386
b1000001 "
b0000001 #
b0000001 $
b1000001 &
b0000001 '
#387
#388
b1000010 "
b0000000 #
b0000000 $
b1000010 &
b0000000 '
#389
#390
b1000011 "
b0000001 #
b0000001 $
b1000011 &
b0000001 '
#391
#392
b1000100 "
b0000000 #
b0000000 $
b1000100 &
b0000000 '
#393
#394
b1000101 "
b0000001 #
b0000001 $
b1000101 &
b0000001 '
#395
#396
b1000110 "
b0000000 #
b0000000 $
b1000110 &
b0000000 '
#397
#398
b1000111 "
b0000001 #
b0000001 $
b1000111 &
b0000001 '
#399
#400
b1001000 "
b0000000 #
b0000000 $
b1001000 &
b0000000 '
#401
#402
b1001001 "
b0000001 #
b0000001 $
b1001001 &
b0000001 '
#403
#404
b1001010 "
b0000000 #
b0000000 $
b1001010 &
b0000000 '
#405
#406
b1001011 "
b0000001 #
b0000001 $
b1001011 &
b0000001 '
#407
#408
b1001100 "
b0000000 #
b0000000 $
b1001100 &
b0000000 '
#409
#410
b1001101 "
b0000001 #
b0000001 $
b1001101 &
b0000001 '
#411
#412
b1001110 "
b0000000 #
b0000000 $
b1001110 &
b0000000 '
#413
#414
b1001111 "
b0000001 #
b0000001 $
b1001111 &
b0000001 '
#415
#416
b1010000 "
b0000000 #
b0000000 $
b1010000 &
b0000000 '
#417
#418
b1010001 "
b0000001 #
b0000001 $
b1010001 &
b0000001 '
#419
#420
b1010010 "
b0000000 #
b0000000 $
b1010010 &
b0000000 '
#421
#422
b1010011 "
b0000001 #
b0000001 $
b1010011 &
b0000001 '
#423
#424
b1010100 "
b0000000 #
b0000000 $
b1010100 &
b0000000 '
#425
#426
b1010101 "
b0000001 #
b0000001 $
b1010101 &
b0000001 '
#427
#428
b1010110 "
b0000000 #
b0000000 $
b1010110 &
b0000000 '
#429
#430
b1010111 "
b0000001 #
b0000001 $
b1010111 &
b0000001 '
#431
#432
b1011000 "
b0000000 #
b0000000 $
b1011000 &
b0000000 '
#433
#434
b1011001 "
b0000001 #
b0000001 $
b1011001 &
b0000001 '
#435
#436
b1011010 "
b0000000 #
b0000000 $
b1011010 &
b0000000 '
#437
#438
b1011011 "
b0000001 #
b0000001 $
b1011011 &
b0000001 '
#439
#440
b1011100 "
b0000000 #
b0000000 $
b1011100 &
b0000000 '
#441
#442
b1011101 "
b0000001 #
b0000001 $
b1011101 &
b0000001 '
#443
#444
b1011110 "
b0000000 #
b0000000 $
b1011110 &
b0000000 '
#445
#446
b1011111 "
b0000001 #
b0000001 $
b1011111 &
b0000001 '
#447
#448
b1100000 "
b0000000 #
b0000000 $
b1100000 &
b0000000 '
#449
#450
b1100001 "
b0000001 #
b0000001 $
b1100001 &
b0000001 '
#451
#452
b1100010 "
b0000000 #
b0000000 $
b1100010 &
b0000000 '
#453
#454
b1100011 "
b0000001 #
b0000001 $
b1100011 &
b0000001 '
#455
#456
b1100100 "
b0000000 #
b0000000 $
b1100100 &
b0000000 '
#457
#458
b1100101 "
b0000001 #
b0000001 $
b1100101 &
b0000001 '
#459
#460
b1100110 "
b0000000 #
b0000000 $
b1100110 &
b0000000 '
#461
#462
b1100111 "
b0000001 #
b0000001 $
b1100111 &
b0000001 '
#463
#464
b1101000 "
b0000000 #
b0000000 $
b1101000 &
b0000000 '
#465
#466
b1101001 "
b0000001 #
b0000001 $
b1101001 &
b0000001 '
#467
#468
b1101010 "
b0000000 #
b0000000 $
b1101010 &
b0000000 '
#469
#470
b1101011 "
b0000001 #
b0000001 $
b1101011 &
b0000001 '
#471
#472
b1101100 "
b0000000 #
b0000000 $
b1101100 &
b0000000 '
#473
#474
b1101101 "
b0000001 #
b0000001 $
b1101101 &
b0000001 '
#475
#476
b1101110 "
b0000000 #
b0000000 $
b1101110 &
b0000000 '
#477
#478
b1101111 "
b0000001 #
b0000001 $
b1101111 &
b0000001 '
#479
#480
b1110000 "
b0000000 #
b0000000 $
b1110000 &
b0000000 '
#481
#482
b1110001 "
b0000001 #
b0000001 $
b1110001 &
b0000001 '
#483
#484
b1110010 "
b0000000 #
b0000000 $
b1110010 &
b0000000 '
#485
#486
b1110011 "
b0000001 #
b0000001 $
b1110011 &
b0000001 '
#487
#488
b1110100 "
b0000000 #
b0000000 $
b1110100 &
b0000000 '
#489
#490
b1110101 "
b0000001 #
b0000001 $
b1110101 &
b0000001 '
#491
#492
b1110110 "
b0000000 #
b0000000 $
b1110110 &
b0000000 '
#493
#494
b1110111 "
b0000001 #
b0000001 $
b1110111 &
b0000001 '
#495
#496
b1111000 "
b0000000 #
b0000000 $
b1111000 &
b0000000 '
#497
#498
b1111001 "
b0000001 #
b0000001 $
b1111001 &
b0000001 '
#499
#500
b1111010 "
b0000000 #
b0000000 $
b1111010 &
b0000000 '
#501
#502
b1111011 "
b0000001 #
b0000001 $
b1111011 &
b0000001 '
#503
#504
b1111100 "
b0000000 #
b0000000 $
b1111100 &
b0000000 '
#505
#506
b1111101 "
b0000001 #
b0000001 $
b1111101 &
b0000001 '
#507
#508
b1111110 "
b0000000 #
b0000000 $
b1111110 &
b0000000 '
#509
#510
b1111111 "
b0000001 #
b0000001 $
b1111111 &
b0000001 '
#511
#512
b0000010 !
b0000000 "
b0000000 #
b0000000 $
b0000010 %
b0000000 &
b0000000 '
#513
#514
b0000001 "
b0000001 &
#515
#516
b0000010 "
b0000010 #
b0000010 $
b0000010 &
b0000010 '
#517
#518
b0000011 "
b0000011 &
#519
#520
b0000100 "
b0000000 #
b0000000 $
b0000100 &
b0000000 '
#521
#522
b0000101 "
b0000101 &
#523
#524
b0000110 "
b0000010 #
b0000010 $
b0000110 &
b0000010 '
#525
#526
b0000111 "
b0000111 &
#527
#528
b0001000 "
b0000000 #
b0000000 $
b0001000 &
b0000000 '
#529
#530
b0001001 "
b0001001 &
#531
#532
b0001010 "
b0000010 #
b0000010 $
b0001010 &
b0000010 '
#533
#534
b0001011 "
b0001011 &
#535
#536
b0001100 "
b0000000 #
b0000000 $
b0001100 &
b0000000 '
#537
#538
b0001101 "
b0001101 &
#539
#540
b0001110 "
b0000010 #
b0000010 $
b0001110 &
b0000010 '
#541
#542
b0001111 "
b0001111 &
#543
#544
b0010000 "
b0000000 #
b0000000 $
b0010000 &
b0000000 '
#545
#546
b0010001 "
b0010001 &
#547
#548
b0010010 "
b0000010 #
b0000010 $
b0010010 &
b0000010 '
#549
#550
b0010011 "
b0010011 &
#551
#552
b0010100 "
b0000000 #
b0000000 $
b0010100 &
b0000000 '
#553
#554
b0010101 "
b0010101 &
#555
#556
b0010110 "
b0000010 #
b0000010 $
b0010110 &
b0000010 '
#557
#558
b0010111 "
b0010111 &
#559
#560
b0011000 "
b0000000 #
b0000000 $
b0011000 &
b0000000 '
#561
#562
b0011001 "
b0011001 &
#563
#564
b0011010 "
b0000010 #
b0000010 $
b0011010 &
b0000010 '
#565
#566
b0011011 "
b0011011 &
#567
#568
b0011100 "
b0000000 #
b0000000 $
b0011100 &
b0000000 '
#569
#570
b0011101 "
b0011101 &
#571
#572
b0011110 "
b0000010 #
b0000010 $
b0011110 &
b0000010 '
#573
#574
b0011111 "
b0011111 &
#575
#576
b0100000 "
b0000000 #
b0000000 $
b0100000 &
b0000000 '
#577
#578
b0100001 "
b0100001 &
#579
#580
b0100010 "
b0000010 #
b0000010 $
b0100010 &
b0000010 '
#581
#582
b0100011 "
b0100011 &
#583
#584
b0100100 "
b0000000 #
b0000000 $
b0100100 &
b0000000 '
#585
#586
b0100101 "
b0100101 &
#587
#588
b0100110 "
b0000010 #
b0000010 $
b0100110 &
b0000010 '
#589
#590
b0100111 "
b0100111 &
#591
#592
b0101000 "
b0000000 #
b0000000 $
b0101000 &
b0000000 '
#593
#594
b0101001 "
b0101001 &
#595
#596
b0101010 "
b0000010 #
b0000010 $
b0101010 &
b0000010 '
#597
#598
b0101011 "
b0101011 &
#599
#600
b0101100 "
b0000000 #
b0000000 $
b0101100 &
b0000000 '
#601
#602
b0101101 "
b0101101 &
#603
#604
b0101110 "
b0000010 #
b0000010 $
b0101110 &
b0000010 '
#605
#606
b0101111 "
b0101111 &
#607
#608
b0110000 "
b0000000 #
b0000000 $
b0110000 &
b0000000 '
#609
#610
b0110001 "
b0110001 &
#611
#612
b0110010 "
b0000010 #
b0000010 $
b0110010 &
b0000010 '
#613
#614
b0110011 "
b0110011 &
#615
#616
b0110100 "
b0000000 #
b0000000 $
b0110100 &
b0000000 '
#617
#618
b0110101 "
b0110101 &
#619
#620
b0110110 "
b0000010 #
b0000010 $
b0110110 &
b0000010 '
#621
#622
b0110111 "
b0110111 &
#623
#624
b0111000 "
b0000000 #
b0000000 $
b0111000 &
b0000000 '
#625
#626
b0111001 "
b0111001 &
#627
#628
b0111010 "
b0000010 #
b0000010 $
b0111010 &
b0000010 '
#629
#630
b0111011 "
b0111011 &
#631
#632
b0111100 "
b0000000 #
b0000000 $
b0111100 &
b0000000 '
#633
#634
b0111101 "
b0111101 &
#635
#636
b0111110 "
b0000010 #
b0000010 $
b0111110 &
b0000010 '
#637
#638
b0111111 "
b0111111 &
#639
#640
b1000000 "
b0000000 #
b0000000 $
b1000000 &
b0000000 '
#641
#642
b1000001 "
b1000001 &
#643
#644
b1000010 "
b0000010 #
b0000010 $
b1000010 &
b0000010 '
#645
#646
b1000011 "
b1000011 &
#647
#648
b1000100 "
b0000000 #
b0000000 $
b1000100 &
b0000000 '
#649
#650
b1000101 "
b1000101 &
#651
#652
b1000110 "
b0000010 #
b0000010 $
b1000110 &
b0000010 '
#653
#654
b1000111 "
b1000111 &
#655
#656
b1001000 "
b0000000 #
b0000000 $
b1001000 &
b0000000 '
#657
#658
b1001001 "
b1001001 &
#659
#660
b1001010 "
b0000010 #
b0000010 $
b1001010 &
b0000010 '
#661
#662
b1001011 "
b1001011 &
#663
#664
b1001100 "
b0000000 #
b0000000 $
b1001100 &
b0000000 '
#665
#666
b1001101 "
b1001101 &
#667
#668
b1001110 "
b0000010 #
b0000010 $
b1001110 &
b0000010 '
#669
#670
b1001111 "
b1001111 &
#671
#672
b1010000 "
b0000000 #
b0000000 $
b1010000 &
b0000000 '
#673
#674
b1010001 "
b1010001 &
#675
#676
b1010010 "
b0000010 #
b0000010 $
b1010010 &
b0000010 '
#677
#678
b1010011 "
b1010011 &
#679
#680
b1010100 "
b0000000 #
b0000000 $
b1010100 &
b0000000 '
#681
#682
b1010101 "
b1010101 &
#683
#684
b1010110 "
b0000010 #
b0000010 $
b1010110 &
b0000010 '
#685
#686
b1010111 "
b1010111 &
#687
#688
b1011000 "
b0000000 #
b0000000 $
b1011000 &
b0000000 '
#689
#690
b1011001 "
b1011001 &
#691
#692
b1011010 "
b0000010 #
b0000010 $
b1011010 &
b0000010 '
#693
#694
b1011011 "
b1011011 &
#695
#696
b1011100 "
b0000000 #
b0000000 $
b1011100 &
b0000000 '
#697
#698
b1011101 "
b1011101 &
#699
#700
b1011110 "
b0000010 #
b0000010 $
b1011110 &
b0000010 '
#701
#702
b1011111 "
b1011111 &
#703
#704
b1100000 "
b0000000 #
b0000000 $
b1100000 &
b0000000 '
#705
#706
b1100001 "
b1100001 &
#707
#708
b1100010 "
b0000010 #
b0000010 $
b1100010 &
b0000010 '
#709
#710
b1100011 "
b1100011 &
#711
#712
b1100100 "
b0000000 #
b0000000 $
b1100100 &
b0000000 '
#713
#714
b1100101 "
b1100101 &
#715
#716
b1100110 "
b0000010 #
b0000010 $
b1100110 &
b0000010 '
#717
#718
b1100111 "
b1100111 &
#719
#720
b1101000 "
b0000000 #
b0000000 $
b1101000 &
b0000000 '
#721
#722
b1101001 "
b1101001 &
#723
#724
b1101010 "
b0000010 #
b0000010 $
b1101010 &
b0000010 '
#725
#726
b1101011 "
b1101011 &
#727
#728
b1101100 "
b0000000 #
b0000000 $
b1101100 &
b0000000 '
#729
#730
b1101101 "
b1101101 &
#731
#732
b1101110 "
b0000010 #
b0000010 $
b1101110 &
b0000010 '
#733
#734
b1101111 "
b1101111 &
#735
#736
b1110000 "
b0000000 #
b0000000 $
b1110000 &
b0000000 '
#737
#738
b1110001 "
b1110001 &
#739
#740
b1110010 "
b0000010 #
b0000010 $
b1110010 &
b0000010 '
#741
#742
b1110011 "
b1110011 &
#743
#744
b1110100 "
b0000000 #
b0000000 $
b1110100 &
b0000000 '
#745
#746
b1110101 "
b1110101 &
#747
#748
b1110110 "
b0000010 #
b0000010 $
b1110110 &
b0000010 '
#749
#750
b1110111 "
b1110111 &
#751
#752
b1111000 "
b0000000 #
b0000000 $
b1111000 &
b0000000 '
#753
#754
b1111001 "
b1111001 &
#755
#756
b1111010 "
b0000010 #
b0000010 $
b1111010 &
b0000010 '
#757
#758
b1111011 "
b1111011 &
#759
#760
b1111100 "
b0000000 #
b0000000 $
b1111100 &
b0000000 '
#761
#762
b1111101 "
b1111101 &
#763
#764
b1111110 "
b0000010 #
b0000010 $
b1111110 &
b0000010 '
#765
#766
b1111111 "
b1111111 &
#767
#768
b0000011 !
b0000000 "
b0000000 #
b0000000 $
b0000011 %
b0000000 &
b0000000 '
#769
#770
b0000001 "
b0000001 #
b0000001 $
b0000001 &
b0000001 '
#771
#772
b0000010 "
b0000010 #
b0000010 $
b0000010 &
b0000010 '
#773
#774
b0000011 "
b0000011 #
b0000011 $
b0000011 &
b0000011 '
#775
#776
b0000100 "
b0000000 #
b0000000 $
b0000100 &
b0000000 '
#777
#778
b0000101 "
b0000001 #
b0000001 $
b0000101 &
b0000001 '
#779
#780
b0000110 "
b0000010 #
b0000010 $
b0000110 &
b0000010 '
#781
#782
b0000111 "
b0000011 #
b0000011 $
b0000111 &
b0000011 '
#783
#784
b0001000 "
b0000000 #
b0000000 $
b0001000 &
b0000000 '
#785
#786
b0001001 "
b0000001 #
b0000001 $
b0001001 &
b0000001 '
#787
#788
b0001010 "
b0000010 #
b0000010 $
b0001010 &
b0000010 '
#789
#790
b0001011 "
b0000011 #
b0000011 $
b0001011 &
b0000011 '
#791
#792
b0001100 "
b0000000 #
b0000000 $
b0001100 &
b0000000 '
#793
#794
b0001101 "
b0000001 #
b0000001 $
b0001101 &
b0000001 '
#795
#796
b0001110 "
b0000010 #
b0000010 $
b0001110 &
b0000010 '
#797
#798
b0001111 "
b0000011 #
b0000011 $
b0001111 &
b0000011 '
#799
#800
b0010000 "
b0000000 #
b0000000 $
b0010000 &
b0000000 '
#801
#802
b0010001 "
b0000001 #
b0000001 $
b0010001 &
b0000001 '
#803
#804
b0010010 "
b0000010 #
b0000010 $
b0010010 &
b0000010 '
#805
#806
b0010011 "
b0000011 #
b0000011 $
b0010011 &
b0000011 '
#807
#808
b0010100 "
b0000000 #
b0000000 $
b0010100 &
b0000000 '
#809
#810
b0010101 "
b0000001 #
b0000001 $
b0010101 &
b0000001 '
#811
#812
b0010110 "
b0000010 #
b0000010 $
b0010110 &
b0000010 '
#813
#814
b0010111 "
b0000011 #
b0000011 $
b0010111 &
b0000011 '
#815
#816
b0011000 "
b0000000 #
b0000000 $
b0011000 &
b0000000 '
#817
#818
b0011001 "
b0000001 #
b0000001 $
b0011001 &
b0000001 '
#819
#820
b0011010 "
b0000010 #
b0000010 $
b0011010 &
b0000010 '
#821
#822
b0011011 "
b0000011 #
b0000011 $
b0011011 &
b0000011 '
#823
#824
b0011100 "
b0000000 #
b0000000 $
b0011100 &
b0000000 '
#825
#826
b0011101 "
b0000001 #
b0000001 $
b0011101 &
b0000001 '
#827
#828
b0011110 "
b0000010 #
b0000010 $
b0011110 &
b0000010 '
#829
#830
b0011111 "
b0000011 #
b0000011 $
b0011111 &
b0000011 '
#831
#832
b0100000 "
b0000000 #
b0000000 $
b0100000 &
b0000000 '
#833
#834
b0100001 "
b0000001 #
b0000001 $
b0100001 &
b0000001 '
#835
#836
b0100010 "
b0000010 #
b0000010 $
b0100010 &
b0000010 '
#837
#838
b0100011 "
b0000011 #
b0000011 $
b0100011 &
b0000011 '
#839
#840
b0100100 "
b0000000 #
b0000000 $
b0100100 &
b0000000 '
#841
#842
b0100101 "
b0000001 #
b0000001 $
b0100101 &
b0000001 '
#843
#844
b0100110 "
b0000010 #
b0000010 $
b0100110 &
b0000010 '
#845
#846
b0100111 "
b0000011 #
b0000011 $
b0100111 &
b0000011 '
#847
#848
b0101000 "
b0000000 #
b0000000 $
b0101000 &
b0000000 '
#849
#850
b0101001 "
b0000001 #
b0000001 $
b0101001 &
b0000001 '
#851
