gdti6/rs_latch.vhdl
library ieee;
use ieee.std_logic_1164.all;

entity rs_latch is
  port (
    r, s : in std_logic;
    y, not_y : out std_logic
  );
end rs_latch;


architecture behav of rs_latch is
signal q : std_logic;
signal not_q : std_logic;
  begin

  q <= r nor not_q;
  not_q <= s nor q;

  not_y <= not_q;
  y <= q;

end architecture;

gdti6/d_latch.vhdl
library ieee;
use ieee.std_logic_1164.all;

entity d_latch 
is port(
  d, clk : in std_logic;
  y, not_y : out std_logic
);
end d_latch;

architecture behav of d_latch is
  component rs_latch is port(
    r, s : in std_logic;
    y, not_y : out std_logic
  ); end component;
  signal r, s: std_logic;
begin 
  latch: rs_latch port map (r,s,y, not_y);
  r <= (not d) and clk;
  s <= d and clk;
end behav;

gdti6/d_ms_ff.vhdl
library ieee;
use ieee.std_logic_1164.all;

entity d_ms_ff 
is port(
  d, clk : in std_logic;
  y, not_y : out std_logic
);
end d_ms_ff;

architecture behav of d_ms_ff is
component d_latch is 
port(
  d, clk : in std_logic;
  y, not_y : out std_logic
);
end component;
signal clk1, din, yout: std_logic;
begin
  latch_0: d_latch port map(d, clk, y => yout);
  latch_1: d_latch port map(d => din, clk => clk1, y => y, not_y => not_y);
  
  din <= yout;
  clk1 <= not clk;
end behav;

gdti6/d_ms_ff_tb.vhdl
library ieee;
use ieee.std_logic_1164.all;

entity d_ms_ff_tb is end d_ms_ff_tb;

architecture behav of d_ms_ff_tb is
  component d_ms_ff is port(
    d, clk : in std_logic;
    y, not_y : out std_logic
  ); end component;
  signal d,clk, y,not_y : std_logic;
  signal expect_y,expect_not_y : std_logic;
begin
  d_ms_ff_0: d_ms_ff port map (d, clk,  y, not_y);

  process
    type testvec is record  d,clk,y,ny : integer; end record;
    type testarray is array (natural range <>) of testvec;
    constant testlist : testarray := (
       (0,1, 2,2),
       (0,0, 0,1),
       (1,0, 0,1),
       (1,1, 0,1),
       (1,0, 1,0),
       (1,1, 1,0),
       (1,0, 1,0),
       (0,1, 1,0),
       (0,0, 0,1),
       (0,1, 0,1),
       (0,0, 0,1),
       (1,0, 0,1)
    );
    variable errcnt : integer := 0;
  begin
    for i in testlist'range loop
      if testlist(i).d=1 then d<='1'; else d<='0'; end if;
      if testlist(i).clk=1 then clk<='1'; else clk<='0'; end if;
      if testlist(i).y=1 then expect_y<='1'; else expect_y<='0'; end if;
      if testlist(i).ny=1 then expect_not_y<='1'; else expect_not_y<='0'; end if;
      wait for 1 fs;
      if testlist(i).y/=2 then
        if y/=expect_y  or  not_y/=expect_not_y then
          report "clocked d ms_ff behaved wrongly" severity error;
          errcnt := errcnt + 1;
        end if;
      end if;
    end loop;
    if errcnt=0 then
      report "clocked d ms_ff OK";
    else
      report "clocked d ms_ff test FAILED";
    end if;
    report "end of test.";
    wait; --  Wait forever; this will finish the simulation.
  end process;
end behav;

gdti6/out_d_ms_ff.vcd
$date
  Tue Dec 13 15:24:27 2022
$end
$version
  GHDL v0
$end
$timescale
  1 fs
$end
$scope module standard $end
$upscope $end
$scope module std_logic_1164 $end
$upscope $end
$scope module d_ms_ff_tb $end
$var reg 1 ! d $end
$var reg 1 " clk $end
$var reg 1 # y $end
$var reg 1 $ not_y $end
$var reg 1 % expect_y $end
$var reg 1 & expect_not_y $end
$scope module d_ms_ff_0 $end
$var reg 1 ' d $end
$var reg 1 ( clk $end
$var reg 1 ) y $end
$var reg 1 * not_y $end
$var reg 1 + clk1 $end
$var reg 1 , din $end
$var reg 1 - yout $end
$scope module latch_0 $end
$var reg 1 . d $end
$var reg 1 / clk $end
$var reg 1 0 y $end
$var reg 1 1 not_y $end
$var reg 1 2 r $end
$var reg 1 3 s $end
$scope module latch $end
$var reg 1 4 r $end
$var reg 1 5 s $end
$var reg 1 6 y $end
$var reg 1 7 not_y $end
$var reg 1 8 q $end
$var reg 1 9 not_q $end
$upscope $end
$upscope $end
$scope module latch_1 $end
$var reg 1 : d $end
$var reg 1 ; clk $end
$var reg 1 < y $end
$var reg 1 = not_y $end
$var reg 1 > r $end
$var reg 1 ? s $end
$scope module latch $end
$var reg 1 @ r $end
$var reg 1 A s $end
$var reg 1 B y $end
$var reg 1 C not_y $end
$var reg 1 D q $end
$var reg 1 E not_q $end
$upscope $end
$upscope $end
$upscope $end
$upscope $end
$enddefinitions $end
#0
0!
1"
U#
U$
0%
0&
0'
1(
U)
U*
0+
0,
0-
0.
1/
00
11
12
03
14
05
06
17
08
19
0:
0;
U<
U=
0>
0?
0@
0A
UB
UC
UD
UE
#1
0"
0#
1$
1&
0(
0)
1*
1+
0/
02
04
1;
0<
1=
1>
1@
0B
1C
0D
1E
#2
1!
1'
1.
#3
1"
1(
0+
1,
1-
1/
10
01
13
15
16
07
18
09
1:
0;
0>
0@
#4
0"
1#
0$
1%
0&
0(
1)
0*
1+
0/
03
05
1;
1<
0=
1?
1A
1B
0C
1D
0E
#5
1"
1(
0+
1/
13
15
0;
0?
0A
#6
0"
0(
1+
0/
03
05
1;
1?
1A
#7
0!
1"
0'
1(
0+
0,
0-
0.
1/
00
11
12
14
06
17
08
19
0:
0;
0?
0A
#8
0"
0#
1$
0%
1&
0(
0)
1*
1+
0/
02
04
1;
0<
1=
1>
1@
0B
1C
0D
1E
#9
1"
1(
0+
1/
12
14
0;
0>
0@
#10
0"
0(
1+
0/
02
04
1;
1>
1@
#11
1!
1'
1.
